Workbook

Sheet Propostas de Alteração
A1: ID | B1: N.º PA | C1: Data Entrada | D1: Versão | E1: Partido | F1: Deputado/Proponente | G1: Artigo Alterado | H1: Tipo de PA | I1: Tema | J1: Área Governativa | K1: Ministério | L1: Descrição Sumária | M1: Impacto Receita (€) | N1: Impacto Despesa (€) | O1: Fonte da Estimativa | P1: Medida Anunciada (S/N) | Q1: Relevância | R1: Necessita Análise Jurídica (S/N) | S1: Estado | T1: Resultado Votação | U1: Sentido de Voto | V1: Data Votação | W1: Observações | X1: Tema AR | Y1: Incide | Z1: Tipo (AR) | AA1: Estado (AR) | AB1: Avocação a Plenário | AC1: Parte | AD1: N.º de votações | AE1: ID AR | AF1: Ligação AR | AG1: PDF | AH1: Primeira captura | AI1: Última captura | AJ1: Ausente da fonte
A2: 1 | B2: 1C-1 | C2: 45959.375 | D2: Original | E2: PSD | F2: Paulo Neves; Pedro Coelho; Vânia Jesus | G2: Art. 62.º (substituição) | L2: N.º1, N.º10, Artigo 36.º-A do EBF | S2: Aprovado(a) em Comissão | T2: Aprovada | U2: Favor: PSD, CH, PS, IL, CDS-PP; Contra: L, PCP, BE, PAN | V2: 45981 | W2: AR: https://www.parlamento.pt/OrcamentoEstado/Paginas/DetalhePropostaAlteracao.aspx?BID=23194 PDF: https://app.parlamento.pt/webutils/docs/doc.pdf?path=6148523063484d364c793942556b356c6443397a6158526c63793959566b6c4a544556484c3039464c7a49774d6a59794d4449314d5441774f5339515153396b5a6a45794e6a41315a5330324e6d5a6d4c5451335a445174596a677a4e69316a4e4751794e546b304e6d4a6b5a4445756347526d&Fich=df12605e-66ff-47d4-b836-c4d25946bdd1.pdf&Inline=true | X2: Orçamento, Finanças e Administração Pública | Y2: Articulado | Z2: Substituição | AA2: Aprovado(a) em Comissão | AC2: 1 | AD2: 1 | AE2: 23194 | AF2: https://www.parlamento.pt/OrcamentoEstado/Paginas/DetalhePropostaAlteracao.aspx?BID=23194 | AG2: https://app.parlamento.pt/webutils/docs/doc.pdf?path=6148523063484d364c793942556b356c6443397a6158526c63793959566b6c4a544556484c3039464c7a49774d6a59794d4449314d5441774f5339515153396b5a6a45794e6a41315a5330324e6d5a6d4c5451335a445174596a677a4e69316a4e4751794e546b304e6d4a6b5a4445756347526d&Fich=df12605e-66ff-47d4-b836-c4d25946bdd1.pdf&Inline=true | AH2: 46321.778 | AI2: 46321.781
A3: 2 | B3: 1C-2 | C3: 45959.375 | D3: Original | E3: PSD | F3: Paulo Neves; Pedro Coelho; Vânia Jesus | G3: Art. 62.º-A (aditamento) | L3: Artigo 62.º-A (Alteração à Lei n.º 21/2021, de 20 de abril) | S3: Aprovado(a) em Comissão | T3: Aprovada | U3: Favor: PSD, CH, PS, IL, CDS-PP; Contra: L, PCP, BE, PAN | V3: 45981 | W3: AR: https://www.parlamento.pt/OrcamentoEstado/Paginas/DetalhePropostaAlteracao.aspx?BID=23490 PDF: https://app.parlamento.pt/webutils/docs/doc.pdf?path=6148523063484d364c793942556b356c6443397a6158526c63793959566b6c4a544556484c3039464c7a49774d6a59794d4449314d5441774f533951515338355954466a4f5452694f43316d5a575a6a4c54517a595751745954526d4f433079595463345a6d46695a5759784e3249756347526d&Fich=9a1c94b8-fefc-43ad-a4f8-2a78fabef17b.pdf&Inline=true | X3: Orçamento, Finanças e Administração Pública | Y3: Articulado | Z3: Aditamento (Artigo PPL) | AA3: Aprovado(a) em Comissão | AC3: 2 | AD3: 1 | AE3: 23490 | AF3: https://www.parlamento.pt/OrcamentoEstado/Paginas/DetalhePropostaAlteracao.aspx?BID=23490 | AG3: https://app.parlamento.pt/webutils/docs/doc.pdf?path=6148523063484d364c793942556b356c6443397a6158526c63793959566b6c4a544556484c3039464c7a49774d6a59794d4449314d5441774f533951515338355954466a4f5452694f43316d5a575a6a4c54517a595751745954526d4f433079595463345a6d46695a5759784e3249756347526d&Fich=9a1c94b8-fefc-43ad-a4f8-2a78fabef17b.pdf&Inline=true | AH3: 46321.778 | AI3: 46321.781
A4: 3 | B4: 2C | C4: 45959.377 | D4: Original | E4: IL | F4: Angélique Da Teresa; Carlos Guimarães Pinto; Joana Cordeiro; Jorge Miguel Teixeira; Mariana Leitão; Mário Amorim Lopes; Miguel Rangel; Rodrigo Saraiva; Rui Rocha | G4: Art. 63.º (substituição) | L4: Verba 2.37, Verba 2.40, Verba 2.41, Lista I anexa ao Código do IVA, constante do Artigo 63.º da PPL | S4: Rejeitado(a) em Comissão | T4: Rejeitada | U4: Favor: CH, IL, BE, PAN; Contra: PSD, L, CDS-PP; Abstenção: PS, PCP | V4: 45982 | W4: AR: https://www.parlamento.pt/OrcamentoEstado/Paginas/DetalhePropostaAlteracao.aspx?BID=23195 PDF: https://app.parlamento.pt/webutils/docs/doc.pdf?path=6148523063484d364c793942556b356c6443397a6158526c63793959566b6c4a544556484c3039464c7a49774d6a59794d4449314d5441774f533951515338344e6d45334d3259304f5330354d7a63324c5451344d6d5974596a49344e6930785a5459314d7a6335595467324f4449756347526d&Fich=86a73f49-9376-482f-b286-1e65379a8682.pdf&Inline=true | X4: Ambiente e Energia; Orçamento, Finanças e Administração Pública | Y4: Articulado | Z4: Substituição | AA4: Rejeitado(a) em Comissão | AD4: 2 | AE4: 23195 | AF4: https://www.parlamento.pt/OrcamentoEstado/Paginas/DetalhePropostaAlteracao.aspx?BID=23195 | AG4: https://app.parlamento.pt/webutils/docs/doc.pdf?path=6148523063484d364c793942556b356c6443397a6158526c63793959566b6c4a544556484c3039464c7a49774d6a59794d4449314d5441774f533951515338344e6d45334d3259304f5330354d7a63324c5451344d6d5974596a49344e6930785a5459314d7a6335595467324f4449756347526d&Fich=86a73f49-9376-482f-b286-1e65379a8682.pdf&Inline=true | AH4: 46321.778 | AI4: 46321.781
A5: 4 | B5: 3C | C5: 45959.377 | D5: Original | E5: PAN | F5: Inês de Sousa Real | G5: Art. 137.º (aditamento) | L5: N.º 4, Artigo 137.º | S5: Aprovado(a) em Comissão | T5: Aprovada | U5: Favor: PSD, CH, PS, IL, L, PCP, BE, PAN; Contra: CDS-PP | V5: 45987 | W5: AR: https://www.parlamento.pt/OrcamentoEstado/Paginas/DetalhePropostaAlteracao.aspx?BID=23196 PDF: https://app.parlamento.pt/webutils/docs/doc.pdf?path=6148523063484d364c793942556b356c6443397a6158526c63793959566b6c4a544556484c3039464c7a49774d6a59794d4449314d5441774f533951515338794e4751774d7a557a4f5330794d446c6a4c54517a4e325174596d5535596931695a546b7a4d7a4932596d59325a6d4d756347526d&Fich=24d03539-209c-437d-be9b-be93326bf6fc.pdf&Inline=true | X5: Agricultura e Pescas | Y5: Articulado | Z5: Aditamento (Números e Alíneas) | AA5: Aprovado(a) em Comissão | AD5: 1 | AE5: 23196 | AF5: https://www.parlamento.pt/OrcamentoEstado/Paginas/DetalhePropostaAlteracao.aspx?BID=23196 | AG5: https://app.parlamento.pt/webutils/docs/doc.pdf?path=6148523063484d364c793942556b356c6443397a6158526c63793959566b6c4a544556484c3039464c7a49774d6a59794d4449314d5441774f533951515338794e4751774d7a557a4f5330794d446c6a4c54517a4e325174596d5535596931695a546b7a4d7a4932596d59325a6d4d756347526d&Fich=24d03539-209c-437d-be9b-be93326bf6fc.pdf&Inline=true | AH5: 46321.778 | AI5: 46321.781
A6: 5 | B6: 4C | C6: 45959.378 | D6: Original | E6: PAN | F6: Inês de Sousa Real | G6: Art. 63.º-A (aditamento) | L6: Artigo 63.º-A (Aditamento à lista I anexa ao Código do Imposto sobre o Valor Acrescentado) | S6: Rejeitado(a) em Comissão | T6: Rejeitada | U6: Favor: CH, IL, L, BE, PAN; Contra: PSD, PCP, CDS-PP; Abstenção: PS | V6: 45982 | W6: AR: https://www.parlamento.pt/OrcamentoEstado/Paginas/DetalhePropostaAlteracao.aspx?BID=23197 PDF: https://app.parlamento.pt/webutils/docs/doc.pdf?path=6148523063484d364c793942556b356c6443397a6158526c63793959566b6c4a544556484c3039464c7a49774d6a59794d4449314d5441774f5339515153396c4f574d334e5755794d7930334f544a694c54526d596a6374596a4a684e6930304d5442684e6a5577593252695a4459756347526d&Fich=e9c75e23-792b-4fb7-b2a6-410a650cdbd6.pdf&Inline=true | X6: Agricultura e Pescas | Y6: Articulado | Z6: Aditamento (Artigo PPL) | AA6: Rejeitado(a) em Comissão | AD6: 1 | AE6: 23197 | AF6: https://www.parlamento.pt/OrcamentoEstado/Paginas/DetalhePropostaAlteracao.aspx?BID=23197 | AG6: https://app.parlamento.pt/webutils/docs/doc.pdf?path=6148523063484d364c793942556b356c6443397a6158526c63793959566b6c4a544556484c3039464c7a49774d6a59794d4449314d5441774f5339515153396c4f574d334e5755794d7930334f544a694c54526d596a6374596a4a684e6930304d5442684e6a5577593252695a4459756347526d&Fich=e9c75e23-792b-4fb7-b2a6-410a650cdbd6.pdf&Inline=true | AH6: 46321.778 | AI6: 46321.781
A7: 6 | B7: 5C | C7: 45959.38 | D7: Original | E7: PAN | F7: Inês de Sousa Real | G7: Art. 63.º-A (aditamento) | L7: Artigo 63.º-A (Aditamento à lista I anexa ao Código do Imposto sobre o Valor Acrescentado) | S7: Rejeitado(a) em Plenário | T7: Rejeitada | U7: Favor: CH, L, BE, PAN, JPP; Contra: PSD, CDS-PP; Abstenção: PS, IL, PCP | V7: 45985 | W7: Avocada a Plenário. AR: https://www.parlamento.pt/OrcamentoEstado/Paginas/DetalhePropostaAlteracao.aspx?BID=23198 PDF: https://app.parlamento.pt/webutils/docs/doc.pdf?path=6148523063484d364c793942556b356c6443397a6158526c63793959566b6c4a544556484c3039464c7a49774d6a59794d4449314d5441774f53395151533878595755795a5749305a533032595759794c5452684e445974595449324e43316d4d6d59324e6d49785957497a596d59756347526d&Fich=1ae2eb4e-6af2-4a46-a264-f2f66b1ab3bf.pdf&Inline=true | X7: Agricultura e Pescas | Y7: Articulado | Z7: Aditamento (Artigo PPL) | AA7: Rejeitado(a) em Plenário | AB7: S | AD7: 2 | AE7: 23198 | AF7: https://www.parlamento.pt/OrcamentoEstado/Paginas/DetalhePropostaAlteracao.aspx?BID=23198 | AG7: https://app.parlamento.pt/webutils/docs/doc.pdf?path=6148523063484d364c793942556b356c6443397a6158526c63793959566b6c4a544556484c3039464c7a49774d6a59794d4449314d5441774f53395151533878595755795a5749305a533032595759794c5452684e445974595449324e43316d4d6d59324e6d49785957497a596d59756347526d&Fich=1ae2eb4e-6af2-4a46-a264-f2f66b1ab3bf.pdf&Inline=true | AH7: 46321.778 | AI7: 46321.781
A8: 7 | B8: 6C | C8: 45959.383 | D8: Original | E8: PAN | F8: Inês de Sousa Real | G8: Art. 130.º (substituição) | L8: N.º 2, Artigo 130.º | S8: Rejeitado(a) em Comissão | T8: Rejeitada | U8: Favor: L, PCP, BE, PAN; Contra: PSD, CH, CDS-PP; Abstenção: PS, IL | V8: 45984 | W8: AR: https://www.parlamento.pt/OrcamentoEstado/Paginas/DetalhePropostaAlteracao.aspx?BID=23199 PDF: https://app.parlamento.pt/webutils/docs/doc.pdf?path=6148523063484d364c793942556b356c6443397a6158526c63793959566b6c4a544556484c3039464c7a49774d6a59794d4449314d5441774f533951515338354e7a4d314d6a4d304d6930344e6d45314c54526c5a4451744f5745325a43316b5a444a6a4e446b344e5749304e6a49756347526d&Fich=97352342-86a5-4ed4-9a6d-dd2c4985b462.pdf&Inline=true | X8: Ambiente e Energia; Assuntos Constitucionais, Direitos, Liberdades e Garantias; Orçamento, Finanças e Administração Pública | Y8: Articulado | Z8: Substituição | AA8: Rejeitado(a) em Comissão | AD8: 1 | AE8: 23199 | AF8: https://www.parlamento.pt/OrcamentoEstado/Paginas/DetalhePropostaAlteracao.aspx?BID=23199 | AG8: https://app.parlamento.pt/webutils/docs/doc.pdf?path=6148523063484d364c793942556b356c6443397a6158526c63793959566b6c4a544556484c3039464c7a49774d6a59794d4449314d5441774f533951515338354e7a4d314d6a4d304d6930344e6d45314c54526c5a4451744f5745325a43316b5a444a6a4e446b344e5749304e6a49756347526d&Fich=97352342-86a5-4ed4-9a6d-dd2c4985b462.pdf&Inline=true | AH8: 46321.778 | AI8: 46321.781
A9: 8 | B9: 7C | C9: 45959.385 | D9: Original | E9: PAN | F9: Inês de Sousa Real | G9: Art. 95.º (substituição) | L9: N.º 4, Artigo 95.º | S9: Rejeitado(a) em Plenário | T9: Rejeitada | U9: Favor: IL, L, PCP, BE, PAN, JPP; Contra: PSD, CDS-PP; Abstenção: CH, PS | V9: 45985 | W9: Avocada a Plenário. AR: https://www.parlamento.pt/OrcamentoEstado/Paginas/DetalhePropostaAlteracao.aspx?BID=23200 PDF: https://app.parlamento.pt/webutils/docs/doc.pdf?path=6148523063484d364c793942556b356c6443397a6158526c63793959566b6c4a544556484c3039464c7a49774d6a59794d4449314d5441774f5339515153396d4d546c6b4e444e6d4e4330344e5755314c5452694d4467745954646b4e4330324d6d466c5a5463794f474a6d4e6d51756347526d&Fich=f19d43f4-85e5-4b08-a7d4-62aee728bf6d.pdf&Inline=true | X9: Ambiente e Energia; Orçamento, Finanças e Administração Pública; Reforma do Estado e Poder Local | Y9: Articulado | Z9: Substituição | AA9: Rejeitado(a) em Plenário | AB9: S | AD9: 1 | AE9: 23200 | AF9: https://www.parlamento.pt/OrcamentoEstado/Paginas/DetalhePropostaAlteracao.aspx?BID=23200 | AG9: https://app.parlamento.pt/webutils/docs/doc.pdf?path=6148523063484d364c793942556b356c6443397a6158526c63793959566b6c4a544556484c3039464c7a49774d6a59794d4449314d5441774f5339515153396d4d546c6b4e444e6d4e4330344e5755314c5452694d4467745954646b4e4330324d6d466c5a5463794f474a6d4e6d51756347526d&Fich=f19d43f4-85e5-4b08-a7d4-62aee728bf6d.pdf&Inline=true | AH9: 46321.778 | AI9: 46321.781
A10: 9 | B10: 8C-1 | C10: 45959.386 | D10: Original | E10: PAN | F10: Inês de Sousa Real | G10: Art. 101.º (substituição) | L10: N.º 1, Artigo 101.º | S10: Rejeitado(a) em Plenário | T10: Rejeitada | U10: Favor: L, PAN, JPP; Contra: PSD, IL, PCP, CDS-PP; Abstenção: CH, PS, BE | V10: 45985 | W10: Avocada a Plenário. AR: https://www.parlamento.pt/OrcamentoEstado/Paginas/DetalhePropostaAlteracao.aspx?BID=23201 PDF: https://app.parlamento.pt/webutils/docs/doc.pdf?path=6148523063484d364c793942556b356c6443397a6158526c63793959566b6c4a544556484c3039464c7a49774d6a59794d4449314d5441774f533951515338304e574d315a474e6c4e53316c4e6a67354c54526d4d6a63744f475579596930304e4749784e6d557a4f44677a4f5451756347526d&Fich=45c5dce5-e689-4f27-8e2b-44b16e388394.pdf&Inline=true | X10: Assuntos Constitucionais, Direitos, Liberdades e Garantias; Infraestruturas, Mobilidade e Habitação | Y10: Articulado | Z10: Substituição | AA10: Rejeitado(a) em Plenário | AB10: S | AC10: 1 | AD10: 1 | AE10: 23201 | AF10: https://www.parlamento.pt/OrcamentoEstado/Paginas/DetalhePropostaAlteracao.aspx?BID=23201 | AG10: https://app.parlamento.pt/webutils/docs/doc.pdf?path=6148523063484d364c793942556b356c6443397a6158526c63793959566b6c4a544556484c3039464c7a49774d6a59794d4449314d5441774f533951515338304e574d315a474e6c4e53316c4e6a67354c54526d4d6a63744f475579596930304e4749784e6d557a4f44677a4f5451756347526d&Fich=45c5dce5-e689-4f27-8e2b-44b16e388394.pdf&Inline=true | AH10: 46321.778 | AI10: 46321.781
A11: 10 | B11: 8C-2 | C11: 45959.386 | D11: Original | E11: PAN | F11: Inês de Sousa Real | G11: Art. 101.º (aditamento) | L11: N.º 4, Artigo 101.º | S11: Rejeitado(a) em Plenário | T11: Rejeitada | U11: Favor: L, PAN, JPP; Contra: PSD, IL, PCP, CDS-PP; Abstenção: CH, PS, BE | V11: 45985 | W11: Avocada a Plenário. AR: https://www.parlamento.pt/OrcamentoEstado/Paginas/DetalhePropostaAlteracao.aspx?BID=25386 PDF: https://app.parlamento.pt/webutils/docs/doc.pdf?path=6148523063484d364c793942556b356c6443397a6158526c63793959566b6c4a544556484c3039464c7a49774d6a59794d4449314d5441774f5339515153396a5a47566b4f5449315979303359544d334c5451794d3255744f546b795a6930344e475a6c597a5a694d6d4e6b595441756347526d&Fich=cded925c-7a37-423e-992f-84fec6b2cda0.pdf&Inline=true | X11: Assuntos Constitucionais, Direitos, Liberdades e Garantias; Infraestruturas, Mobilidade e Habitação | Y11: Articulado | Z11: Aditamento (Números e Alíneas) | AA11: Rejeitado(a) em Plenário | AB11: S | AC11: 2 | AD11: 1 | AE11: 25386 | AF11: https://www.parlamento.pt/OrcamentoEstado/Paginas/DetalhePropostaAlteracao.aspx?BID=25386 | AG11: https://app.parlamento.pt/webutils/docs/doc.pdf?path=6148523063484d364c793942556b356c6443397a6158526c63793959566b6c4a544556484c3039464c7a49774d6a59794d4449314d5441774f5339515153396a5a47566b4f5449315979303359544d334c5451794d3255744f546b795a6930344e475a6c597a5a694d6d4e6b595441756347526d&Fich=cded925c-7a37-423e-992f-84fec6b2cda0.pdf&Inline=true | AH11: 46321.778 | AI11: 46321.781
A12: 11 | B12: 9C | C12: 45959.388 | D12: Original | E12: PAN | F12: Inês de Sousa Real | G12: Art. 108.º-A (aditamento) | L12: Artigo 108.º-A (Planos plurianuais de promoção do bem-estar dos animais de companhia nas freguesias) | S12: Aprovado(a) em Comissão | T12: Aprovada | U12: Favor: CH, PS, L, BE, PAN; Contra: PSD, IL, PCP, CDS-PP | V12: 45982 | W12: AR: https://www.parlamento.pt/OrcamentoEstado/Paginas/DetalhePropostaAlteracao.aspx?BID=23202 PDF: https://app.parlamento.pt/webutils/docs/doc.pdf?path=6148523063484d364c793942556b356c6443397a6158526c63793959566b6c4a544556484c3039464c7a49774d6a59794d4449314d5441774f533951515338344f47526d4d6d59314d4330794e4755794c54526c5a6d4d74596d4e695a53307a4f4441354e6d5135596a4a6d4e446b756347526d&Fich=88df2f50-24e2-4efc-bcbe-38096d9b2f49.pdf&Inline=true | X12: Defesa Nacional; Educação e Ciência | Y12: Articulado | Z12: Aditamento (Artigo PPL) | AA12: Aprovado(a) em Comissão | AD12: 1 | AE12: 23202 | AF12: https://www.parlamento.pt/OrcamentoEstado/Paginas/DetalhePropostaAlteracao.aspx?BID=23202 | AG12: https://app.parlamento.pt/webutils/docs/doc.pdf?path=6148523063484d364c793942556b356c6443397a6158526c63793959566b6c4a544556484c3039464c7a49774d6a59794d4449314d5441774f533951515338344f47526d4d6d59314d4330794e4755794c54526c5a6d4d74596d4e695a53307a4f4441354e6d5135596a4a6d4e446b756347526d&Fich=88df2f50-24e2-4efc-bcbe-38096d9b2f49.pdf&Inline=true | AH12: 46321.778 | AI12: 46321.781
A13: 12 | B13: 10C | C13: 45959.39 | D13: Original | E13: PAN | F13: Inês de Sousa Real | G13: Art. 108.º (substituição) | L13: Subalínea i), Corpo, Alínea c), Alínea f), Corpo, N.º 1, Artigo 108.º | S13: Rejeitado(a) em Comissão | T13: Rejeitada | U13: Favor: L, PCP, BE, PAN; Contra: PSD, CDS-PP; Abstenção: CH, PS, IL | V13: 45982 | W13: AR: https://www.parlamento.pt/OrcamentoEstado/Paginas/DetalhePropostaAlteracao.aspx?BID=23203 PDF: https://app.parlamento.pt/webutils/docs/doc.pdf?path=6148523063484d364c793942556b356c6443397a6158526c63793959566b6c4a544556484c3039464c7a49774d6a59794d4449314d5441774f533951515338334e7a6b774e44686a4d79316859546c6b4c5451784f545574596a5a6c5979316d4d544977595459344e7a49334d4449756347526d&Fich=779048c3-aa9d-4195-b6ec-f120a6872702.pdf&Inline=true | X13: Agricultura e Pescas | Y13: Articulado | Z13: Substituição | AA13: Rejeitado(a) em Comissão | AD13: 1 | AE13: 23203 | AF13: https://www.parlamento.pt/OrcamentoEstado/Paginas/DetalhePropostaAlteracao.aspx?BID=23203 | AG13: https://app.parlamento.pt/webutils/docs/doc.pdf?path=6148523063484d364c793942556b356c6443397a6158526c63793959566b6c4a544556484c3039464c7a49774d6a59794d4449314d5441774f533951515338334e7a6b774e44686a4d79316859546c6b4c5451784f545574596a5a6c5979316d4d544977595459344e7a49334d4449756347526d&Fich=779048c3-aa9d-4195-b6ec-f120a6872702.pdf&Inline=true | AH13: 46321.778 | AI13: 46321.781
A14: 13 | B14: 11C-1 | C14: 45959.392 | D14: Original | E14: PAN | F14: Inês de Sousa Real | G14: Art. 113.º (substituição) | L14: N.º 2, Artigo 113.º | S14: Rejeitado(a) em Comissão | T14: Rejeitada | U14: Favor: CH, L, PCP, BE, PAN; Contra: PSD, IL, CDS-PP; Abstenção: PS | V14: 45985 | W14: AR: https://www.parlamento.pt/OrcamentoEstado/Paginas/DetalhePropostaAlteracao.aspx?BID=23204 PDF: https://app.parlamento.pt/webutils/docs/doc.pdf?path=6148523063484d364c793942556b356c6443397a6158526c63793959566b6c4a544556484c3039464c7a49774d6a59794d4449314d5441774f53395151533877597a4a6a4e57566c4e533032596d4d794c5451344f544974595751784d43316a4d4441304d6a63335a4445334d3255756347526d&Fich=0c2c5ee5-6bc2-4892-ad10-c004277d173e.pdf&Inline=true | X14: Agricultura e Pescas; Assuntos Constitucionais, Direitos, Liberdades e Garantias; Orçamento, Finanças e Administração Pública | Y14: Articulado | Z14: Substituição | AA14: Rejeitado(a) em Comissão | AC14: 1 | AD14: 1 | AE14: 23204 | AF14: https://www.parlamento.pt/OrcamentoEstado/Paginas/DetalhePropostaAlteracao.aspx?BID=23204 | AG14: https://app.parlamento.pt/webutils/docs/doc.pdf?path=6148523063484d364c793942556b356c6443397a6158526c63793959566b6c4a544556484c3039464c7a49774d6a59794d4449314d5441774f53395151533877597a4a6a4e57566c4e533032596d4d794c5451344f544974595751784d43316a4d4441304d6a63335a4445334d3255756347526d&Fich=0c2c5ee5-6bc2-4892-ad10-c004277d173e.pdf&Inline=true | AH14: 46321.778 | AI14: 46321.781
A15: 14 | B15: 11C-2 | C15: 45959.392 | D15: Original | E15: PAN | F15: Inês de Sousa Real | G15: Art. 113.º (aditamento) | L15: N.º 5, Artigo 113.º | S15: Rejeitado(a) em Comissão | T15: Rejeitada | U15: Favor: CH, L, BE, PAN; Contra: PSD, IL, CDS-PP; Abstenção: PS, PCP | V15: 45985 | W15: AR: https://www.parlamento.pt/OrcamentoEstado/Paginas/DetalhePropostaAlteracao.aspx?BID=23436 PDF: https://app.parlamento.pt/webutils/docs/doc.pdf?path=6148523063484d364c793942556b356c6443397a6158526c63793959566b6c4a544556484c3039464c7a49774d6a59794d4449314d5441774f5339515153396c4e6a4d79595442685a53307a4e544e684c5451324f546b744f44417a596930784f5455304f4755305a57466b4e3259756347526d&Fich=e632a0ae-353a-4699-803b-19548e4ead7f.pdf&Inline=true | X15: Agricultura e Pescas; Assuntos Constitucionais, Direitos, Liberdades e Garantias; Orçamento, Finanças e Administração Pública | Y15: Articulado | Z15: Aditamento (Números e Alíneas) | AA15: Rejeitado(a) em Comissão | AC15: 2 | AD15: 1 | AE15: 23436 | AF15: https://www.parlamento.pt/OrcamentoEstado/Paginas/DetalhePropostaAlteracao.aspx?BID=23436 | AG15: https://app.parlamento.pt/webutils/docs/doc.pdf?path=6148523063484d364c793942556b356c6443397a6158526c63793959566b6c4a544556484c3039464c7a49774d6a59794d4449314d5441774f5339515153396c4e6a4d79595442685a53307a4e544e684c5451324f546b744f44417a596930784f5455304f4755305a57466b4e3259756347526d&Fich=e632a0ae-353a-4699-803b-19548e4ead7f.pdf&Inline=true | AH15: 46321.778 | AI15: 46321.781
A16: 15 | B16: 12C | C16: 45959.394 | D16: Original | E16: PAN | F16: Inês de Sousa Real | G16: Art. 60.º (substituição) | L16: N.º 7, Artigo 12.º, N.º 19, Artigo 72.º do Código do IRS | S16: Rejeitado(a) em Comissão | T16: Rejeitada | U16: Favor: CH, BE, PAN; Contra: PSD, CDS-PP; Abstenção: PS, IL, L, PCP | V16: 45981 | W16: AR: https://www.parlamento.pt/OrcamentoEstado/Paginas/DetalhePropostaAlteracao.aspx?BID=23205 PDF: https://app.parlamento.pt/webutils/docs/doc.pdf?path=6148523063484d364c793942556b356c6443397a6158526c63793959566b6c4a544556484c3039464c7a49774d6a59794d4449314d5441774f5339515153396d4d444d335a4463305979316a595455794c5452685a4759744f47466b4d5330324d474d335a5756685957566c4d4467756347526d&Fich=f037d74c-ca52-4adf-8ad1-60c7eeaaee08.pdf&Inline=true | X16: Assuntos Constitucionais, Direitos, Liberdades e Garantias; Orçamento, Finanças e Administração Pública | Y16: Articulado | Z16: Substituição | AA16: Rejeitado(a) em Comissão | AD16: 2 | AE16: 23205 | AF16: https://www.parlamento.pt/OrcamentoEstado/Paginas/DetalhePropostaAlteracao.aspx?BID=23205 | AG16: https://app.parlamento.pt/webutils/docs/doc.pdf?path=6148523063484d364c793942556b356c6443397a6158526c63793959566b6c4a544556484c3039464c7a49774d6a59794d4449314d5441774f5339515153396d4d444d335a4463305979316a595455794c5452685a4759744f47466b4d5330324d474d335a5756685957566c4d4467756347526d&Fich=f037d74c-ca52-4adf-8ad1-60c7eeaaee08.pdf&Inline=true | AH16: 46321.778 | AI16: 46321.781
A17: 16 | B17: 13C | C17: 45959.395 | D17: Original | E17: PAN | F17: Inês de Sousa Real | G17: Art. 7.º (substituição) | L17: Verba 28, Mapa de alterações e transferências orçamentais, Artigo 7.º | S17: Rejeitado(a) em Comissão | T17: Rejeitada | U17: Favor: L, PCP, BE, PAN; Contra: PSD, IL, CDS-PP; Abstenção: CH, PS | V17: 45987 | W17: AR: https://www.parlamento.pt/OrcamentoEstado/Paginas/DetalhePropostaAlteracao.aspx?BID=23206 PDF: https://app.parlamento.pt/webutils/docs/doc.pdf?path=6148523063484d364c793942556b356c6443397a6158526c63793959566b6c4a544556484c3039464c7a49774d6a59794d4449314d5441774f5339515153396a4f4455794d6a63775a6930784e574d784c54526c4d57497459546b34595331694d6d59314e32566859324e6a595463756347526d&Fich=c852270f-15c1-4e1b-a98a-b2f57eaccca7.pdf&Inline=true | X17: Ambiente e Energia | Y17: Mapas | Z17: Substituição | AA17: Rejeitado(a) em Comissão | AD17: 1 | AE17: 23206 | AF17: https://www.parlamento.pt/OrcamentoEstado/Paginas/DetalhePropostaAlteracao.aspx?BID=23206 | AG17: https://app.parlamento.pt/webutils/docs/doc.pdf?path=6148523063484d364c793942556b356c6443397a6158526c63793959566b6c4a544556484c3039464c7a49774d6a59794d4449314d5441774f5339515153396a4f4455794d6a63775a6930784e574d784c54526c4d57497459546b34595331694d6d59314e32566859324e6a595463756347526d&Fich=c852270f-15c1-4e1b-a98a-b2f57eaccca7.pdf&Inline=true | AH17: 46321.778 | AI17: 46321.781
A18: 17 | B18: 14C | C18: 45959.397 | D18: Original | E18: PAN | F18: Inês de Sousa Real | G18: Art. 81.º-A (aditamento) | L18: Artigo 81.º-A (Alteração ao Decreto-Lei n.º 84/2017, de 21 de julho) | S18: Rejeitado(a) em Comissão | T18: Rejeitada | U18: Favor: IL, L, PCP, BE, PAN; Contra: PSD, CDS-PP; Abstenção: CH, PS | V18: 45982 | W18: AR: https://www.parlamento.pt/OrcamentoEstado/Paginas/DetalhePropostaAlteracao.aspx?BID=23207 PDF: https://app.parlamento.pt/webutils/docs/doc.pdf?path=6148523063484d364c793942556b356c6443397a6158526c63793959566b6c4a544556484c3039464c7a49774d6a59794d4449314d5441774f533951515339695a474e684d7a49784f4330335a5755794c5451334e7a63744f546b7a5a4330304f5441774d6a49794d6d55334f4445756347526d&Fich=bdca3218-7ee2-4777-993d-49002222e781.pdf&Inline=true | X18: Orçamento, Finanças e Administração Pública; Reforma do Estado e Poder Local | Y18: Articulado | Z18: Aditamento (Artigo PPL) | AA18: Rejeitado(a) em Comissão | AD18: 1 | AE18: 23207 | AF18: https://www.parlamento.pt/OrcamentoEstado/Paginas/DetalhePropostaAlteracao.aspx?BID=23207 | AG18: https://app.parlamento.pt/webutils/docs/doc.pdf?path=6148523063484d364c793942556b356c6443397a6158526c63793959566b6c4a544556484c3039464c7a49774d6a59794d4449314d5441774f533951515339695a474e684d7a49784f4330335a5755794c5451334e7a63744f546b7a5a4330304f5441774d6a49794d6d55334f4445756347526d&Fich=bdca3218-7ee2-4777-993d-49002222e781.pdf&Inline=true | AH18: 46321.778 | AI18: 46321.781
A19: 18 | B19: 15C | C19: 45959.399 | D19: Retirada | E19: PAN | F19: Inês de Sousa Real | G19: Articulado | L19: Artigo 81.º-A | S19: Retirado(a) | T19: Retirada | W19: AR: https://www.parlamento.pt/OrcamentoEstado/Paginas/DetalhePropostaAlteracao.aspx?BID=23208 PDF: https://app.parlamento.pt/webutils/docs/doc.pdf?path=6148523063484d364c793942556b356c6443397a6158526c63793959566b6c4a544556484c3039464c7a49774d6a59794d4449314d5441774f533951515338354d44686a595759774e69316d4e6a41774c54526859544974596a4a6a4f5330344d7a51774e575a6a4f5749354f544d756347526d&Fich=908caf06-f600-4aa2-b2c9-83405fc9b993.pdf&Inline=true | X19: Assuntos Constitucionais, Direitos, Liberdades e Garantias; Orçamento, Finanças e Administração Pública | Y19: Articulado | Z19: Por Definir | AA19: Retirado(a) | AD19: 0 | AE19: 23208 | AF19: https://www.parlamento.pt/OrcamentoEstado/Paginas/DetalhePropostaAlteracao.aspx?BID=23208 | AG19: https://app.parlamento.pt/webutils/docs/doc.pdf?path=6148523063484d364c793942556b356c6443397a6158526c63793959566b6c4a544556484c3039464c7a49774d6a59794d4449314d5441774f533951515338354d44686a595759774e69316d4e6a41774c54526859544974596a4a6a4f5330344d7a51774e575a6a4f5749354f544d756347526d&Fich=908caf06-f600-4aa2-b2c9-83405fc9b993.pdf&Inline=true | AH19: 46321.778 | AI19: 46321.781
A20: 19 | B20: 16C | C20: 45959.399 | D20: Original | E20: PAN | F20: Inês de Sousa Real | G20: Art. 63.º-A (aditamento) | L20: Artigo 63.º-A (Aditamento à lista I anexa ao Código do Imposto sobre o Valor Acrescentado) | S20: Rejeitado(a) em Comissão | T20: Rejeitada | U20: Favor: CH, IL, L, PCP, BE, PAN; Contra: PSD, CDS-PP; Abstenção: PS | V20: 45982 | W20: AR: https://www.parlamento.pt/OrcamentoEstado/Paginas/DetalhePropostaAlteracao.aspx?BID=23209 PDF: https://app.parlamento.pt/webutils/docs/doc.pdf?path=6148523063484d364c793942556b356c6443397a6158526c63793959566b6c4a544556484c3039464c7a49774d6a59794d4449314d5441774f5339515153396a4f4759794d3249795953316b4d324d794c5451774f4441744f57566a5953316a4e4755784d7a4e684f54646a4f574d756347526d&Fich=c8f23b2a-d3c2-4080-9eca-c4e133a97c9c.pdf&Inline=true | X20: Ambiente e Energia; Orçamento, Finanças e Administração Pública | Y20: Articulado | Z20: Aditamento (Artigo PPL) | AA20: Rejeitado(a) em Comissão | AD20: 1 | AE20: 23209 | AF20: https://www.parlamento.pt/OrcamentoEstado/Paginas/DetalhePropostaAlteracao.aspx?BID=23209 | AG20: https://app.parlamento.pt/webutils/docs/doc.pdf?path=6148523063484d364c793942556b356c6443397a6158526c63793959566b6c4a544556484c3039464c7a49774d6a59794d4449314d5441774f5339515153396a4f4759794d3249795953316b4d324d794c5451774f4441744f57566a5953316a4e4755784d7a4e684f54646a4f574d756347526d&Fich=c8f23b2a-d3c2-4080-9eca-c4e133a97c9c.pdf&Inline=true | AH20: 46321.778 | AI20: 46321.781
A21: 20 | B21: 17C | C21: 45959.401 | D21: Original | E21: PAN | F21: Inês de Sousa Real | G21: Art. 60.º (substituição) | L21: Alínea b), alínea c), alínea d), N.º 1, Artigo 78.º-E do Código do IRS | S21: Rejeitado(a) em Comissão | T21: Rejeitada | U21: Favor: CH, IL, L, PCP, BE, PAN; Contra: PSD, CDS-PP; Abstenção: PS | V21: 45981 | W21: AR: https://www.parlamento.pt/OrcamentoEstado/Paginas/DetalhePropostaAlteracao.aspx?BID=23210 PDF: https://app.parlamento.pt/webutils/docs/doc.pdf?path=6148523063484d364c793942556b356c6443397a6158526c63793959566b6c4a544556484c3039464c7a49774d6a59794d4449314d5441774f53395151533835596d4d30595755794e7930304e6d45784c5451354f5751744f544e6a4e79316a4d4745334d44426b4e575532596d51756347526d&Fich=9bc4ae27-46a1-499d-93c7-c0a700d5e6bd.pdf&Inline=true | X21: Infraestruturas, Mobilidade e Habitação; Orçamento, Finanças e Administração Pública | Y21: Articulado | Z21: Substituição | AA21: Rejeitado(a) em Comissão | AD21: 1 | AE21: 23210 | AF21: https://www.parlamento.pt/OrcamentoEstado/Paginas/DetalhePropostaAlteracao.aspx?BID=23210 | AG21: https://app.parlamento.pt/webutils/docs/doc.pdf?path=6148523063484d364c793942556b356c6443397a6158526c63793959566b6c4a544556484c3039464c7a49774d6a59794d4449314d5441774f53395151533835596d4d30595755794e7930304e6d45784c5451354f5751744f544e6a4e79316a4d4745334d44426b4e575532596d51756347526d&Fich=9bc4ae27-46a1-499d-93c7-c0a700d5e6bd.pdf&Inline=true | AH21: 46321.778 | AI21: 46321.781
A22: 21 | B22: 18C | C22: 45959.402 | D22: Original | E22: PAN | F22: Inês de Sousa Real | G22: Art. 8.º (substituição) | L22: N.º 17, Artigo 8.º | S22: Rejeitado(a) em Comissão | T22: Rejeitada | U22: Favor: IL, L, PCP, CDS-PP, BE, PAN; Contra: PSD, CH; Abstenção: PS | V22: 45981 | W22: AR: https://www.parlamento.pt/OrcamentoEstado/Paginas/DetalhePropostaAlteracao.aspx?BID=23211 PDF: https://app.parlamento.pt/webutils/docs/doc.pdf?path=6148523063484d364c793942556b356c6443397a6158526c63793959566b6c4a544556484c3039464c7a49774d6a59794d4449314d5441774f5339515153396d5a44426a5a546b79596930784f574d774c5451774f5441745954646d4d7930334d6d45335a4755354d574a685a4463756347526d&Fich=fd0ce92b-19c0-4090-a7f3-72a7de91bad7.pdf&Inline=true | X22: Assuntos Constitucionais, Direitos, Liberdades e Garantias | Y22: Articulado | Z22: Substituição | AA22: Rejeitado(a) em Comissão | AD22: 1 | AE22: 23211 | AF22: https://www.parlamento.pt/OrcamentoEstado/Paginas/DetalhePropostaAlteracao.aspx?BID=23211 | AG22: https://app.parlamento.pt/webutils/docs/doc.pdf?path=6148523063484d364c793942556b356c6443397a6158526c63793959566b6c4a544556484c3039464c7a49774d6a59794d4449314d5441774f5339515153396d5a44426a5a546b79596930784f574d774c5451774f5441745954646d4d7930334d6d45335a4755354d574a685a4463756347526d&Fich=fd0ce92b-19c0-4090-a7f3-72a7de91bad7.pdf&Inline=true | AH22: 46321.778 | AI22: 46321.781
A23: 22 | B23: 19C | C23: 45959.417 | D23: Original | E23: PAN | F23: Inês de Sousa Real | G23: Art. 39.º-A (aditamento) | L23: Artigo 39.º-A (Respostas de suporte habitacional a pessoas em situação de sem-abrigo) | S23: Aprovado(a) em Comissão | T23: Aprovada | U23: Favor: CH, PS, IL, L, PCP, BE, PAN; Contra: PSD, CDS-PP | V23: 45981 | W23: AR: https://www.parlamento.pt/OrcamentoEstado/Paginas/DetalhePropostaAlteracao.aspx?BID=23212 PDF: https://app.parlamento.pt/webutils/docs/doc.pdf?path=6148523063484d364c793942556b356c6443397a6158526c63793959566b6c4a544556484c3039464c7a49774d6a59794d4449314d5441774f533951515338784e7a646a4f5451304d5330775a5751304c54526d4e446b744f544a695a6930334d6a6c6a596a466c4e6d566c595463756347526d&Fich=177c9441-0ed4-4f49-92bf-729cb1e6eea7.pdf&Inline=true | X23: Assuntos Constitucionais, Direitos, Liberdades e Garantias; Trabalho, Segurança Social e Inclusão | Y23: Articulado | Z23: Aditamento (Artigo PPL) | AA23: Aprovado(a) em Comissão | AD23: 1 | AE23: 23212 | AF23: https://www.parlamento.pt/OrcamentoEstado/Paginas/DetalhePropostaAlteracao.aspx?BID=23212 | AG23: https://app.parlamento.pt/webutils/docs/doc.pdf?path=6148523063484d364c793942556b356c6443397a6158526c63793959566b6c4a544556484c3039464c7a49774d6a59794d4449314d5441774f533951515338784e7a646a4f5451304d5330775a5751304c54526d4e446b744f544a695a6930334d6a6c6a596a466c4e6d566c595463756347526d&Fich=177c9441-0ed4-4f49-92bf-729cb1e6eea7.pdf&Inline=true | AH23: 46321.778 | AI23: 46321.781
A24: 23 | B24: 20C | C24: 45959.419 | D24: Original | E24: PAN | F24: Inês de Sousa Real | G24: Art. 7.º (aditamento) | L24: Verba 107, Mapa de alterações e transferências orçamentais, Artigo 7.º | S24: Rejeitado(a) em Comissão | T24: Rejeitada | U24: Favor: CH, L, PCP, BE, PAN; Contra: PSD, IL, CDS-PP; Abstenção: PS | V24: 45987 | W24: AR: https://www.parlamento.pt/OrcamentoEstado/Paginas/DetalhePropostaAlteracao.aspx?BID=23213 PDF: https://app.parlamento.pt/webutils/docs/doc.pdf?path=6148523063484d364c793942556b356c6443397a6158526c63793959566b6c4a544556484c3039464c7a49774d6a59794d4449314d5441774f533951515338784f54686b4f5463314f43316c4f5456684c5451314d7a4d744f4441325953303459544e6a4e44466c59544e6c4f5441756347526d&Fich=198d9758-e95a-4533-806a-8a3c41ea3e90.pdf&Inline=true | X24: Infraestruturas, Mobilidade e Habitação; Orçamento, Finanças e Administração Pública | Y24: Mapas | Z24: Aditamento (Números e Alíneas) | AA24: Rejeitado(a) em Comissão | AD24: 1 | AE24: 23213 | AF24: https://www.parlamento.pt/OrcamentoEstado/Paginas/DetalhePropostaAlteracao.aspx?BID=23213 | AG24: https://app.parlamento.pt/webutils/docs/doc.pdf?path=6148523063484d364c793942556b356c6443397a6158526c63793959566b6c4a544556484c3039464c7a49774d6a59794d4449314d5441774f533951515338784f54686b4f5463314f43316c4f5456684c5451314d7a4d744f4441325953303459544e6a4e44466c59544e6c4f5441756347526d&Fich=198d9758-e95a-4533-806a-8a3c41ea3e90.pdf&Inline=true | AH24: 46321.778 | AI24: 46321.781
A25: 24 | B25: 21C-1 | C25: 45959.42 | D25: Original | E25: PAN | F25: Inês de Sousa Real | G25: Art. 7.º (aditamento) | L25: Verba 107, Mapa de alterações e transferências orçamentais, Artigo 7.º | S25: Rejeitado(a) em Comissão | T25: Rejeitada | U25: Favor: PS, L, PCP, BE, PAN; Contra: PSD, CH, CDS-PP; Abstenção: IL | V25: 45987 | W25: AR: https://www.parlamento.pt/OrcamentoEstado/Paginas/DetalhePropostaAlteracao.aspx?BID=23214 PDF: https://app.parlamento.pt/webutils/docs/doc.pdf?path=6148523063484d364c793942556b356c6443397a6158526c63793959566b6c4a544556484c3039464c7a49774d6a59794d4449314d5441774f533951515338324e3255324e6d49794f4330774d3259314c54517a4f57517459545133596930774d6a557a59574d305a4463344d6d51756347526d&Fich=67e66b28-03f5-439d-a47b-0253ac4d782d.pdf&Inline=true | X25: Transparência e Estatuto dos Deputados | Y25: Mapas | Z25: Aditamento (Números e Alíneas) | AA25: Rejeitado(a) em Comissão | AC25: 1 | AD25: 1 | AE25: 23214 | AF25: https://www.parlamento.pt/OrcamentoEstado/Paginas/DetalhePropostaAlteracao.aspx?BID=23214 | AG25: https://app.parlamento.pt/webutils/docs/doc.pdf?path=6148523063484d364c793942556b356c6443397a6158526c63793959566b6c4a544556484c3039464c7a49774d6a59794d4449314d5441774f533951515338324e3255324e6d49794f4330774d3259314c54517a4f57517459545133596930774d6a557a59574d305a4463344d6d51756347526d&Fich=67e66b28-03f5-439d-a47b-0253ac4d782d.pdf&Inline=true | AH25: 46321.778 | AI25: 46321.781
A26: 25 | B26: 21C-2 | C26: 45959.42 | D26: Original | E26: PAN | F26: Inês de Sousa Real | G26: Art. 1.º (substituição) | L26: Mapa 4, Reforço da verba, € 1.600.000 | S26: Rejeitado(a) em Comissão | T26: Rejeitada | U26: Favor: PS, L, PCP, BE, PAN; Contra: PSD, CH, CDS-PP; Abstenção: IL | V26: 45987 | W26: AR: https://www.parlamento.pt/OrcamentoEstado/Paginas/DetalhePropostaAlteracao.aspx?BID=24520 PDF: https://app.parlamento.pt/webutils/docs/doc.pdf?path=6148523063484d364c793942556b356c6443397a6158526c63793959566b6c4a544556484c3039464c7a49774d6a59794d4449314d5441774f5339515153396c4f47457a4d32517a5a43316d4d7a646d4c545132597a4d744f444e685a4330304e7a45784e44637a4d3245784f5463756347526d&Fich=e8a33d3d-f37f-46c3-83ad-47114733a197.pdf&Inline=true | X26: Transparência e Estatuto dos Deputados | Y26: Mapas | Z26: Substituição | AA26: Rejeitado(a) em Comissão | AC26: 2 | AD26: 1 | AE26: 24520 | AF26: https://www.parlamento.pt/OrcamentoEstado/Paginas/DetalhePropostaAlteracao.aspx?BID=24520 | AG26: https://app.parlamento.pt/webutils/docs/doc.pdf?path=6148523063484d364c793942556b356c6443397a6158526c63793959566b6c4a544556484c3039464c7a49774d6a59794d4449314d5441774f5339515153396c4f47457a4d32517a5a43316d4d7a646d4c545132597a4d744f444e685a4330304e7a45784e44637a4d3245784f5463756347526d&Fich=e8a33d3d-f37f-46c3-83ad-47114733a197.pdf&Inline=true | AH26: 46321.778 | AI26: 46321.781
A27: 26 | B27: 22C | C27: 45959.421 | D27: Original | E27: PAN | F27: Inês de Sousa Real | G27: Art. 11.º-A (aditamento) | L27: Artigo 11.º-A (Portal Queixa Eletrónica) | S27: Aprovado(a) em Comissão | T27: Aprovada | U27: Favor: CH, PS, L, PCP, BE, PAN; Contra: PSD, CDS-PP; Abstenção: IL | V27: 45981 | W27: AR: https://www.parlamento.pt/OrcamentoEstado/Paginas/DetalhePropostaAlteracao.aspx?BID=23215 PDF: https://app.parlamento.pt/webutils/docs/doc.pdf?path=6148523063484d364c793942556b356c6443397a6158526c63793959566b6c4a544556484c3039464c7a49774d6a59794d4449314d5441774f533951515338335a6a4d794d4441315953316a4e4751784c5451334e6a41744f5467354e79307a4d474d784e44566a4d7a51314e4745756347526d&Fich=7f32005a-c4d1-4760-9897-30c145c3454a.pdf&Inline=true | X27: Assuntos Constitucionais, Direitos, Liberdades e Garantias | Y27: Articulado | Z27: Aditamento (Artigo PPL) | AA27: Aprovado(a) em Comissão | AD27: 1 | AE27: 23215 | AF27: https://www.parlamento.pt/OrcamentoEstado/Paginas/DetalhePropostaAlteracao.aspx?BID=23215 | AG27: https://app.parlamento.pt/webutils/docs/doc.pdf?path=6148523063484d364c793942556b356c6443397a6158526c63793959566b6c4a544556484c3039464c7a49774d6a59794d4449314d5441774f533951515338335a6a4d794d4441315953316a4e4751784c5451334e6a41744f5467354e79307a4d474d784e44566a4d7a51314e4745756347526d&Fich=7f32005a-c4d1-4760-9897-30c145c3454a.pdf&Inline=true | AH27: 46321.778 | AI27: 46321.781
A28: 27 | B28: 23C | C28: 45959.423 | D28: Original | E28: PAN | F28: Inês de Sousa Real | G28: Art. 11.º-B (aditamento) | L28: Artigo 11.º-B (Enquadramento de práticas tradicionais nefastas no âmbito do Portal Queixa Eletrónica) | S28: Rejeitado(a) em Comissão | T28: Rejeitada | U28: Favor: CH, IL, L, PCP, BE, PAN; Contra: PSD; Abstenção: PS, CDS-PP | V28: 45981 | W28: AR: https://www.parlamento.pt/OrcamentoEstado/Paginas/DetalhePropostaAlteracao.aspx?BID=23216 PDF: https://app.parlamento.pt/webutils/docs/doc.pdf?path=6148523063484d364c793942556b356c6443397a6158526c63793959566b6c4a544556484c3039464c7a49774d6a59794d4449314d5441774f5339515153396d5a6a49784d54566b4d69316c4e5463794c545177595755744f4463314e53316b4d325a6b5a5755794d47457a596a4d756347526d&Fich=ff2115d2-e572-40ae-8755-d3fdee20a3b3.pdf&Inline=true | X28: Assuntos Constitucionais, Direitos, Liberdades e Garantias | Y28: Articulado | Z28: Aditamento (Artigo PPL) | AA28: Rejeitado(a) em Comissão | AD28: 1 | AE28: 23216 | AF28: https://www.parlamento.pt/OrcamentoEstado/Paginas/DetalhePropostaAlteracao.aspx?BID=23216 | AG28: https://app.parlamento.pt/webutils/docs/doc.pdf?path=6148523063484d364c793942556b356c6443397a6158526c63793959566b6c4a544556484c3039464c7a49774d6a59794d4449314d5441774f5339515153396d5a6a49784d54566b4d69316c4e5463794c545177595755744f4463314e53316b4d325a6b5a5755794d47457a596a4d756347526d&Fich=ff2115d2-e572-40ae-8755-d3fdee20a3b3.pdf&Inline=true | AH28: 46321.778 | AI28: 46321.781
A29: 28 | B29: 24C | C29: 45959.424 | D29: Original | E29: PAN | F29: Inês de Sousa Real | G29: Art. 129.º-B (aditamento) | L29: Artigo 129.º-B (Prevenção da corrupção na Administração Pública) | S29: Aprovado(a) em Comissão | T29: Aprovada | U29: Favor: CH, IL, L, PCP, BE, PAN; Abstenção: PSD, PS, CDS-PP | V29: 45985 | W29: AR: https://www.parlamento.pt/OrcamentoEstado/Paginas/DetalhePropostaAlteracao.aspx?BID=23217 PDF: https://app.parlamento.pt/webutils/docs/doc.pdf?path=6148523063484d364c793942556b356c6443397a6158526c63793959566b6c4a544556484c3039464c7a49774d6a59794d4449314d5441774f533951515339694d6a67794e6a497a5a4330344e4446694c5451794f4755744f5459774f4330774e47466d4e54426a5a575934595745756347526d&Fich=b282623d-841b-428e-9608-04af50cef8aa.pdf&Inline=true | X29: Orçamento, Finanças e Administração Pública | Y29: Articulado | Z29: Aditamento (Artigo PPL) | AA29: Aprovado(a) em Comissão | AD29: 1 | AE29: 23217 | AF29: https://www.parlamento.pt/OrcamentoEstado/Paginas/DetalhePropostaAlteracao.aspx?BID=23217 | AG29: https://app.parlamento.pt/webutils/docs/doc.pdf?path=6148523063484d364c793942556b356c6443397a6158526c63793959566b6c4a544556484c3039464c7a49774d6a59794d4449314d5441774f533951515339694d6a67794e6a497a5a4330344e4446694c5451794f4755744f5459774f4330774e47466d4e54426a5a575934595745756347526d&Fich=b282623d-841b-428e-9608-04af50cef8aa.pdf&Inline=true | AH29: 46321.778 | AI29: 46321.781
A30: 29 | B30: 25C | C30: 45959.424 | D30: Original | E30: PAN | F30: Inês de Sousa Real | G30: Art. 108.º-A (aditamento) | L30: Artigo 108.º-A (Programa Nacional de financiamento da rede de centros de recuperação de fauna selvagem) | S30: Rejeitado(a) em Comissão | T30: Rejeitada | U30: Favor: CH, L, PCP, BE, PAN; Contra: PSD, IL, CDS-PP; Abstenção: PS | V30: 45982 | W30: AR: https://www.parlamento.pt/OrcamentoEstado/Paginas/DetalhePropostaAlteracao.aspx?BID=23218 PDF: https://app.parlamento.pt/webutils/docs/doc.pdf?path=6148523063484d364c793942556b356c6443397a6158526c63793959566b6c4a544556484c3039464c7a49774d6a59794d4449314d5441774f533951515338784d6a6c6c4f574e684e5330334d5749774c5451794f446b7459575530597931694e574e6d4e7a59355a4464694f4745756347526d&Fich=129e9ca5-71b0-4289-ae4c-b5cf769d7b8a.pdf&Inline=true | X30: Agricultura e Pescas; Ambiente e Energia | Y30: Articulado | Z30: Aditamento (Artigo PPL) | AA30: Rejeitado(a) em Comissão | AD30: 1 | AE30: 23218 | AF30: https://www.parlamento.pt/OrcamentoEstado/Paginas/DetalhePropostaAlteracao.aspx?BID=23218 | AG30: https://app.parlamento.pt/webutils/docs/doc.pdf?path=6148523063484d364c793942556b356c6443397a6158526c63793959566b6c4a544556484c3039464c7a49774d6a59794d4449314d5441774f533951515338784d6a6c6c4f574e684e5330334d5749774c5451794f446b7459575530597931694e574e6d4e7a59355a4464694f4745756347526d&Fich=129e9ca5-71b0-4289-ae4c-b5cf769d7b8a.pdf&Inline=true | AH30: 46321.778 | AI30: 46321.781
A31: 30 | B31: 26C | C31: 45959.424 | D31: Original | E31: PAN | F31: Inês de Sousa Real | G31: Art. 129.º-A (aditamento) | L31: Artigo 129.º-A (Reforço do combate à corrupção, fraude e criminalidade económico-financeira) | S31: Aprovado(a) Parcialmente em Comissão | T31: Aprovada parcialmente | U31: Favor: PSD, CH, IL, L, PCP, CDS-PP, BE, PAN; Abstenção: PS | V31: 45985 | W31: AR: https://www.parlamento.pt/OrcamentoEstado/Paginas/DetalhePropostaAlteracao.aspx?BID=23219 PDF: https://app.parlamento.pt/webutils/docs/doc.pdf?path=6148523063484d364c793942556b356c6443397a6158526c63793959566b6c4a544556484c3039464c7a49774d6a59794d4449314d5441774f533951515338334d6a68694e6a5532597930794d4445784c5451354e6a49744f5745354d5330794e57526b4d54686a4f54646c4f4745756347526d&Fich=728b656c-2011-4962-9a91-25dd18c97e8a.pdf&Inline=true | X31: Assuntos Constitucionais, Direitos, Liberdades e Garantias; Orçamento, Finanças e Administração Pública | Y31: Articulado | Z31: Aditamento (Artigo PPL) | AA31: Aprovado(a) Parcialmente em Comissão | AD31: 1 | AE31: 23219 | AF31: https://www.parlamento.pt/OrcamentoEstado/Paginas/DetalhePropostaAlteracao.aspx?BID=23219 | AG31: https://app.parlamento.pt/webutils/docs/doc.pdf?path=6148523063484d364c793942556b356c6443397a6158526c63793959566b6c4a544556484c3039464c7a49774d6a59794d4449314d5441774f533951515338334d6a68694e6a5532597930794d4445784c5451354e6a49744f5745354d5330794e57526b4d54686a4f54646c4f4745756347526d&Fich=728b656c-2011-4962-9a91-25dd18c97e8a.pdf&Inline=true | AH31: 46321.778 | AI31: 46321.781
A32: 31 | B32: 27C | C32: 45959.424 | D32: Original | E32: PAN | F32: Inês de Sousa Real | G32: Art. 108.º-B (aditamento) | L32: Artigo 108.º-B (Revisão da Portaria n.º 1112/2009, de 28 de setembro) | S32: Rejeitado(a) em Comissão | T32: Rejeitada | U32: Favor: CH, L, PCP, BE, PAN; Contra: PSD, CDS-PP; Abstenção: PS, IL | V32: 45982 | W32: AR: https://www.parlamento.pt/OrcamentoEstado/Paginas/DetalhePropostaAlteracao.aspx?BID=23220 PDF: https://app.parlamento.pt/webutils/docs/doc.pdf?path=6148523063484d364c793942556b356c6443397a6158526c63793959566b6c4a544556484c3039464c7a49774d6a59794d4449314d5441774f5339515153396a4e6a5135596a67774d69316a4e5756684c5451314e575174595463304f4331684d7a426d4e47566b4e5755304d4749756347526d&Fich=c649b802-c5ea-455d-a748-a30f4ed5e40b.pdf&Inline=true | X32: Agricultura e Pescas; Ambiente e Energia | Y32: Articulado | Z32: Aditamento (Artigo PPL) | AA32: Rejeitado(a) em Comissão | AD32: 1 | AE32: 23220 | AF32: https://www.parlamento.pt/OrcamentoEstado/Paginas/DetalhePropostaAlteracao.aspx?BID=23220 | AG32: https://app.parlamento.pt/webutils/docs/doc.pdf?path=6148523063484d364c793942556b356c6443397a6158526c63793959566b6c4a544556484c3039464c7a49774d6a59794d4449314d5441774f5339515153396a4e6a5135596a67774d69316a4e5756684c5451314e575174595463304f4331684d7a426d4e47566b4e5755304d4749756347526d&Fich=c649b802-c5ea-455d-a748-a30f4ed5e40b.pdf&Inline=true | AH32: 46321.778 | AI32: 46321.781
A33: 32 | B33: 28C | C33: 45959.426 | D33: Original | E33: PAN | F33: Inês de Sousa Real | G33: Art. 108.º-A (aditamento) | L33: Artigo 108.º-A (Criação da linha telefónica nacional de socorro animal) | S33: Rejeitado(a) em Comissão | T33: Rejeitada | U33: Favor: CH, L, BE, PAN; Contra: PSD, IL, PCP, CDS-PP; Abstenção: PS | V33: 45982 | W33: AR: https://www.parlamento.pt/OrcamentoEstado/Paginas/DetalhePropostaAlteracao.aspx?BID=23221 PDF: https://app.parlamento.pt/webutils/docs/doc.pdf?path=6148523063484d364c793942556b356c6443397a6158526c63793959566b6c4a544556484c3039464c7a49774d6a59794d4449314d5441774f533951515339684f544931596a4d31596930344f54557a4c5451344e7a4174596a4533597930784d54686b4e6d45345a5755785a4449756347526d&Fich=a925b35b-8953-4870-b17c-118d6a8ee1d2.pdf&Inline=true | X33: Agricultura e Pescas; Ambiente e Energia | Y33: Articulado | Z33: Aditamento (Artigo PPL) | AA33: Rejeitado(a) em Comissão | AD33: 1 | AE33: 23221 | AF33: https://www.parlamento.pt/OrcamentoEstado/Paginas/DetalhePropostaAlteracao.aspx?BID=23221 | AG33: https://app.parlamento.pt/webutils/docs/doc.pdf?path=6148523063484d364c793942556b356c6443397a6158526c63793959566b6c4a544556484c3039464c7a49774d6a59794d4449314d5441774f533951515339684f544931596a4d31596930344f54557a4c5451344e7a4174596a4533597930784d54686b4e6d45345a5755785a4449756347526d&Fich=a925b35b-8953-4870-b17c-118d6a8ee1d2.pdf&Inline=true | AH33: 46321.778 | AI33: 46321.781
A34: 33 | B34: 29C | C34: 45959.426 | D34: Original | E34: PAN | F34: Inês de Sousa Real | G34: Art. 109.º-A (aditamento) | L34: Artigo 109.º-A (Extensão da Cobertura dos Seguros Multirriscos Habitação a Situações de Violência Doméstica) | S34: Rejeitado(a) em Comissão | T34: Rejeitada | U34: Favor: L, BE, PAN; Contra: PSD, PS, IL, CDS-PP; Abstenção: CH, PCP | V34: 45982 | W34: AR: https://www.parlamento.pt/OrcamentoEstado/Paginas/DetalhePropostaAlteracao.aspx?BID=23222 PDF: https://app.parlamento.pt/webutils/docs/doc.pdf?path=6148523063484d364c793942556b356c6443397a6158526c63793959566b6c4a544556484c3039464c7a49774d6a59794d4449314d5441774f533951515338354d574e6a4f4751344d5330784e47597a4c5451354d474d744f44566b4e79307a5932526c595463785954426a596a51756347526d&Fich=91cc8d81-14f3-490c-85d7-3cdea71a0cb4.pdf&Inline=true | X34: Assuntos Constitucionais, Direitos, Liberdades e Garantias; Infraestruturas, Mobilidade e Habitação | Y34: Articulado | Z34: Aditamento (Artigo PPL) | AA34: Rejeitado(a) em Comissão | AD34: 1 | AE34: 23222 | AF34: https://www.parlamento.pt/OrcamentoEstado/Paginas/DetalhePropostaAlteracao.aspx?BID=23222 | AG34: https://app.parlamento.pt/webutils/docs/doc.pdf?path=6148523063484d364c793942556b356c6443397a6158526c63793959566b6c4a544556484c3039464c7a49774d6a59794d4449314d5441774f533951515338354d574e6a4f4751344d5330784e47597a4c5451354d474d744f44566b4e79307a5932526c595463785954426a596a51756347526d&Fich=91cc8d81-14f3-490c-85d7-3cdea71a0cb4.pdf&Inline=true | AH34: 46321.778 | AI34: 46321.781
A35: 34 | B35: 30C | C35: 45959.426 | D35: Original | E35: PAN | F35: Inês de Sousa Real | G35: Art. 108.º (aditamento) | L35: Novo N.º 3, Artigo 108.º | S35: Rejeitado(a) em Comissão | T35: Rejeitada | U35: Favor: CH, IL, L, BE, PAN; Contra: PSD, CDS-PP; Abstenção: PS, PCP | V35: 45982 | W35: AR: https://www.parlamento.pt/OrcamentoEstado/Paginas/DetalhePropostaAlteracao.aspx?BID=23223 PDF: https://app.parlamento.pt/webutils/docs/doc.pdf?path=6148523063484d364c793942556b356c6443397a6158526c63793959566b6c4a544556484c3039464c7a49774d6a59794d4449314d5441774f533951515338794d47557a4e7a64695a43303159574d794c5452684e6a41745954526a4d7930314e325a6a5a6a5a6a4f544d77595749756347526d&Fich=20e377bd-5ac2-4a60-a4c3-57fcf6c930ab.pdf&Inline=true | X35: Agricultura e Pescas | Y35: Articulado | Z35: Aditamento (Números e Alíneas) | AA35: Rejeitado(a) em Comissão | AD35: 1 | AE35: 23223 | AF35: https://www.parlamento.pt/OrcamentoEstado/Paginas/DetalhePropostaAlteracao.aspx?BID=23223 | AG35: https://app.parlamento.pt/webutils/docs/doc.pdf?path=6148523063484d364c793942556b356c6443397a6158526c63793959566b6c4a544556484c3039464c7a49774d6a59794d4449314d5441774f533951515338794d47557a4e7a64695a43303159574d794c5452684e6a41745954526a4d7930314e325a6a5a6a5a6a4f544d77595749756347526d&Fich=20e377bd-5ac2-4a60-a4c3-57fcf6c930ab.pdf&Inline=true | AH35: 46321.778 | AI35: 46321.781
A36: 35 | B36: 31C | C36: 45959.426 | D36: Original | E36: PAN | F36: Inês de Sousa Real | G36: Art. 11.º-C (aditamento) | L36: Artigo 11.º-C (Prevenção e combate da Mutilação Genital Feminina) | S36: Aprovado(a) em Comissão | T36: Aprovada | U36: Favor: CH, PS, IL, L, PCP, BE, PAN; Contra: PSD; Abstenção: CDS-PP | V36: 45981 | W36: AR: https://www.parlamento.pt/OrcamentoEstado/Paginas/DetalhePropostaAlteracao.aspx?BID=23224 PDF: https://app.parlamento.pt/webutils/docs/doc.pdf?path=6148523063484d364c793942556b356c6443397a6158526c63793959566b6c4a544556484c3039464c7a49774d6a59794d4449314d5441774f533951515338334d6a6b314e6a59794e4330345a444e684c54526d596a4d744f4751774e7930334d7a6b775932526d4e6d5978596d51756347526d&Fich=72956624-8d3a-4fb3-8d07-7390cdf6f1bd.pdf&Inline=true | X36: Assuntos Constitucionais, Direitos, Liberdades e Garantias; Saúde | Y36: Articulado | Z36: Aditamento (Artigo PPL) | AA36: Aprovado(a) em Comissão | AD36: 1 | AE36: 23224 | AF36: https://www.parlamento.pt/OrcamentoEstado/Paginas/DetalhePropostaAlteracao.aspx?BID=23224 | AG36: https://app.parlamento.pt/webutils/docs/doc.pdf?path=6148523063484d364c793942556b356c6443397a6158526c63793959566b6c4a544556484c3039464c7a49774d6a59794d4449314d5441774f533951515338334d6a6b314e6a59794e4330345a444e684c54526d596a4d744f4751774e7930334d7a6b775932526d4e6d5978596d51756347526d&Fich=72956624-8d3a-4fb3-8d07-7390cdf6f1bd.pdf&Inline=true | AH36: 46321.778 | AI36: 46321.781
A37: 36 | B37: 32C | C37: 45959.428 | D37: Original | E37: PAN | F37: Inês de Sousa Real | G37: Art. 101.º-A (aditamento) | L37: Artigo 101.º-A (Programa nacional de apoio às cooperativas de habitação) | S37: Rejeitado(a) em Comissão | T37: Rejeitada | U37: Favor: L, PCP, BE, PAN; Contra: PSD, IL, CDS-PP; Abstenção: CH, PS | V37: 45982 | W37: AR: https://www.parlamento.pt/OrcamentoEstado/Paginas/DetalhePropostaAlteracao.aspx?BID=23225 PDF: https://app.parlamento.pt/webutils/docs/doc.pdf?path=6148523063484d364c793942556b356c6443397a6158526c63793959566b6c4a544556484c3039464c7a49774d6a59794d4449314d5441774f533951515338775a4745324d32497a4d43316c4e44677a4c545179596a5574596d51304d79316d596a6b7a4d544d785a6d45304e6d55756347526d&Fich=0da63b30-e483-42b5-bd43-fb93131fa46e.pdf&Inline=true | X37: Infraestruturas, Mobilidade e Habitação | Y37: Articulado | Z37: Aditamento (Artigo PPL) | AA37: Rejeitado(a) em Comissão | AD37: 1 | AE37: 23225 | AF37: https://www.parlamento.pt/OrcamentoEstado/Paginas/DetalhePropostaAlteracao.aspx?BID=23225 | AG37: https://app.parlamento.pt/webutils/docs/doc.pdf?path=6148523063484d364c793942556b356c6443397a6158526c63793959566b6c4a544556484c3039464c7a49774d6a59794d4449314d5441774f533951515338775a4745324d32497a4d43316c4e44677a4c545179596a5574596d51304d79316d596a6b7a4d544d785a6d45304e6d55756347526d&Fich=0da63b30-e483-42b5-bd43-fb93131fa46e.pdf&Inline=true | AH37: 46321.778 | AI37: 46321.781
A38: 37 | B38: 33C | C38: 45959.428 | D38: Original | E38: PAN | F38: Inês de Sousa Real | G38: Art. 10.º-A (aditamento) | L38: Artigo 10.º-A (Alargamento do Porta 65+ às vítimas de violência doméstica) | S38: Aprovado(a) por Unanimidade em Comissão | T38: Aprovada | U38: Favor: PSD, CH, PS, IL, L, PCP, CDS-PP, BE, PAN | V38: 45981 | W38: AR: https://www.parlamento.pt/OrcamentoEstado/Paginas/DetalhePropostaAlteracao.aspx?BID=23226 PDF: https://app.parlamento.pt/webutils/docs/doc.pdf?path=6148523063484d364c793942556b356c6443397a6158526c63793959566b6c4a544556484c3039464c7a49774d6a59794d4449314d5441774f5339515153387a4f544e6d596a4e6b4d7930784e574a6d4c54526a4d545574596d55774e4330304f474579596a41314e6a52695a446b756347526d&Fich=393fb3d3-15bf-4c15-be04-48a2b0564bd9.pdf&Inline=true | X38: Assuntos Constitucionais, Direitos, Liberdades e Garantias; Infraestruturas, Mobilidade e Habitação | Y38: Articulado | Z38: Aditamento (Artigo PPL) | AA38: Aprovado(a) por Unanimidade em Comissão | AD38: 1 | AE38: 23226 | AF38: https://www.parlamento.pt/OrcamentoEstado/Paginas/DetalhePropostaAlteracao.aspx?BID=23226 | AG38: https://app.parlamento.pt/webutils/docs/doc.pdf?path=6148523063484d364c793942556b356c6443397a6158526c63793959566b6c4a544556484c3039464c7a49774d6a59794d4449314d5441774f5339515153387a4f544e6d596a4e6b4d7930784e574a6d4c54526a4d545574596d55774e4330304f474579596a41314e6a52695a446b756347526d&Fich=393fb3d3-15bf-4c15-be04-48a2b0564bd9.pdf&Inline=true | AH38: 46321.778 | AI38: 46321.781
A39: 38 | B39: 34C | C39: 45959.429 | D39: Original | E39: PAN | F39: Inês de Sousa Real | G39: Art. 120.º-A (aditamento) | L39: Artigo 120.º-A (Kits emergenciais para vítimas de abuso sexual e violação) | S39: Aprovado(a) por Unanimidade em Comissão | T39: Aprovada | U39: Favor: PSD, CH, PS, L, PCP, CDS-PP, BE, PAN | V39: 45985 | W39: AR: https://www.parlamento.pt/OrcamentoEstado/Paginas/DetalhePropostaAlteracao.aspx?BID=23227 PDF: https://app.parlamento.pt/webutils/docs/doc.pdf?path=6148523063484d364c793942556b356c6443397a6158526c63793959566b6c4a544556484c3039464c7a49774d6a59794d4449314d5441774f5339515153396b5a6a67794f5752694e6930334d5759354c5451305a6d4d744f5463784e7930324e7a59314d7a45354d5445334d6d49756347526d&Fich=df829db6-71f9-44fc-9717-67653191172b.pdf&Inline=true | X39: Assuntos Constitucionais, Direitos, Liberdades e Garantias; Saúde | Y39: Articulado | Z39: Aditamento (Artigo PPL) | AA39: Aprovado(a) por Unanimidade em Comissão | AD39: 1 | AE39: 23227 | AF39: https://www.parlamento.pt/OrcamentoEstado/Paginas/DetalhePropostaAlteracao.aspx?BID=23227 | AG39: https://app.parlamento.pt/webutils/docs/doc.pdf?path=6148523063484d364c793942556b356c6443397a6158526c63793959566b6c4a544556484c3039464c7a49774d6a59794d4449314d5441774f5339515153396b5a6a67794f5752694e6930334d5759354c5451305a6d4d744f5463784e7930324e7a59314d7a45354d5445334d6d49756347526d&Fich=df829db6-71f9-44fc-9717-67653191172b.pdf&Inline=true | AH39: 46321.778 | AI39: 46321.781
A40: 39 | B40: 35C | C40: 45959.429 | D40: Original | E40: IL | F40: Angélique Da Teresa; Carlos Guimarães Pinto; Joana Cordeiro; Jorge Miguel Teixeira; Mariana Leitão; Mário Amorim Lopes; Miguel Rangel; Rodrigo Saraiva; Rui Rocha | G40: Art. 138.º (aditamento) | L40: Alínea c), Artigo 138.º | S40: Rejeitado(a) em Plenário | T40: Rejeitada | U40: Favor: CH, IL; Contra: PSD, PS, L, PCP, BE, PAN; Abstenção: CDS-PP, JPP | V40: 45988 | W40: Avocada a Plenário. AR: https://www.parlamento.pt/OrcamentoEstado/Paginas/DetalhePropostaAlteracao.aspx?BID=23228 PDF: https://app.parlamento.pt/webutils/docs/doc.pdf?path=6148523063484d364c793942556b356c6443397a6158526c63793959566b6c4a544556484c3039464c7a49774d6a59794d4449314d5441774f533951515338784f446869596a637a4e4330794e6d45344c5451354e6a51744f4441314d693034595746694e6a63314e7a55334e6a67756347526d&Fich=188bb734-26a8-4964-8052-8aab67575768.pdf&Inline=true | X40: Infraestruturas, Mobilidade e Habitação; Orçamento, Finanças e Administração Pública | Y40: Articulado | Z40: Aditamento (Números e Alíneas) | AA40: Rejeitado(a) em Plenário | AB40: S | AD40: 2 | AE40: 23228 | AF40: https://www.parlamento.pt/OrcamentoEstado/Paginas/DetalhePropostaAlteracao.aspx?BID=23228 | AG40: https://app.parlamento.pt/webutils/docs/doc.pdf?path=6148523063484d364c793942556b356c6443397a6158526c63793959566b6c4a544556484c3039464c7a49774d6a59794d4449314d5441774f533951515338784f446869596a637a4e4330794e6d45344c5451354e6a51744f4441314d693034595746694e6a63314e7a55334e6a67756347526d&Fich=188bb734-26a8-4964-8052-8aab67575768.pdf&Inline=true | AH40: 46321.778 | AI40: 46321.781
A41: 40 | B41: 36C | C41: 45959.431 | D41: Original | E41: PAN | F41: Inês de Sousa Real | G41: Art. 99.º-A (aditamento) | L41: Artigo 99.º-A (Utilização Inteligência Artificial para a prevenção de incêndios florestais) | S41: Rejeitado(a) em Comissão | T41: Rejeitada | U41: Favor: IL, L, PAN; Contra: PSD, CDS-PP; Abstenção: CH, PS, PCP, BE | V41: 45982 | W41: AR: https://www.parlamento.pt/OrcamentoEstado/Paginas/DetalhePropostaAlteracao.aspx?BID=23229 PDF: https://app.parlamento.pt/webutils/docs/doc.pdf?path=6148523063484d364c793942556b356c6443397a6158526c63793959566b6c4a544556484c3039464c7a49774d6a59794d4449314d5441774f5339515153396b4f5468694e6a63784d7930324e57566c4c54517a5a6a4174596a49794e43316c4e6a45794e546b79597a46684e6a59756347526d&Fich=d98b6713-65ee-43f0-b224-e612592c1a66.pdf&Inline=true | X41: Ambiente e Energia | Y41: Articulado | Z41: Aditamento (Artigo PPL) | AA41: Rejeitado(a) em Comissão | AD41: 1 | AE41: 23229 | AF41: https://www.parlamento.pt/OrcamentoEstado/Paginas/DetalhePropostaAlteracao.aspx?BID=23229 | AG41: https://app.parlamento.pt/webutils/docs/doc.pdf?path=6148523063484d364c793942556b356c6443397a6158526c63793959566b6c4a544556484c3039464c7a49774d6a59794d4449314d5441774f5339515153396b4f5468694e6a63784d7930324e57566c4c54517a5a6a4174596a49794e43316c4e6a45794e546b79597a46684e6a59756347526d&Fich=d98b6713-65ee-43f0-b224-e612592c1a66.pdf&Inline=true | AH41: 46321.778 | AI41: 46321.781
A42: 41 | B42: 37C | C42: 45959.431 | D42: Original | E42: PAN | F42: Inês de Sousa Real | G42: Art. 66.º (aditamento) | L42: N.º 11, N.º 12, Artigo 66.º | S42: Rejeitado(a) em Comissão | T42: Rejeitada | U42: Favor: IL, L, BE, PAN; Contra: PSD, CDS-PP; Abstenção: CH, PS, PCP | V42: 45982 | W42: AR: https://www.parlamento.pt/OrcamentoEstado/Paginas/DetalhePropostaAlteracao.aspx?BID=23230 PDF: https://app.parlamento.pt/webutils/docs/doc.pdf?path=6148523063484d364c793942556b356c6443397a6158526c63793959566b6c4a544556484c3039464c7a49774d6a59794d4449314d5441774f533951515338354f4759315a4745354f4330325a54466b4c54526c59324d7459544e684e6930315a6a566b4e5759344f57457959574d756347526d&Fich=98f5da98-6e1d-4ecc-a3a6-5f5d5f89a2ac.pdf&Inline=true | X42: Ambiente e Energia; Orçamento, Finanças e Administração Pública | Y42: Articulado | Z42: Aditamento (Números e Alíneas) | AA42: Rejeitado(a) em Comissão | AD42: 1 | AE42: 23230 | AF42: https://www.parlamento.pt/OrcamentoEstado/Paginas/DetalhePropostaAlteracao.aspx?BID=23230 | AG42: https://app.parlamento.pt/webutils/docs/doc.pdf?path=6148523063484d364c793942556b356c6443397a6158526c63793959566b6c4a544556484c3039464c7a49774d6a59794d4449314d5441774f533951515338354f4759315a4745354f4330325a54466b4c54526c59324d7459544e684e6930315a6a566b4e5759344f57457959574d756347526d&Fich=98f5da98-6e1d-4ecc-a3a6-5f5d5f89a2ac.pdf&Inline=true | AH42: 46321.778 | AI42: 46321.781
A43: 42 | B43: 38C | C43: 45959.431 | D43: Original | E43: PAN | F43: Inês de Sousa Real | G43: Art. 10.º-A (aditamento) | L43: Artigo 10.º-A (Transparência em matéria de política climática) | S43: Rejeitado(a) em Comissão | T43: Rejeitada | U43: Favor: PS, IL, L, PCP, BE, PAN; Contra: PSD, CDS-PP; Abstenção: CH | V43: 45981 | W43: AR: https://www.parlamento.pt/OrcamentoEstado/Paginas/DetalhePropostaAlteracao.aspx?BID=23231 PDF: https://app.parlamento.pt/webutils/docs/doc.pdf?path=6148523063484d364c793942556b356c6443397a6158526c63793959566b6c4a544556484c3039464c7a49774d6a59794d4449314d5441774f5339515153396c5954686d4e446c6d4d4330794d7a55794c54526a5a6a5174596d59314d5330304e6d4e6d4d546c695a444e6c4e6a67756347526d&Fich=ea8f49f0-2352-4cf4-bf51-46cf19bd3e68.pdf&Inline=true | X43: Ambiente e Energia; Orçamento, Finanças e Administração Pública | Y43: Articulado | Z43: Aditamento (Artigo PPL) | AA43: Rejeitado(a) em Comissão | AD43: 1 | AE43: 23231 | AF43: https://www.parlamento.pt/OrcamentoEstado/Paginas/DetalhePropostaAlteracao.aspx?BID=23231 | AG43: https://app.parlamento.pt/webutils/docs/doc.pdf?path=6148523063484d364c793942556b356c6443397a6158526c63793959566b6c4a544556484c3039464c7a49774d6a59794d4449314d5441774f5339515153396c5954686d4e446c6d4d4330794d7a55794c54526a5a6a5174596d59314d5330304e6d4e6d4d546c695a444e6c4e6a67756347526d&Fich=ea8f49f0-2352-4cf4-bf51-46cf19bd3e68.pdf&Inline=true | AH43: 46321.778 | AI43: 46321.781
A44: 43 | B44: 39C-1 | C44: 45959.433 | D44: Original | E44: PAN | F44: Inês de Sousa Real | G44: Art. 66.º (substituição) | L44: N.º 3, N.º 7, N.º 10, Artigo 66.º | S44: Rejeitado(a) em Comissão | T44: Rejeitada | U44: Favor: PSD, L, CDS-PP, BE, PAN; Contra: CH, PS, PCP; Abstenção: IL | V44: 45982 | W44: AR: https://www.parlamento.pt/OrcamentoEstado/Paginas/DetalhePropostaAlteracao.aspx?BID=23232 PDF: https://app.parlamento.pt/webutils/docs/doc.pdf?path=6148523063484d364c793942556b356c6443397a6158526c63793959566b6c4a544556484c3039464c7a49774d6a59794d4449314d5441774f533951515338354f4459774e5445334d5330774f444d7a4c54526d4d4459744f4751345969316d4d3249784e4451314e4755324e4745756347526d&Fich=98605171-0833-4f06-8d8b-f3b14454e64a.pdf&Inline=true | X44: Ambiente e Energia; Orçamento, Finanças e Administração Pública | Y44: Articulado | Z44: Substituição | AA44: Rejeitado(a) em Comissão | AC44: 1 | AD44: 1 | AE44: 23232 | AF44: https://www.parlamento.pt/OrcamentoEstado/Paginas/DetalhePropostaAlteracao.aspx?BID=23232 | AG44: https://app.parlamento.pt/webutils/docs/doc.pdf?path=6148523063484d364c793942556b356c6443397a6158526c63793959566b6c4a544556484c3039464c7a49774d6a59794d4449314d5441774f533951515338354f4459774e5445334d5330774f444d7a4c54526d4d4459744f4751345969316d4d3249784e4451314e4755324e4745756347526d&Fich=98605171-0833-4f06-8d8b-f3b14454e64a.pdf&Inline=true | AH44: 46321.778 | AI44: 46321.781
A45: 44 | B45: 39C-2 | C45: 45959.433 | D45: Original | E45: PAN | F45: Inês de Sousa Real | G45: Art. 66.º (aditamento) | L45: Novo N.º 11, Artigo 66.º | S45: Rejeitado(a) em Comissão | T45: Rejeitada | U45: Favor: PSD, CDS-PP, BE, PAN; Contra: CH, PS; Abstenção: IL, L, PCP | V45: 45982 | W45: AR: https://www.parlamento.pt/OrcamentoEstado/Paginas/DetalhePropostaAlteracao.aspx?BID=23491 PDF: https://app.parlamento.pt/webutils/docs/doc.pdf?path=6148523063484d364c793942556b356c6443397a6158526c63793959566b6c4a544556484c3039464c7a49774d6a59794d4449314d5441774f5339515153396d4d7a5a6a4f44566a4d5330304f444a6b4c5451324e6a63744f574d324d53316d4e6a63334f54566a4e3251334e4459756347526d&Fich=f36c85c1-482d-4667-9c61-f67795c7d746.pdf&Inline=true | X45: Ambiente e Energia; Orçamento, Finanças e Administração Pública | Y45: Articulado | Z45: Aditamento (Números e Alíneas) | AA45: Rejeitado(a) em Comissão | AC45: 2 | AD45: 1 | AE45: 23491 | AF45: https://www.parlamento.pt/OrcamentoEstado/Paginas/DetalhePropostaAlteracao.aspx?BID=23491 | AG45: https://app.parlamento.pt/webutils/docs/doc.pdf?path=6148523063484d364c793942556b356c6443397a6158526c63793959566b6c4a544556484c3039464c7a49774d6a59794d4449314d5441774f5339515153396d4d7a5a6a4f44566a4d5330304f444a6b4c5451324e6a63744f574d324d53316d4e6a63334f54566a4e3251334e4459756347526d&Fich=f36c85c1-482d-4667-9c61-f67795c7d746.pdf&Inline=true | AH45: 46321.778 | AI45: 46321.781
A46: 45 | B46: 40C-1 | C46: 45959.506 | D46: Original | E46: L | F46: Filipa Pinto; Isabel Mendes Lopes; Jorge Pinto; Patrícia Gonçalves; Paulo Muacho; Rui Tavares | G46: Art. 63.º-A (aditamento) | L46: Artigo 63.º-A (Alteração ao artigo 18.º do Código do Imposto sobre o Valor Acrescentado) | S46: Rejeitado(a) em Comissão | T46: Rejeitada | U46: Favor: L, PCP, BE, PAN; Contra: PSD, CDS-PP; Abstenção: CH, PS, IL | V46: 45982 | W46: AR: https://www.parlamento.pt/OrcamentoEstado/Paginas/DetalhePropostaAlteracao.aspx?BID=23233 PDF: https://app.parlamento.pt/webutils/docs/doc.pdf?path=6148523063484d364c793942556b356c6443397a6158526c63793959566b6c4a544556484c3039464c7a49774d6a59794d4449314d5441774f533951515338304e6a51324f544d33597930344e3245324c54526a4f5455744f546c694f4330775a4451304d446335596d4e6d4e6a49756347526d&Fich=4646937c-87a6-4c95-99b8-0d44079bcf62.pdf&Inline=true | X46: Orçamento, Finanças e Administração Pública | Y46: Articulado | Z46: Aditamento (Artigo PPL) | AA46: Rejeitado(a) em Comissão | AC46: 1 | AD46: 1 | AE46: 23233 | AF46: https://www.parlamento.pt/OrcamentoEstado/Paginas/DetalhePropostaAlteracao.aspx?BID=23233 | AG46: https://app.parlamento.pt/webutils/docs/doc.pdf?path=6148523063484d364c793942556b356c6443397a6158526c63793959566b6c4a544556484c3039464c7a49774d6a59794d4449314d5441774f533951515338304e6a51324f544d33597930344e3245324c54526a4f5455744f546c694f4330775a4451304d446335596d4e6d4e6a49756347526d&Fich=4646937c-87a6-4c95-99b8-0d44079bcf62.pdf&Inline=true | AH46: 46321.778 | AI46: 46321.781
A47: 46 | B47: 40C-2 | C47: 45959.506 | D47: Original | E47: L | F47: Filipa Pinto; Isabel Mendes Lopes; Jorge Pinto; Patrícia Gonçalves; Paulo Muacho; Rui Tavares | G47: Art. 63.º-B (aditamento) | L47: Artigo 63.º-B (Redução faseada da taxa de IVA) | S47: Rejeitado(a) em Comissão | T47: Rejeitada | U47: Favor: L, PCP, BE, PAN; Contra: PSD, CDS-PP; Abstenção: CH, PS, IL | V47: 45982 | W47: AR: https://www.parlamento.pt/OrcamentoEstado/Paginas/DetalhePropostaAlteracao.aspx?BID=23594 PDF: https://app.parlamento.pt/webutils/docs/doc.pdf?path=6148523063484d364c793942556b356c6443397a6158526c63793959566b6c4a544556484c3039464c7a49774d6a59794d4449314d5441774f533951515339684d6a41344e474d774e5331694e3259324c5451324f5445744f5745775a4330774d575578597a566859545669596a67756347526d&Fich=a2084c05-b7f6-4691-9a0d-01e1c5aa5bb8.pdf&Inline=true | X47: Orçamento, Finanças e Administração Pública | Y47: Articulado | Z47: Aditamento (Artigo PPL) | AA47: Rejeitado(a) em Comissão | AC47: 2 | AD47: 1 | AE47: 23594 | AF47: https://www.parlamento.pt/OrcamentoEstado/Paginas/DetalhePropostaAlteracao.aspx?BID=23594 | AG47: https://app.parlamento.pt/webutils/docs/doc.pdf?path=6148523063484d364c793942556b356c6443397a6158526c63793959566b6c4a544556484c3039464c7a49774d6a59794d4449314d5441774f533951515339684d6a41344e474d774e5331694e3259324c5451324f5445744f5745775a4330774d575578597a566859545669596a67756347526d&Fich=a2084c05-b7f6-4691-9a0d-01e1c5aa5bb8.pdf&Inline=true | AH47: 46321.778 | AI47: 46321.781
A48: 47 | B48: 40C-3 | C48: 45959.506 | D48: Original | E48: L | F48: Filipa Pinto; Isabel Mendes Lopes; Jorge Pinto; Patrícia Gonçalves; Paulo Muacho; Rui Tavares | G48: Art. 63.º-C (aditamento) | L48: Artigo 63.º-C (Alteração ao artigo 18.º do Código do Imposto sobre o Valor Acrescentado) | S48: Rejeitado(a) em Comissão | T48: Rejeitada | U48: Favor: L, PCP, BE, PAN; Contra: PSD, CDS-PP; Abstenção: CH, PS, IL | V48: 45982 | W48: AR: https://www.parlamento.pt/OrcamentoEstado/Paginas/DetalhePropostaAlteracao.aspx?BID=23595 PDF: https://app.parlamento.pt/webutils/docs/doc.pdf?path=6148523063484d364c793942556b356c6443397a6158526c63793959566b6c4a544556484c3039464c7a49774d6a59794d4449314d5441774f5339515153396c4d446734597a49324e43307a597a63344c5451344d575974596d4d79596930304d574d7a4d6a45784e7a41334d7a63756347526d&Fich=e088c264-3c78-481f-bc2b-41c321170737.pdf&Inline=true | X48: Orçamento, Finanças e Administração Pública | Y48: Articulado | Z48: Aditamento (Artigo PPL) | AA48: Rejeitado(a) em Comissão | AC48: 3 | AD48: 1 | AE48: 23595 | AF48: https://www.parlamento.pt/OrcamentoEstado/Paginas/DetalhePropostaAlteracao.aspx?BID=23595 | AG48: https://app.parlamento.pt/webutils/docs/doc.pdf?path=6148523063484d364c793942556b356c6443397a6158526c63793959566b6c4a544556484c3039464c7a49774d6a59794d4449314d5441774f5339515153396c4d446734597a49324e43307a597a63344c5451344d575974596d4d79596930304d574d7a4d6a45784e7a41334d7a63756347526d&Fich=e088c264-3c78-481f-bc2b-41c321170737.pdf&Inline=true | AH48: 46321.778 | AI48: 46321.781
A49: 48 | B49: 41C | C49: 45959.543 | D49: Original | E49: L | F49: Filipa Pinto; Isabel Mendes Lopes; Jorge Pinto; Patrícia Gonçalves; Paulo Muacho; Rui Tavares | G49: Art. 19.º-A (aditamento) | L49: Artigo 19.º-A (Aumento salarial na Administração Pública) | S49: Rejeitado(a) em Comissão | T49: Rejeitada | U49: Favor: L, PCP, BE, PAN; Contra: PSD, IL, CDS-PP; Abstenção: CH, PS | V49: 45981 | W49: AR: https://www.parlamento.pt/OrcamentoEstado/Paginas/DetalhePropostaAlteracao.aspx?BID=23234 PDF: https://app.parlamento.pt/webutils/docs/doc.pdf?path=6148523063484d364c793942556b356c6443397a6158526c63793959566b6c4a544556484c3039464c7a49774d6a59794d4449314d5441774f533951515338314f57466d4d544935595331684d546b354c54526c597a63744f44637a597930354d5445355a6a457a5932597a4d6a55756347526d&Fich=59af129a-a199-4ec7-873c-9119f13cf325.pdf&Inline=true | X49: Orçamento, Finanças e Administração Pública | Y49: Articulado | Z49: Aditamento (Artigo PPL) | AA49: Rejeitado(a) em Comissão | AD49: 1 | AE49: 23234 | AF49: https://www.parlamento.pt/OrcamentoEstado/Paginas/DetalhePropostaAlteracao.aspx?BID=23234 | AG49: https://app.parlamento.pt/webutils/docs/doc.pdf?path=6148523063484d364c793942556b356c6443397a6158526c63793959566b6c4a544556484c3039464c7a49774d6a59794d4449314d5441774f533951515338314f57466d4d544935595331684d546b354c54526c597a63744f44637a597930354d5445355a6a457a5932597a4d6a55756347526d&Fich=59af129a-a199-4ec7-873c-9119f13cf325.pdf&Inline=true | AH49: 46321.778 | AI49: 46321.781
A50: 49 | B50: 42C | C50: 45959.558 | D50: Original | E50: L | F50: Filipa Pinto; Isabel Mendes Lopes; Jorge Pinto; Patrícia Gonçalves; Paulo Muacho; Rui Tavares | G50: Art. 112.º-A (aditamento) | L50: Artigo 112.º-A (Alarga o Projeto-piloto da semana de quatro dias de trabalho no setor privado) | S50: Rejeitado(a) em Comissão | T50: Rejeitada | U50: Favor: L, BE, PAN; Contra: PSD, CH, IL, CDS-PP; Abstenção: PS, PCP | V50: 45982 | W50: AR: https://www.parlamento.pt/OrcamentoEstado/Paginas/DetalhePropostaAlteracao.aspx?BID=23235 PDF: https://app.parlamento.pt/webutils/docs/doc.pdf?path=6148523063484d364c793942556b356c6443397a6158526c63793959566b6c4a544556484c3039464c7a49774d6a59794d4449314d5441774f533951515338344e6d4d325a4445774e53316a4d574d774c54526c4d6a41744f4749774e5330784e6a426c4e574a6b4e7a686c5a5449756347526d&Fich=86c6d105-c1c0-4e20-8b05-160e5bd78ee2.pdf&Inline=true | X50: Trabalho, Segurança Social e Inclusão | Y50: Articulado | Z50: Aditamento (Artigo PPL) | AA50: Rejeitado(a) em Comissão | AD50: 1 | AE50: 23235 | AF50: https://www.parlamento.pt/OrcamentoEstado/Paginas/DetalhePropostaAlteracao.aspx?BID=23235 | AG50: https://app.parlamento.pt/webutils/docs/doc.pdf?path=6148523063484d364c793942556b356c6443397a6158526c63793959566b6c4a544556484c3039464c7a49774d6a59794d4449314d5441774f533951515338344e6d4d325a4445774e53316a4d574d774c54526c4d6a41744f4749774e5330784e6a426c4e574a6b4e7a686c5a5449756347526d&Fich=86c6d105-c1c0-4e20-8b05-160e5bd78ee2.pdf&Inline=true | AH50: 46321.778 | AI50: 46321.781
A51: 50 | B51: 43C | C51: 45959.564 | D51: Original | E51: L | F51: Filipa Pinto; Isabel Mendes Lopes; Jorge Pinto; Patrícia Gonçalves; Paulo Muacho; Rui Tavares | G51: Art. 112.º-A (aditamento) | L51: Artigo 112.º-A (Cria o Serviço Nacional de Habitação) | S51: Rejeitado(a) em Comissão | T51: Rejeitada | U51: Favor: L, PCP, BE, PAN; Contra: PSD, CH, IL, CDS-PP; Abstenção: PS | V51: 45982 | W51: AR: https://www.parlamento.pt/OrcamentoEstado/Paginas/DetalhePropostaAlteracao.aspx?BID=23236 PDF: https://app.parlamento.pt/webutils/docs/doc.pdf?path=6148523063484d364c793942556b356c6443397a6158526c63793959566b6c4a544556484c3039464c7a49774d6a59794d4449314d5441774f5339515153396d4e47526d5a4745774e53316c597a63774c54517a4f445174596d4d314e53316b595756695a544d774e6a55344e6a6b756347526d&Fich=f4dfda05-ec70-4384-bc55-daebe3065869.pdf&Inline=true | X51: Infraestruturas, Mobilidade e Habitação | Y51: Articulado | Z51: Aditamento (Artigo PPL) | AA51: Rejeitado(a) em Comissão | AD51: 1 | AE51: 23236 | AF51: https://www.parlamento.pt/OrcamentoEstado/Paginas/DetalhePropostaAlteracao.aspx?BID=23236 | AG51: https://app.parlamento.pt/webutils/docs/doc.pdf?path=6148523063484d364c793942556b356c6443397a6158526c63793959566b6c4a544556484c3039464c7a49774d6a59794d4449314d5441774f5339515153396d4e47526d5a4745774e53316c597a63774c54517a4f445174596d4d314e53316b595756695a544d774e6a55344e6a6b756347526d&Fich=f4dfda05-ec70-4384-bc55-daebe3065869.pdf&Inline=true | AH51: 46321.778 | AI51: 46321.781
A52: 51 | B52: 44C | C52: 45959.567 | D52: Original | E52: L | F52: Filipa Pinto; Isabel Mendes Lopes; Jorge Pinto; Patrícia Gonçalves; Paulo Muacho; Rui Tavares | G52: Art. 112.º-A (aditamento) | L52: Artigo 112.º-A (Aumento do Salário Mínimo Nacional) | S52: Rejeitado(a) em Comissão | T52: Rejeitada | U52: Favor: L, PCP, BE, PAN; Contra: PSD, IL, CDS-PP; Abstenção: CH, PS | V52: 45982 | W52: AR: https://www.parlamento.pt/OrcamentoEstado/Paginas/DetalhePropostaAlteracao.aspx?BID=23237 PDF: https://app.parlamento.pt/webutils/docs/doc.pdf?path=6148523063484d364c793942556b356c6443397a6158526c63793959566b6c4a544556484c3039464c7a49774d6a59794d4449314d5441774f533951515338314d446c6a4e6a67315a4330774e446b7a4c54526a4f544974596a41324f433077597a4d305a4445335a6a4d344d6d49756347526d&Fich=509c685d-0493-4c92-b068-0c34d17f382b.pdf&Inline=true | X52: Trabalho, Segurança Social e Inclusão | Y52: Articulado | Z52: Aditamento (Artigo PPL) | AA52: Rejeitado(a) em Comissão | AD52: 1 | AE52: 23237 | AF52: https://www.parlamento.pt/OrcamentoEstado/Paginas/DetalhePropostaAlteracao.aspx?BID=23237 | AG52: https://app.parlamento.pt/webutils/docs/doc.pdf?path=6148523063484d364c793942556b356c6443397a6158526c63793959566b6c4a544556484c3039464c7a49774d6a59794d4449314d5441774f533951515338314d446c6a4e6a67315a4330774e446b7a4c54526a4f544974596a41324f433077597a4d305a4445335a6a4d344d6d49756347526d&Fich=509c685d-0493-4c92-b068-0c34d17f382b.pdf&Inline=true | AH52: 46321.778 | AI52: 46321.781
A53: 52 | B53: 45C | C53: 45959.603 | D53: Original | E53: PCP | F53: Alfredo Maia; Paula Santos; Paulo Raimundo | G53: Art. 18.º-A (aditamento) | L53: Artigo 18.º-A (Valorização Poder Compra Trabalhadores da Administração Pública) | S53: Rejeitado(a) em Comissão | T53: Rejeitada | U53: Favor: L, PCP, BE, PAN; Contra: PSD, IL, CDS-PP; Abstenção: CH, PS | V53: 45981 | W53: AR: https://www.parlamento.pt/OrcamentoEstado/Paginas/DetalhePropostaAlteracao.aspx?BID=23238 PDF: https://app.parlamento.pt/webutils/docs/doc.pdf?path=6148523063484d364c793942556b356c6443397a6158526c63793959566b6c4a544556484c3039464c7a49774d6a59794d4449314d5441774f5339515153396b4f446732596a557a4f5330794e4449794c5451795a6d59744f445a6c5a5330784f5756685a44426d4f545a6b4d6a4d756347526d&Fich=d886b539-2422-42ff-86ee-19ead0f96d23.pdf&Inline=true | X53: Orçamento, Finanças e Administração Pública | Y53: Articulado | Z53: Aditamento (Artigo PPL) | AA53: Rejeitado(a) em Comissão | AD53: 1 | AE53: 23238 | AF53: https://www.parlamento.pt/OrcamentoEstado/Paginas/DetalhePropostaAlteracao.aspx?BID=23238 | AG53: https://app.parlamento.pt/webutils/docs/doc.pdf?path=6148523063484d364c793942556b356c6443397a6158526c63793959566b6c4a544556484c3039464c7a49774d6a59794d4449314d5441774f5339515153396b4f446732596a557a4f5330794e4449794c5451795a6d59744f445a6c5a5330784f5756685a44426d4f545a6b4d6a4d756347526d&Fich=d886b539-2422-42ff-86ee-19ead0f96d23.pdf&Inline=true | AH53: 46321.778 | AI53: 46321.781
A54: 53 | B54: 46C | C54: 45959.606 | D54: Original | E54: PCP | F54: Alfredo Maia; Paula Santos; Paulo Raimundo | G54: Art. 18.º-A (aditamento) | L54: Artigo 18.º-A (Atualização do subsídio de refeição) | S54: Rejeitado(a) em Comissão | T54: Rejeitada | U54: Favor: CH, L, PCP, BE, PAN; Contra: PSD, IL, CDS-PP; Abstenção: PS | V54: 45981 | W54: AR: https://www.parlamento.pt/OrcamentoEstado/Paginas/DetalhePropostaAlteracao.aspx?BID=23239 PDF: https://app.parlamento.pt/webutils/docs/doc.pdf?path=6148523063484d364c793942556b356c6443397a6158526c63793959566b6c4a544556484c3039464c7a49774d6a59794d4449314d5441774f5339515153387a5a574e695a474a6d5a6930775a6d526d4c5451794f4467744f5463304f53316b4e32566a4e6a45794e5452685a5441756347526d&Fich=3ecbdbff-0fdf-4288-9749-d7ec61254ae0.pdf&Inline=true | X54: Orçamento, Finanças e Administração Pública | Y54: Articulado | Z54: Aditamento (Artigo PPL) | AA54: Rejeitado(a) em Comissão | AD54: 1 | AE54: 23239 | AF54: https://www.parlamento.pt/OrcamentoEstado/Paginas/DetalhePropostaAlteracao.aspx?BID=23239 | AG54: https://app.parlamento.pt/webutils/docs/doc.pdf?path=6148523063484d364c793942556b356c6443397a6158526c63793959566b6c4a544556484c3039464c7a49774d6a59794d4449314d5441774f5339515153387a5a574e695a474a6d5a6930775a6d526d4c5451794f4467744f5463304f53316b4e32566a4e6a45794e5452685a5441756347526d&Fich=3ecbdbff-0fdf-4288-9749-d7ec61254ae0.pdf&Inline=true | AH54: 46321.778 | AI54: 46321.781
A55: 54 | B55: 47C | C55: 45959.607 | D55: Original | E55: PCP | F55: Alfredo Maia; Paula Santos; Paulo Raimundo | G55: Art. 38.º-A (aditamento) | L55: Artigo 38.º-A (Atualização de pensões) | S55: Rejeitado(a) em Plenário | T55: Rejeitada | U55: Favor: L, PCP, BE, PAN, JPP; Contra: PSD, IL, CDS-PP; Abstenção: CH, PS | V55: 45982 | W55: Avocada a Plenário. AR: https://www.parlamento.pt/OrcamentoEstado/Paginas/DetalhePropostaAlteracao.aspx?BID=23240 PDF: https://app.parlamento.pt/webutils/docs/doc.pdf?path=6148523063484d364c793942556b356c6443397a6158526c63793959566b6c4a544556484c3039464c7a49774d6a59794d4449314d5441774f5339515153396a5a6a553259574d34595331684e4441354c5451784e6a67744f4449354d53316c4e474d354e325a684f544d7a4e444d756347526d&Fich=cf56ac8a-a409-4168-8291-e4c97fa93343.pdf&Inline=true | X55: Trabalho, Segurança Social e Inclusão | Y55: Articulado | Z55: Aditamento (Artigo PPL) | AA55: Rejeitado(a) em Plenário | AB55: S | AD55: 2 | AE55: 23240 | AF55: https://www.parlamento.pt/OrcamentoEstado/Paginas/DetalhePropostaAlteracao.aspx?BID=23240 | AG55: https://app.parlamento.pt/webutils/docs/doc.pdf?path=6148523063484d364c793942556b356c6443397a6158526c63793959566b6c4a544556484c3039464c7a49774d6a59794d4449314d5441774f5339515153396a5a6a553259574d34595331684e4441354c5451784e6a67744f4449354d53316c4e474d354e325a684f544d7a4e444d756347526d&Fich=cf56ac8a-a409-4168-8291-e4c97fa93343.pdf&Inline=true | AH55: 46321.778 | AI55: 46321.781
A56: 55 | B56: 48C | C56: 45959.609 | D56: Original | E56: PCP | F56: Alfredo Maia; Paula Santos; Paulo Raimundo | G56: Art. 126.º-A (aditamento) | L56: Artigo 126.º-A (Controlo e fixação de preços do GPL - Gases de Petróleo Liquefeito Butano engarrafado (13kg)) | S56: Rejeitado(a) em Comissão | T56: Rejeitada | U56: Favor: L, PCP, BE, PAN; Contra: PSD, CH, IL, CDS-PP; Abstenção: PS | V56: 45985 | W56: AR: https://www.parlamento.pt/OrcamentoEstado/Paginas/DetalhePropostaAlteracao.aspx?BID=23241 PDF: https://app.parlamento.pt/webutils/docs/doc.pdf?path=6148523063484d364c793942556b356c6443397a6158526c63793959566b6c4a544556484c3039464c7a49774d6a59794d4449314d5441774f53395151533969597a453559574e684e6930314d7a68684c5452684e6a597459574a6b5a43316b4d5449784d6a55334e7a4d344d6a6b756347526d&Fich=bc19aca6-538a-4a66-abdd-d12125773829.pdf&Inline=true | X56: Ambiente e Energia | Y56: Articulado | Z56: Aditamento (Artigo PPL) | AA56: Rejeitado(a) em Comissão | AD56: 1 | AE56: 23241 | AF56: https://www.parlamento.pt/OrcamentoEstado/Paginas/DetalhePropostaAlteracao.aspx?BID=23241 | AG56: https://app.parlamento.pt/webutils/docs/doc.pdf?path=6148523063484d364c793942556b356c6443397a6158526c63793959566b6c4a544556484c3039464c7a49774d6a59794d4449314d5441774f53395151533969597a453559574e684e6930314d7a68684c5452684e6a597459574a6b5a43316b4d5449784d6a55334e7a4d344d6a6b756347526d&Fich=bc19aca6-538a-4a66-abdd-d12125773829.pdf&Inline=true | AH56: 46321.778 | AI56: 46321.781
A57: 56 | B57: 49C | C57: 45959.61 | D57: Original | E57: PCP | F57: Alfredo Maia; Paula Santos; Paulo Raimundo | G57: Art. 121.º-A (aditamento) | L57: Artigo 121.º-A (Gratuitidade de medicamentos para doentes crónicos, utentes com mais de 65 anos e utentes com insuficiência económica) | S57: Rejeitado(a) em Comissão | T57: Rejeitada | U57: Favor: CH, L, PCP, BE, PAN; Contra: PSD, IL, CDS-PP; Abstenção: PS | V57: 45985 | W57: AR: https://www.parlamento.pt/OrcamentoEstado/Paginas/DetalhePropostaAlteracao.aspx?BID=23242 PDF: https://app.parlamento.pt/webutils/docs/doc.pdf?path=6148523063484d364c793942556b356c6443397a6158526c63793959566b6c4a544556484c3039464c7a49774d6a59794d4449314d5441774f533951515338344d6d51314d324a6a5a6930315a474d344c5451354e6a45744f5449324f5330795932526a595455314d7a45344d4445756347526d&Fich=82d53bcf-5dc8-4961-9269-2cdca5531801.pdf&Inline=true | X57: Saúde | Y57: Articulado | Z57: Aditamento (Artigo PPL) | AA57: Rejeitado(a) em Comissão | AD57: 1 | AE57: 23242 | AF57: https://www.parlamento.pt/OrcamentoEstado/Paginas/DetalhePropostaAlteracao.aspx?BID=23242 | AG57: https://app.parlamento.pt/webutils/docs/doc.pdf?path=6148523063484d364c793942556b356c6443397a6158526c63793959566b6c4a544556484c3039464c7a49774d6a59794d4449314d5441774f533951515338344d6d51314d324a6a5a6930315a474d344c5451354e6a45744f5449324f5330795932526a595455314d7a45344d4445756347526d&Fich=82d53bcf-5dc8-4961-9269-2cdca5531801.pdf&Inline=true | AH57: 46321.778 | AI57: 46321.781
A58: 57 | B58: 50C | C58: 45959.612 | D58: Original | E58: PCP | F58: Alfredo Maia; Paula Santos; Paulo Raimundo | G58: Art. 22.º-A (aditamento) | L58: Artigo 22.º-A (Criação do regime de dedicação exclusiva no SNS) | S58: Rejeitado(a) em Comissão | T58: Rejeitada | U58: Favor: L, BE, PAN; Contra: PSD, IL, CDS-PP; Abstenção: CH, PS | V58: 45981 | W58: AR: https://www.parlamento.pt/OrcamentoEstado/Paginas/DetalhePropostaAlteracao.aspx?BID=23243 PDF: https://app.parlamento.pt/webutils/docs/doc.pdf?path=6148523063484d364c793942556b356c6443397a6158526c63793959566b6c4a544556484c3039464c7a49774d6a59794d4449314d5441774f53395151533879596d59334d4449775a6930344e6d51774c5451335a475974596d4932595330794d7a4d344e7a67774e5452695a5455756347526d&Fich=2bf7020f-86d0-47df-bb6a-233878054be5.pdf&Inline=true | X58: Saúde | Y58: Articulado | Z58: Aditamento (Artigo PPL) | AA58: Rejeitado(a) em Comissão | AD58: 1 | AE58: 23243 | AF58: https://www.parlamento.pt/OrcamentoEstado/Paginas/DetalhePropostaAlteracao.aspx?BID=23243 | AG58: https://app.parlamento.pt/webutils/docs/doc.pdf?path=6148523063484d364c793942556b356c6443397a6158526c63793959566b6c4a544556484c3039464c7a49774d6a59794d4449314d5441774f53395151533879596d59334d4449775a6930344e6d51774c5451335a475974596d4932595330794d7a4d344e7a67774e5452695a5455756347526d&Fich=2bf7020f-86d0-47df-bb6a-233878054be5.pdf&Inline=true | AH58: 46321.778 | AI58: 46321.781
A59: 58 | B59: 51C | C59: 45959.613 | D59: Original | E59: PCP | F59: Alfredo Maia; Paula Santos; Paulo Raimundo | G59: Art. 21.º-A (aditamento) | L59: Artigo 21.º-A (Medidas de valorização da Carreira Docente) | S59: Rejeitado(a) em Comissão | T59: Rejeitada | U59: Favor: L, PCP, BE, PAN; Contra: PSD, CDS-PP; Abstenção: CH, PS, IL | V59: 45981 | W59: AR: https://www.parlamento.pt/OrcamentoEstado/Paginas/DetalhePropostaAlteracao.aspx?BID=23244 PDF: https://app.parlamento.pt/webutils/docs/doc.pdf?path=6148523063484d364c793942556b356c6443397a6158526c63793959566b6c4a544556484c3039464c7a49774d6a59794d4449314d5441774f53395151533834596a677a4e54686b4f4331694e3259314c5451775a6a6b74596a5a6b4e7930324d6a6b795a6d59784d47466c5a446b756347526d&Fich=8b8358d8-b7f5-40f9-b6d7-6292ff10aed9.pdf&Inline=true | X59: Educação e Ciência | Y59: Articulado | Z59: Aditamento (Artigo PPL) | AA59: Rejeitado(a) em Comissão | AD59: 1 | AE59: 23244 | AF59: https://www.parlamento.pt/OrcamentoEstado/Paginas/DetalhePropostaAlteracao.aspx?BID=23244 | AG59: https://app.parlamento.pt/webutils/docs/doc.pdf?path=6148523063484d364c793942556b356c6443397a6158526c63793959566b6c4a544556484c3039464c7a49774d6a59794d4449314d5441774f53395151533834596a677a4e54686b4f4331694e3259314c5451775a6a6b74596a5a6b4e7930324d6a6b795a6d59784d47466c5a446b756347526d&Fich=8b8358d8-b7f5-40f9-b6d7-6292ff10aed9.pdf&Inline=true | AH59: 46321.778 | AI59: 46321.781
A60: 59 | B60: 52C | C60: 45959.615 | D60: Original | E60: PCP | F60: Alfredo Maia; Paula Santos; Paulo Raimundo | G60: Art. 118.º-A (aditamento) | L60: Artigo 118.º-A (Eliminação das propinas, taxas e emolumentos no ensino superior público) | S60: Rejeitado(a) em Comissão | T60: Rejeitada | U60: Favor: PCP, BE, PAN; Contra: PSD, CH, IL, CDS-PP; Abstenção: PS, L | V60: 45985 | W60: AR: https://www.parlamento.pt/OrcamentoEstado/Paginas/DetalhePropostaAlteracao.aspx?BID=23245 PDF: https://app.parlamento.pt/webutils/docs/doc.pdf?path=6148523063484d364c793942556b356c6443397a6158526c63793959566b6c4a544556484c3039464c7a49774d6a59794d4449314d5441774f5339515153396a4d7a49355a5451774d69316c4e5751314c545178597a6374596d51354e79316a4e4441784d4441354f5749775a6a67756347526d&Fich=c329e402-e5d5-41c7-bd97-c4010099b0f8.pdf&Inline=true | X60: Educação e Ciência | Y60: Articulado | Z60: Aditamento (Artigo PPL) | AA60: Rejeitado(a) em Comissão | AD60: 1 | AE60: 23245 | AF60: https://www.parlamento.pt/OrcamentoEstado/Paginas/DetalhePropostaAlteracao.aspx?BID=23245 | AG60: https://app.parlamento.pt/webutils/docs/doc.pdf?path=6148523063484d364c793942556b356c6443397a6158526c63793959566b6c4a544556484c3039464c7a49774d6a59794d4449314d5441774f5339515153396a4d7a49355a5451774d69316c4e5751314c545178597a6374596d51354e79316a4e4441784d4441354f5749775a6a67756347526d&Fich=c329e402-e5d5-41c7-bd97-c4010099b0f8.pdf&Inline=true | AH60: 46321.778 | AI60: 46321.781
A61: 60 | B61: 53C | C61: 45959.617 | D61: Original | E61: PCP | F61: Alfredo Maia; Paula Santos; Paulo Raimundo | G61: Art. 118.º-A (aditamento) | L61: Artigo 118.º-A (Rede pública de creches) | S61: Rejeitado(a) em Plenário | T61: Rejeitada | U61: Favor: CH, L, PCP, BE, PAN, JPP; Contra: PSD, IL, CDS-PP; Abstenção: PS | V61: 45987 | W61: Avocada a Plenário. AR: https://www.parlamento.pt/OrcamentoEstado/Paginas/DetalhePropostaAlteracao.aspx?BID=23246 PDF: https://app.parlamento.pt/webutils/docs/doc.pdf?path=6148523063484d364c793942556b356c6443397a6158526c63793959566b6c4a544556484c3039464c7a49774d6a59794d4449314d5441774f533951515338304d474d304e6d56694d7930305a44426b4c5452684e544d744f546c695a5330344d3259354d7a417759574a684d4455756347526d&Fich=40c46eb3-4d0d-4a53-99be-83f9300aba05.pdf&Inline=true | X61: Trabalho, Segurança Social e Inclusão | Y61: Articulado | Z61: Aditamento (Artigo PPL) | AA61: Rejeitado(a) em Plenário | AB61: S | AD61: 2 | AE61: 23246 | AF61: https://www.parlamento.pt/OrcamentoEstado/Paginas/DetalhePropostaAlteracao.aspx?BID=23246 | AG61: https://app.parlamento.pt/webutils/docs/doc.pdf?path=6148523063484d364c793942556b356c6443397a6158526c63793959566b6c4a544556484c3039464c7a49774d6a59794d4449314d5441774f533951515338304d474d304e6d56694d7930305a44426b4c5452684e544d744f546c695a5330344d3259354d7a417759574a684d4455756347526d&Fich=40c46eb3-4d0d-4a53-99be-83f9300aba05.pdf&Inline=true | AH61: 46321.778 | AI61: 46321.781
A62: 61 | B62: 54C | C62: 45959.618 | D62: Original | E62: PCP | F62: Alfredo Maia; Paula Santos; Paulo Raimundo | G62: Art. 128.º-A (aditamento) | L62: Artigo 128.º-A (Regime especial de proteção da habitação arrendada) | S62: Rejeitado(a) em Comissão | T62: Rejeitada | U62: Favor: L, PCP, BE; Contra: PSD, CH, IL, CDS-PP, PAN; Abstenção: PS | V62: 45985 | W62: AR: https://www.parlamento.pt/OrcamentoEstado/Paginas/DetalhePropostaAlteracao.aspx?BID=23247 PDF: https://app.parlamento.pt/webutils/docs/doc.pdf?path=6148523063484d364c793942556b356c6443397a6158526c63793959566b6c4a544556484c3039464c7a49774d6a59794d4449314d5441774f533951515338355a474d35595749345a53307a4e4441354c5451354f446b74596d49324e4330314d5452684e7a63785a6a4d775a5467756347526d&Fich=9dc9ab8e-3409-4989-bb64-514a771f30e8.pdf&Inline=true | X62: Infraestruturas, Mobilidade e Habitação | Y62: Articulado | Z62: Aditamento (Artigo PPL) | AA62: Rejeitado(a) em Comissão | AD62: 1 | AE62: 23247 | AF62: https://www.parlamento.pt/OrcamentoEstado/Paginas/DetalhePropostaAlteracao.aspx?BID=23247 | AG62: https://app.parlamento.pt/webutils/docs/doc.pdf?path=6148523063484d364c793942556b356c6443397a6158526c63793959566b6c4a544556484c3039464c7a49774d6a59794d4449314d5441774f533951515338355a474d35595749345a53307a4e4441354c5451354f446b74596d49324e4330314d5452684e7a63785a6a4d775a5467756347526d&Fich=9dc9ab8e-3409-4989-bb64-514a771f30e8.pdf&Inline=true | AH62: 46321.778 | AI62: 46321.781
A63: 62 | B63: 55C-1 | C63: 45959.631 | D63: Original | E63: PAN | F63: Inês de Sousa Real | G63: Art. 95.º (substituição) | L63: N.º 1, Artigo 95.º | S63: Rejeitado(a) em Plenário | T63: Rejeitada | U63: Favor: IL, L, PCP, BE, PAN, JPP; Contra: PSD, CDS-PP; Abstenção: CH, PS | V63: 45985 | W63: Avocada a Plenário. AR: https://www.parlamento.pt/OrcamentoEstado/Paginas/DetalhePropostaAlteracao.aspx?BID=23248 PDF: https://app.parlamento.pt/webutils/docs/doc.pdf?path=6148523063484d364c793942556b356c6443397a6158526c63793959566b6c4a544556484c3039464c7a49774d6a59794d4449314d5441774f533951515338774f444d304d4759304f43316a4d474e6b4c5451774e3251744f544e685a4330354d5467314e7a426b596a6468596a4d756347526d&Fich=08340f48-c0cd-407d-93ad-918570db7ab3.pdf&Inline=true | X63: Ambiente e Energia; Reforma do Estado e Poder Local | Y63: Articulado | Z63: Substituição | AA63: Rejeitado(a) em Plenário | AB63: S | AC63: 1 | AD63: 1 | AE63: 23248 | AF63: https://www.parlamento.pt/OrcamentoEstado/Paginas/DetalhePropostaAlteracao.aspx?BID=23248 | AG63: https://app.parlamento.pt/webutils/docs/doc.pdf?path=6148523063484d364c793942556b356c6443397a6158526c63793959566b6c4a544556484c3039464c7a49774d6a59794d4449314d5441774f533951515338774f444d304d4759304f43316a4d474e6b4c5451774e3251744f544e685a4330354d5467314e7a426b596a6468596a4d756347526d&Fich=08340f48-c0cd-407d-93ad-918570db7ab3.pdf&Inline=true | AH63: 46321.778 | AI63: 46321.781
A64: 63 | B64: 55C-2 | C64: 45959.631 | D64: Original | E64: PAN | F64: Inês de Sousa Real | G64: Art. 95.º (aditamento) | L64: N.º 5, Artigo 95.º | S64: Rejeitado(a) em Plenário | T64: Rejeitada | U64: Favor: IL, L, BE, PAN, JPP; Contra: PSD, CDS-PP; Abstenção: CH, PS, PCP | V64: 45985 | W64: Avocada a Plenário. AR: https://www.parlamento.pt/OrcamentoEstado/Paginas/DetalhePropostaAlteracao.aspx?BID=24171 PDF: https://app.parlamento.pt/webutils/docs/doc.pdf?path=6148523063484d364c793942556b356c6443397a6158526c63793959566b6c4a544556484c3039464c7a49774d6a59794d4449314d5441774f533951515338314e6a41334e546b794d69307a4e7a67304c5451314f5745744f54686d4e5330325a44646d596d49325a444d354e3245756347526d&Fich=56075922-3784-459a-98f5-6d7fbb6d397a.pdf&Inline=true | X64: Ambiente e Energia; Reforma do Estado e Poder Local | Y64: Articulado | Z64: Aditamento (Números e Alíneas) | AA64: Rejeitado(a) em Plenário | AB64: S | AC64: 2 | AD64: 1 | AE64: 24171 | AF64: https://www.parlamento.pt/OrcamentoEstado/Paginas/DetalhePropostaAlteracao.aspx?BID=24171 | AG64: https://app.parlamento.pt/webutils/docs/doc.pdf?path=6148523063484d364c793942556b356c6443397a6158526c63793959566b6c4a544556484c3039464c7a49774d6a59794d4449314d5441774f533951515338314e6a41334e546b794d69307a4e7a67304c5451314f5745744f54686d4e5330325a44646d596d49325a444d354e3245756347526d&Fich=56075922-3784-459a-98f5-6d7fbb6d397a.pdf&Inline=true | AH64: 46321.778 | AI64: 46321.781
A65: 64 | B65: 56C | C65: 45959.643 | D65: Original | E65: PAN | F65: Inês de Sousa Real | G65: Art. 95.º (substituição) | L65: N.º 3, Artigo 95.º | S65: Aprovado(a) em Plenário | T65: Aprovada | U65: Favor: PSD, L, PCP, CDS-PP, BE, PAN, JPP; Contra: IL; Abstenção: CH, PS | V65: 45985 | W65: Avocada a Plenário. AR: https://www.parlamento.pt/OrcamentoEstado/Paginas/DetalhePropostaAlteracao.aspx?BID=23249 PDF: https://app.parlamento.pt/webutils/docs/doc.pdf?path=6148523063484d364c793942556b356c6443397a6158526c63793959566b6c4a544556484c3039464c7a49774d6a59794d4449314d5441774f533951515338334e6a6b77596d49774f4330774e7a457a4c54526c4e7a4974595449304e693169596d45354d6a4d3259575a6d5a4755756347526d&Fich=7690bb08-0713-4e72-a246-bba9236affde.pdf&Inline=true | X65: Ambiente e Energia; Reforma do Estado e Poder Local | Y65: Articulado | Z65: Substituição | AA65: Aprovado(a) em Plenário | AB65: S | AD65: 1 | AE65: 23249 | AF65: https://www.parlamento.pt/OrcamentoEstado/Paginas/DetalhePropostaAlteracao.aspx?BID=23249 | AG65: https://app.parlamento.pt/webutils/docs/doc.pdf?path=6148523063484d364c793942556b356c6443397a6158526c63793959566b6c4a544556484c3039464c7a49774d6a59794d4449314d5441774f533951515338334e6a6b77596d49774f4330774e7a457a4c54526c4e7a4974595449304e693169596d45354d6a4d3259575a6d5a4755756347526d&Fich=7690bb08-0713-4e72-a246-bba9236affde.pdf&Inline=true | AH65: 46321.778 | AI65: 46321.781
A66: 65 | B66: 57C | C66: 45959.76 | D66: Original | E66: L | F66: Filipa Pinto; Isabel Mendes Lopes; Jorge Pinto; Patrícia Gonçalves; Paulo Muacho; Rui Tavares | G66: Art. 38.º-A (aditamento) | L66: Artigo 38.º-A (Alteração ao Decreto-Lei n.º 89/2009, de 9 de abril) | S66: Rejeitado(a) em Comissão | T66: Rejeitada | U66: Favor: CH, L, PCP, BE, PAN; Contra: PSD, CDS-PP; Abstenção: PS, IL | V66: 45981 | W66: AR: https://www.parlamento.pt/OrcamentoEstado/Paginas/DetalhePropostaAlteracao.aspx?BID=23250 PDF: https://app.parlamento.pt/webutils/docs/doc.pdf?path=6148523063484d364c793942556b356c6443397a6158526c63793959566b6c4a544556484c3039464c7a49774d6a59794d4449314d5441774f5339515153396a4f47497a4d544a6c4d6930354d446b344c5451794e6d5174595459784e6930784e4463795a4467314e6a466d4e324d756347526d&Fich=c8b312e2-9098-426d-a616-1472d8561f7c.pdf&Inline=true | X66: Trabalho, Segurança Social e Inclusão | Y66: Articulado | Z66: Aditamento (Artigo PPL) | AA66: Rejeitado(a) em Comissão | AD66: 1 | AE66: 23250 | AF66: https://www.parlamento.pt/OrcamentoEstado/Paginas/DetalhePropostaAlteracao.aspx?BID=23250 | AG66: https://app.parlamento.pt/webutils/docs/doc.pdf?path=6148523063484d364c793942556b356c6443397a6158526c63793959566b6c4a544556484c3039464c7a49774d6a59794d4449314d5441774f5339515153396a4f47497a4d544a6c4d6930354d446b344c5451794e6d5174595459784e6930784e4463795a4467314e6a466d4e324d756347526d&Fich=c8b312e2-9098-426d-a616-1472d8561f7c.pdf&Inline=true | AH66: 46321.778 | AI66: 46321.781
A67: 66 | B67: 58C-1 | C67: 45959.817 | D67: Original | E67: L | F67: Filipa Pinto; Isabel Mendes Lopes; Jorge Pinto; Patrícia Gonçalves; Paulo Muacho; Rui Tavares | G67: Art. 38.º-A (aditamento) | L67: Artigo 38.º-A (Alteração ao Código do Trabalho) | S67: Rejeitado(a) em Comissão | T67: Rejeitada | U67: Favor: CH, IL, L, PCP, BE, PAN; Contra: PSD, CDS-PP; Abstenção: PS | V67: 45981 | W67: AR: https://www.parlamento.pt/OrcamentoEstado/Paginas/DetalhePropostaAlteracao.aspx?BID=23251 PDF: https://app.parlamento.pt/webutils/docs/doc.pdf?path=6148523063484d364c793942556b356c6443397a6158526c63793959566b6c4a544556484c3039464c7a49774d6a59794d4449314d5441774f5339515153396d4d54646d5a474d3159793031595445354c54513559546774595441334d5330304e44646c597a45314e6d597a596a63756347526d&Fich=f17fdc5c-5a19-49a8-a071-447ec156f3b7.pdf&Inline=true | X67: Trabalho, Segurança Social e Inclusão | Y67: Articulado | Z67: Aditamento (Artigo PPL) | AA67: Rejeitado(a) em Comissão | AC67: 1 | AD67: 1 | AE67: 23251 | AF67: https://www.parlamento.pt/OrcamentoEstado/Paginas/DetalhePropostaAlteracao.aspx?BID=23251 | AG67: https://app.parlamento.pt/webutils/docs/doc.pdf?path=6148523063484d364c793942556b356c6443397a6158526c63793959566b6c4a544556484c3039464c7a49774d6a59794d4449314d5441774f5339515153396d4d54646d5a474d3159793031595445354c54513559546774595441334d5330304e44646c597a45314e6d597a596a63756347526d&Fich=f17fdc5c-5a19-49a8-a071-447ec156f3b7.pdf&Inline=true | AH67: 46321.778 | AI67: 46321.781
A68: 67 | B68: 58C-2 | C68: 45959.817 | D68: Original | E68: L | F68: Filipa Pinto; Isabel Mendes Lopes; Jorge Pinto; Patrícia Gonçalves; Paulo Muacho; Rui Tavares | G68: Art. 38.º-B (aditamento) | L68: Artigo 38.º-B (Subsídio para assistência a filho com deficiência, doença crónica ou doença oncológica) | S68: Rejeitado(a) em Plenário | T68: Rejeitada | U68: Favor: CH, IL, L, PCP, BE, PAN, JPP; Contra: PSD, CDS-PP; Abstenção: PS | V68: 45982 | W68: Avocada a Plenário. AR: https://www.parlamento.pt/OrcamentoEstado/Paginas/DetalhePropostaAlteracao.aspx?BID=23444 PDF: https://app.parlamento.pt/webutils/docs/doc.pdf?path=6148523063484d364c793942556b356c6443397a6158526c63793959566b6c4a544556484c3039464c7a49774d6a59794d4449314d5441774f53395151533835596a5a6d5a6a4e684d7930305a6a4d7a4c5451334e7a6b74596d52694e6930324e4449344e575a6c596a68684e4745756347526d&Fich=9b6ff3a3-4f33-4779-bdb6-64285feb8a4a.pdf&Inline=true | X68: Trabalho, Segurança Social e Inclusão | Y68: Articulado | Z68: Aditamento (Artigo PPL) | AA68: Rejeitado(a) em Plenário | AB68: S | AC68: 2 | AD68: 2 | AE68: 23444 | AF68: https://www.parlamento.pt/OrcamentoEstado/Paginas/DetalhePropostaAlteracao.aspx?BID=23444 | AG68: https://app.parlamento.pt/webutils/docs/doc.pdf?path=6148523063484d364c793942556b356c6443397a6158526c63793959566b6c4a544556484c3039464c7a49774d6a59794d4449314d5441774f53395151533835596a5a6d5a6a4e684d7930305a6a4d7a4c5451334e7a6b74596d52694e6930324e4449344e575a6c596a68684e4745756347526d&Fich=9b6ff3a3-4f33-4779-bdb6-64285feb8a4a.pdf&Inline=true | AH68: 46321.778 | AI68: 46321.781
A69: 68 | B69: 59C | C69: 45960.487 | D69: Original | E69: PCP | F69: Alfredo Maia; Paula Santos; Paulo Raimundo | G69: Art. 7.º (aditamento) | L69: Nova Verba 81, Mapa de alterações e transferências orçamentais, Artigo 7.º | S69: Rejeitado(a) em Comissão | T69: Rejeitada | U69: Favor: CH, L, PCP, BE, PAN; Contra: PSD, CDS-PP; Abstenção: PS, IL | V69: 45987 | W69: AR: https://www.parlamento.pt/OrcamentoEstado/Paginas/DetalhePropostaAlteracao.aspx?BID=23252 PDF: https://app.parlamento.pt/webutils/docs/doc.pdf?path=6148523063484d364c793942556b356c6443397a6158526c63793959566b6c4a544556484c3039464c7a49774d6a59794d4449314d5441774f533951515338314e7a49324e7a45795a693078597a49354c54526a4e7a4174596a49794d69316c59574d30595468694d6d4d334d3251756347526d&Fich=5726712f-1c29-4c70-b222-eac4a8b2c73d.pdf&Inline=true | X69: Assuntos Constitucionais, Direitos, Liberdades e Garantias | Y69: Articulado | Z69: Aditamento (Números e Alíneas) | AA69: Rejeitado(a) em Comissão | AD69: 1 | AE69: 23252 | AF69: https://www.parlamento.pt/OrcamentoEstado/Paginas/DetalhePropostaAlteracao.aspx?BID=23252 | AG69: https://app.parlamento.pt/webutils/docs/doc.pdf?path=6148523063484d364c793942556b356c6443397a6158526c63793959566b6c4a544556484c3039464c7a49774d6a59794d4449314d5441774f533951515338314e7a49324e7a45795a693078597a49354c54526a4e7a4174596a49794d69316c59574d30595468694d6d4d334d3251756347526d&Fich=5726712f-1c29-4c70-b222-eac4a8b2c73d.pdf&Inline=true | AH69: 46321.778 | AI69: 46321.781
A70: 69 | B70: 60C | C70: 45960.488 | D70: Original | E70: PCP | F70: Alfredo Maia; Paula Santos; Paulo Raimundo | G70: Art. 7.º (aditamento) | L70: Nova Verba 80, Mapa de alterações e transferências orçamentais, Artigo 7.º | S70: Rejeitado(a) em Comissão | T70: Rejeitada | U70: Favor: CH, L, PCP, BE, PAN; Contra: PSD, CDS-PP; Abstenção: PS, IL | V70: 45987 | W70: AR: https://www.parlamento.pt/OrcamentoEstado/Paginas/DetalhePropostaAlteracao.aspx?BID=23253 PDF: https://app.parlamento.pt/webutils/docs/doc.pdf?path=6148523063484d364c793942556b356c6443397a6158526c63793959566b6c4a544556484c3039464c7a49774d6a59794d4449314d5441774f533951515338354f5441314e3259314e6930334d4459334c5451335a4441744f4759334f5330344f5441774f4749794e6d45774e6d55756347526d&Fich=99057f56-7067-47d0-8f79-89008b26a06e.pdf&Inline=true | X70: Assuntos Constitucionais, Direitos, Liberdades e Garantias | Y70: Articulado | Z70: Aditamento (Números e Alíneas) | AA70: Rejeitado(a) em Comissão | AD70: 1 | AE70: 23253 | AF70: https://www.parlamento.pt/OrcamentoEstado/Paginas/DetalhePropostaAlteracao.aspx?BID=23253 | AG70: https://app.parlamento.pt/webutils/docs/doc.pdf?path=6148523063484d364c793942556b356c6443397a6158526c63793959566b6c4a544556484c3039464c7a49774d6a59794d4449314d5441774f533951515338354f5441314e3259314e6930334d4459334c5451335a4441744f4759334f5330344f5441774f4749794e6d45774e6d55756347526d&Fich=99057f56-7067-47d0-8f79-89008b26a06e.pdf&Inline=true | AH70: 46321.778 | AI70: 46321.781
A71: 70 | B71: 61C | C71: 45960.49 | D71: Original | E71: PCP | F71: Alfredo Maia; Paula Santos; Paulo Raimundo | G71: Art. 8.º (aditamento) | L71: Novo N.º 6, Artigo 8.º | S71: Rejeitado(a) em Comissão | T71: Rejeitada | U71: Favor: L, PCP, BE, PAN; Contra: PSD, CH, CDS-PP; Abstenção: PS, IL | V71: 45981 | W71: AR: https://www.parlamento.pt/OrcamentoEstado/Paginas/DetalhePropostaAlteracao.aspx?BID=23254 PDF: https://app.parlamento.pt/webutils/docs/doc.pdf?path=6148523063484d364c793942556b356c6443397a6158526c63793959566b6c4a544556484c3039464c7a49774d6a59794d4449314d5441774f5339515153396d4e6a593359544130596931694d4455784c5451324e544574595751324f4330354e6d5935596d466c4d5449794f4745756347526d&Fich=f667a04b-b051-4651-ad68-96f9bae1228a.pdf&Inline=true | X71: Assuntos Constitucionais, Direitos, Liberdades e Garantias | Y71: Articulado | Z71: Aditamento (Números e Alíneas) | AA71: Rejeitado(a) em Comissão | AD71: 1 | AE71: 23254 | AF71: https://www.parlamento.pt/OrcamentoEstado/Paginas/DetalhePropostaAlteracao.aspx?BID=23254 | AG71: https://app.parlamento.pt/webutils/docs/doc.pdf?path=6148523063484d364c793942556b356c6443397a6158526c63793959566b6c4a544556484c3039464c7a49774d6a59794d4449314d5441774f5339515153396d4e6a593359544130596931694d4455784c5451324e544574595751324f4330354e6d5935596d466c4d5449794f4745756347526d&Fich=f667a04b-b051-4651-ad68-96f9bae1228a.pdf&Inline=true | AH71: 46321.778 | AI71: 46321.781
A72: 71 | B72: 62C | C72: 45960.492 | D72: Original | E72: PCP | F72: Alfredo Maia; Paula Santos; Paulo Raimundo | G72: Art. 8.º (aditamento) | L72: Novo N.º 6, Artigo 8.º | S72: Rejeitado(a) em Comissão | T72: Rejeitada | U72: Favor: L, PCP, BE, PAN; Contra: PSD, CDS-PP; Abstenção: CH, PS, IL | V72: 45981 | W72: AR: https://www.parlamento.pt/OrcamentoEstado/Paginas/DetalhePropostaAlteracao.aspx?BID=23255 PDF: https://app.parlamento.pt/webutils/docs/doc.pdf?path=6148523063484d364c793942556b356c6443397a6158526c63793959566b6c4a544556484c3039464c7a49774d6a59794d4449314d5441774f533951515338784e4441305a44417759533079596d466d4c54526c4d47497459574e6d5a43316a5a6a4e684e7a55795a445130595467756347526d&Fich=1404d00a-2baf-4e0b-acfd-cf3a752d44a8.pdf&Inline=true | X72: Assuntos Constitucionais, Direitos, Liberdades e Garantias | Y72: Articulado | Z72: Aditamento (Números e Alíneas) | AA72: Rejeitado(a) em Comissão | AD72: 1 | AE72: 23255 | AF72: https://www.parlamento.pt/OrcamentoEstado/Paginas/DetalhePropostaAlteracao.aspx?BID=23255 | AG72: https://app.parlamento.pt/webutils/docs/doc.pdf?path=6148523063484d364c793942556b356c6443397a6158526c63793959566b6c4a544556484c3039464c7a49774d6a59794d4449314d5441774f533951515338784e4441305a44417759533079596d466d4c54526c4d47497459574e6d5a43316a5a6a4e684e7a55795a445130595467756347526d&Fich=1404d00a-2baf-4e0b-acfd-cf3a752d44a8.pdf&Inline=true | AH72: 46321.778 | AI72: 46321.781
A73: 72 | B73: 63C | C73: 45960.495 | D73: Original | E73: PCP | F73: Alfredo Maia; Paula Santos; Paulo Raimundo | G73: Art. 8.º (aditamento) | L73: Novo N.º 16, Artigo 8.º | S73: Rejeitado(a) em Comissão | T73: Rejeitada | U73: Favor: PCP, BE, PAN; Contra: PSD, CH, CDS-PP; Abstenção: PS, IL, L | V73: 45981 | W73: AR: https://www.parlamento.pt/OrcamentoEstado/Paginas/DetalhePropostaAlteracao.aspx?BID=23256 PDF: https://app.parlamento.pt/webutils/docs/doc.pdf?path=6148523063484d364c793942556b356c6443397a6158526c63793959566b6c4a544556484c3039464c7a49774d6a59794d4449314d5441774f5339515153396d5a5759314e44646b5a69316c4e6d56694c5451335a6a4d74596a55344e7930334e6a51305a5751324f4455334d5745756347526d&Fich=fef547df-e6eb-47f3-b587-7644ed68571a.pdf&Inline=true | X73: Assuntos Constitucionais, Direitos, Liberdades e Garantias | Y73: Articulado | Z73: Aditamento (Números e Alíneas) | AA73: Rejeitado(a) em Comissão | AD73: 1 | AE73: 23256 | AF73: https://www.parlamento.pt/OrcamentoEstado/Paginas/DetalhePropostaAlteracao.aspx?BID=23256 | AG73: https://app.parlamento.pt/webutils/docs/doc.pdf?path=6148523063484d364c793942556b356c6443397a6158526c63793959566b6c4a544556484c3039464c7a49774d6a59794d4449314d5441774f5339515153396d5a5759314e44646b5a69316c4e6d56694c5451335a6a4d74596a55344e7930334e6a51305a5751324f4455334d5745756347526d&Fich=fef547df-e6eb-47f3-b587-7644ed68571a.pdf&Inline=true | AH73: 46321.778 | AI73: 46321.781
A74: 73 | B74: 64C | C74: 45960.499 | D74: Original | E74: PCP | F74: Alfredo Maia; Paula Santos; Paulo Raimundo | G74: Art. 27.º-A (aditamento) | L74: Artigo 27.º-A (Contratação de mediadores culturais e linguísticos para a Escola Pública) | S74: Rejeitado(a) em Comissão | T74: Rejeitada | U74: Favor: PS, L, PCP, BE, PAN; Contra: PSD, CH, IL, CDS-PP | V74: 45981 | W74: AR: https://www.parlamento.pt/OrcamentoEstado/Paginas/DetalhePropostaAlteracao.aspx?BID=23257 PDF: https://app.parlamento.pt/webutils/docs/doc.pdf?path=6148523063484d364c793942556b356c6443397a6158526c63793959566b6c4a544556484c3039464c7a49774d6a59794d4449314d5441774f5339515153396a596d49795a47526b4d793079596d45784c5451344e6a63744f54497a4d79307a5a57566c59574e6c4f445131597a49756347526d&Fich=cbb2ddd3-2ba1-4867-9233-3eeeace845c2.pdf&Inline=true | X74: Assuntos Constitucionais, Direitos, Liberdades e Garantias | Y74: Articulado | Z74: Aditamento (Artigo PPL) | AA74: Rejeitado(a) em Comissão | AD74: 1 | AE74: 23257 | AF74: https://www.parlamento.pt/OrcamentoEstado/Paginas/DetalhePropostaAlteracao.aspx?BID=23257 | AG74: https://app.parlamento.pt/webutils/docs/doc.pdf?path=6148523063484d364c793942556b356c6443397a6158526c63793959566b6c4a544556484c3039464c7a49774d6a59794d4449314d5441774f5339515153396a596d49795a47526b4d793079596d45784c5451344e6a63744f54497a4d79307a5a57566c59574e6c4f445131597a49756347526d&Fich=cbb2ddd3-2ba1-4867-9233-3eeeace845c2.pdf&Inline=true | AH74: 46321.778 | AI74: 46321.781
A75: 74 | B75: 65C | C75: 45960.502 | D75: Original | E75: PCP | F75: Alfredo Maia; Paula Santos; Paulo Raimundo | G75: Art. 27.º-A (aditamento) | L75: Artigo 27.º-A (Vinculação de trabalhadores e mediadores na Agência para a Integração, Migrações e Asilo) | S75: Rejeitado(a) em Comissão | T75: Rejeitada | U75: Favor: L, PCP, BE, PAN; Contra: PSD, CH, IL, CDS-PP; Abstenção: PS | V75: 45981 | W75: AR: https://www.parlamento.pt/OrcamentoEstado/Paginas/DetalhePropostaAlteracao.aspx?BID=23258 PDF: https://app.parlamento.pt/webutils/docs/doc.pdf?path=6148523063484d364c793942556b356c6443397a6158526c63793959566b6c4a544556484c3039464c7a49774d6a59794d4449314d5441774f533951515338325a6d59774e5445305953316b4e7a6c6d4c5452684e7a677459575a6d4f4331684e4467335a4749795954526b4f4441756347526d&Fich=6ff0514a-d79f-4a78-aff8-a487db2a4d80.pdf&Inline=true | X75: Assuntos Constitucionais, Direitos, Liberdades e Garantias | Y75: Articulado | Z75: Aditamento (Artigo PPL) | AA75: Rejeitado(a) em Comissão | AD75: 1 | AE75: 23258 | AF75: https://www.parlamento.pt/OrcamentoEstado/Paginas/DetalhePropostaAlteracao.aspx?BID=23258 | AG75: https://app.parlamento.pt/webutils/docs/doc.pdf?path=6148523063484d364c793942556b356c6443397a6158526c63793959566b6c4a544556484c3039464c7a49774d6a59794d4449314d5441774f533951515338325a6d59774e5445305953316b4e7a6c6d4c5452684e7a677459575a6d4f4331684e4467335a4749795954526b4f4441756347526d&Fich=6ff0514a-d79f-4a78-aff8-a487db2a4d80.pdf&Inline=true | AH75: 46321.778 | AI75: 46321.781
A76: 75 | B76: 66C | C76: 45960.503 | D76: Original | E76: PCP | F76: Alfredo Maia; Paula Santos; Paulo Raimundo | G76: Art. 135.º-A (aditamento) | L76: Artigo 135.º-A (Suspensão do aumento das taxas de requerimentos de autorização de residência e vistos de trabalho) | S76: Rejeitado(a) em Comissão | T76: Rejeitada | U76: Favor: L, PCP, BE, PAN; Contra: PSD, CH, IL, CDS-PP; Abstenção: PS | V76: 45987 | W76: AR: https://www.parlamento.pt/OrcamentoEstado/Paginas/DetalhePropostaAlteracao.aspx?BID=23259 PDF: https://app.parlamento.pt/webutils/docs/doc.pdf?path=6148523063484d364c793942556b356c6443397a6158526c63793959566b6c4a544556484c3039464c7a49774d6a59794d4449314d5441774f533951515338304d546c685a6a4d345a4330325a5745774c54517a4f5751744f47557a4e5330324e6a49355a546b794e5751354e4459756347526d&Fich=419af38d-6ea0-439d-8e35-6629e925d946.pdf&Inline=true | X76: Assuntos Constitucionais, Direitos, Liberdades e Garantias | Y76: Articulado | Z76: Aditamento (Artigo PPL) | AA76: Rejeitado(a) em Comissão | AD76: 1 | AE76: 23259 | AF76: https://www.parlamento.pt/OrcamentoEstado/Paginas/DetalhePropostaAlteracao.aspx?BID=23259 | AG76: https://app.parlamento.pt/webutils/docs/doc.pdf?path=6148523063484d364c793942556b356c6443397a6158526c63793959566b6c4a544556484c3039464c7a49774d6a59794d4449314d5441774f533951515338304d546c685a6a4d345a4330325a5745774c54517a4f5751744f47557a4e5330324e6a49355a546b794e5751354e4459756347526d&Fich=419af38d-6ea0-439d-8e35-6629e925d946.pdf&Inline=true | AH76: 46321.778 | AI76: 46321.781
A77: 76 | B77: 67C | C77: 45960.508 | D77: Original | E77: PCP | F77: Alfredo Maia; Paula Santos; Paulo Raimundo | G77: Art. 7.º (aditamento) | L77: Nova Verba 81, Mapa de alterações e transferências orçamentais, Artigo 7.º | S77: Rejeitado(a) em Comissão | T77: Rejeitada | U77: Favor: L, PCP, BE, PAN; Contra: PSD, CH, IL, CDS-PP; Abstenção: PS | V77: 45987 | W77: AR: https://www.parlamento.pt/OrcamentoEstado/Paginas/DetalhePropostaAlteracao.aspx?BID=23260 PDF: https://app.parlamento.pt/webutils/docs/doc.pdf?path=6148523063484d364c793942556b356c6443397a6158526c63793959566b6c4a544556484c3039464c7a49774d6a59794d4449314d5441774f5339515153396c4d4745344d3245774d79316d4d4463304c5451345a6d55744f4463794e6930334d324e685a6a5a6b4d7a526a5a5441756347526d&Fich=e0a83a03-f074-48fe-8726-73caf6d34ce0.pdf&Inline=true | X77: Assuntos Constitucionais, Direitos, Liberdades e Garantias | Y77: Articulado | Z77: Aditamento (Números e Alíneas) | AA77: Rejeitado(a) em Comissão | AD77: 1 | AE77: 23260 | AF77: https://www.parlamento.pt/OrcamentoEstado/Paginas/DetalhePropostaAlteracao.aspx?BID=23260 | AG77: https://app.parlamento.pt/webutils/docs/doc.pdf?path=6148523063484d364c793942556b356c6443397a6158526c63793959566b6c4a544556484c3039464c7a49774d6a59794d4449314d5441774f5339515153396c4d4745344d3245774d79316d4d4463304c5451345a6d55744f4463794e6930334d324e685a6a5a6b4d7a526a5a5441756347526d&Fich=e0a83a03-f074-48fe-8726-73caf6d34ce0.pdf&Inline=true | AH77: 46321.778 | AI77: 46321.781
A78: 77 | B78: 68C | C78: 45960.511 | D78: Original | E78: PCP | F78: Alfredo Maia; Paula Santos; Paulo Raimundo | G78: Art. 7.º (aditamento) | L78: Nova Verba 104, Mapa de alterações e transferências orçamentais, Artigo 7.º | S78: Rejeitado(a) em Comissão | T78: Rejeitada | U78: Favor: L, PCP, BE, PAN; Contra: PSD, CH, CDS-PP; Abstenção: PS, IL | V78: 45987 | W78: AR: https://www.parlamento.pt/OrcamentoEstado/Paginas/DetalhePropostaAlteracao.aspx?BID=23261 PDF: https://app.parlamento.pt/webutils/docs/doc.pdf?path=6148523063484d364c793942556b356c6443397a6158526c63793959566b6c4a544556484c3039464c7a49774d6a59794d4449314d5441774f5339515153396c4e7a4d345a47566a4d43316b4d5468684c54526c597a49744f54426d4d43316d5a5463775a6a6c684e544d344e444d756347526d&Fich=e738dec0-d18a-4ec2-90f0-fe70f9a53843.pdf&Inline=true | X78: Assuntos Constitucionais, Direitos, Liberdades e Garantias | Y78: Articulado | Z78: Aditamento (Números e Alíneas) | AA78: Rejeitado(a) em Comissão | AD78: 1 | AE78: 23261 | AF78: https://www.parlamento.pt/OrcamentoEstado/Paginas/DetalhePropostaAlteracao.aspx?BID=23261 | AG78: https://app.parlamento.pt/webutils/docs/doc.pdf?path=6148523063484d364c793942556b356c6443397a6158526c63793959566b6c4a544556484c3039464c7a49774d6a59794d4449314d5441774f5339515153396c4e7a4d345a47566a4d43316b4d5468684c54526c597a49744f54426d4d43316d5a5463775a6a6c684e544d344e444d756347526d&Fich=e738dec0-d18a-4ec2-90f0-fe70f9a53843.pdf&Inline=true | AH78: 46321.778 | AI78: 46321.781
A79: 78 | B79: 69C | C79: 45960.512 | D79: Original | E79: PCP | F79: Alfredo Maia; Paula Santos; Paulo Raimundo | G79: Art. 7.º (aditamento) | L79: Nova Verba 81, Mapa de alterações e transferências orçamentais, Artigo 7.º | S79: Rejeitado(a) em Comissão | T79: Rejeitada | U79: Favor: L, PCP, BE, PAN; Contra: PSD, CDS-PP; Abstenção: CH, PS, IL | V79: 45987 | W79: AR: https://www.parlamento.pt/OrcamentoEstado/Paginas/DetalhePropostaAlteracao.aspx?BID=23262 PDF: https://app.parlamento.pt/webutils/docs/doc.pdf?path=6148523063484d364c793942556b356c6443397a6158526c63793959566b6c4a544556484c3039464c7a49774d6a59794d4449314d5441774f533951515338774d5751315a44457a4d4330354d4449344c5451334d544d744f5441304d533031597a5978596d466b5a6a41354e6a63756347526d&Fich=01d5d130-9028-4713-9041-5c61badf0967.pdf&Inline=true | X79: Assuntos Constitucionais, Direitos, Liberdades e Garantias | Y79: Articulado | Z79: Aditamento (Números e Alíneas) | AA79: Rejeitado(a) em Comissão | AD79: 1 | AE79: 23262 | AF79: https://www.parlamento.pt/OrcamentoEstado/Paginas/DetalhePropostaAlteracao.aspx?BID=23262 | AG79: https://app.parlamento.pt/webutils/docs/doc.pdf?path=6148523063484d364c793942556b356c6443397a6158526c63793959566b6c4a544556484c3039464c7a49774d6a59794d4449314d5441774f533951515338774d5751315a44457a4d4330354d4449344c5451334d544d744f5441304d533031597a5978596d466b5a6a41354e6a63756347526d&Fich=01d5d130-9028-4713-9041-5c61badf0967.pdf&Inline=true | AH79: 46321.778 | AI79: 46321.781
A80: 79 | B80: 70C | C80: 45960.515 | D80: Original | E80: PCP | F80: Alfredo Maia; Paula Santos; Paulo Raimundo | G80: Art. 131.º (aditamento) | L80: Novo N.º 4, Artigo 131.º | S80: Rejeitado(a) em Comissão | T80: Rejeitada | U80: Favor: IL, L, PCP, BE, PAN; Contra: PSD, CH, CDS-PP; Abstenção: PS | V80: 45985 | W80: AR: https://www.parlamento.pt/OrcamentoEstado/Paginas/DetalhePropostaAlteracao.aspx?BID=23263 PDF: https://app.parlamento.pt/webutils/docs/doc.pdf?path=6148523063484d364c793942556b356c6443397a6158526c63793959566b6c4a544556484c3039464c7a49774d6a59794d4449314d5441774f533951515338334e7a4a6b5a5751305a693079596d55314c5451314d7a557459546b314e4331695a5459775954426b597a466b4d7a55756347526d&Fich=772ded4f-2be5-4535-a954-be60a0dc1d35.pdf&Inline=true | X80: Assuntos Constitucionais, Direitos, Liberdades e Garantias | Y80: Articulado | Z80: Aditamento (Números e Alíneas) | AA80: Rejeitado(a) em Comissão | AD80: 1 | AE80: 23263 | AF80: https://www.parlamento.pt/OrcamentoEstado/Paginas/DetalhePropostaAlteracao.aspx?BID=23263 | AG80: https://app.parlamento.pt/webutils/docs/doc.pdf?path=6148523063484d364c793942556b356c6443397a6158526c63793959566b6c4a544556484c3039464c7a49774d6a59794d4449314d5441774f533951515338334e7a4a6b5a5751305a693079596d55314c5451314d7a557459546b314e4331695a5459775954426b597a466b4d7a55756347526d&Fich=772ded4f-2be5-4535-a954-be60a0dc1d35.pdf&Inline=true | AH80: 46321.778 | AI80: 46321.781
... A87: 86 | B87: 77C | C87: 45960.757 | D87: Original | E87: L | F87: Filipa Pinto; Isabel Mendes Lopes; Jorge Pinto; Patrícia Gonçalves; Paulo Muacho; Rui Tavares | G87: Art. 119.º-A (aditamento) | L87: Artigo 119.º-A (Reforço do Programa de Saúde Sexual e Reprodutiva) | S87: Rejeitado(a) em Comissão | T87: Rejeitada | U87: Favor: L, PCP, BE, PAN; Contra: PSD, CDS-PP; Abstenção: CH, PS, IL | V87: 45985 | W87: AR: https://www.parlamento.pt/OrcamentoEstado/Paginas/DetalhePropostaAlteracao.aspx?BID=23270 PDF: https://app.parlamento.pt/webutils/docs/doc.pdf?path=6148523063484d364c793942556b356c6443397a6158526c63793959566b6c4a544556484c3039464c7a49774d6a59794d4449314d5441774f5339515153383359546c69597a59774e69307a4d6a41354c54526d4f5751745957566a4e4330774f446b7a4e44426a5a6a41324f4745756347526d&Fich=7a9bc606-3209-4f9d-aec4-089340cf068a.pdf&Inline=true | X87: Saúde | Y87: Articulado | Z87: Aditamento (Artigo PPL) | AA87: Rejeitado(a) em Comissão | AD87: 1 | AE87: 23270 | AF87: https://www.parlamento.pt/OrcamentoEstado/Paginas/DetalhePropostaAlteracao.aspx?BID=23270 | AG87: https://app.parlamento.pt/webutils/docs/doc.pdf?path=6148523063484d364c793942556b356c6443397a6158526c63793959566b6c4a544556484c3039464c7a49774d6a59794d4449314d5441774f5339515153383359546c69597a59774e69307a4d6a41354c54526d4f5751745957566a4e4330774f446b7a4e44426a5a6a41324f4745756347526d&Fich=7a9bc606-3209-4f9d-aec4-089340cf068a.pdf&Inline=true | AH87: 46321.778 | AI87: 46321.781
A88: 87 | B88: 78C | C88: 45960.77 | D88: Original | E88: L | F88: Filipa Pinto; Isabel Mendes Lopes; Jorge Pinto; Patrícia Gonçalves; Paulo Muacho; Rui Tavares | G88: Art. 17.º (aditamento) | L88: N.º 10, Artigo 17.º | S88: Rejeitado(a) em Plenário | T88: Rejeitada | U88: Favor: L, PCP, BE, PAN, JPP; Contra: PSD, IL, CDS-PP; Abstenção: CH, PS | V88: 45982 | W88: Avocada a Plenário. AR: https://www.parlamento.pt/OrcamentoEstado/Paginas/DetalhePropostaAlteracao.aspx?BID=23271 PDF: https://app.parlamento.pt/webutils/docs/doc.pdf?path=6148523063484d364c793942556b356c6443397a6158526c63793959566b6c4a544556484c3039464c7a49774d6a59794d4449314d5441774f5339515153396b4f4749314d6a466b597930334e7a6b784c5452685a574574595745314d53316c4e5441304f474a6b4d4752694d4759756347526d&Fich=d8b521dc-7791-4aea-aa51-e5048bd0db0f.pdf&Inline=true | X88: Saúde | Y88: Articulado | Z88: Aditamento (Números e Alíneas) | AA88: Rejeitado(a) em Plenário | AB88: S | AD88: 2 | AE88: 23271 | AF88: https://www.parlamento.pt/OrcamentoEstado/Paginas/DetalhePropostaAlteracao.aspx?BID=23271 | AG88: https://app.parlamento.pt/webutils/docs/doc.pdf?path=6148523063484d364c793942556b356c6443397a6158526c63793959566b6c4a544556484c3039464c7a49774d6a59794d4449314d5441774f5339515153396b4f4749314d6a466b597930334e7a6b784c5452685a574574595745314d53316c4e5441304f474a6b4d4752694d4759756347526d&Fich=d8b521dc-7791-4aea-aa51-e5048bd0db0f.pdf&Inline=true | AH88: 46321.778 | AI88: 46321.781
A89: 88 | B89: 79C-1 | C89: 45961.471 | D89: Original | E89: IL | F89: Angélique Da Teresa; Carlos Guimarães Pinto; Joana Cordeiro; Jorge Miguel Teixeira; Mariana Leitão; Mário Amorim Lopes; Miguel Rangel; Rodrigo Saraiva; Rui Rocha | G89: Art. 63.º (substituição) | L89: Verba 2.27, Lista I anexa ao Código do IVA | S89: Rejeitado(a) em Comissão | T89: Rejeitada | U89: Favor: CH, IL; Contra: PSD, PS, L, PCP, CDS-PP, BE; Abstenção: PAN | V89: 45982 | W89: AR: https://www.parlamento.pt/OrcamentoEstado/Paginas/DetalhePropostaAlteracao.aspx?BID=23272 PDF: https://app.parlamento.pt/webutils/docs/doc.pdf?path=6148523063484d364c793942556b356c6443397a6158526c63793959566b6c4a544556484c3039464c7a49774d6a59794d4449314d5441774f533951515338354d6a4d334d546b334e53316c4d4749324c5451314e545174596a6b344d69307a4f444e6c596a67794d5449345a474d756347526d&Fich=92371975-e0b6-4554-b982-383eb82128dc.pdf&Inline=true | X89: Comissão de Economia e Coesão Territorial; Infraestruturas, Mobilidade e Habitação; Orçamento, Finanças e Administração Pública | Y89: Articulado | Z89: Substituição | AA89: Rejeitado(a) em Comissão | AC89: 1 | AD89: 1 | AE89: 23272 | AF89: https://www.parlamento.pt/OrcamentoEstado/Paginas/DetalhePropostaAlteracao.aspx?BID=23272 | AG89: https://app.parlamento.pt/webutils/docs/doc.pdf?path=6148523063484d364c793942556b356c6443397a6158526c63793959566b6c4a544556484c3039464c7a49774d6a59794d4449314d5441774f533951515338354d6a4d334d546b334e53316c4d4749324c5451314e545174596a6b344d69307a4f444e6c596a67794d5449345a474d756347526d&Fich=92371975-e0b6-4554-b982-383eb82128dc.pdf&Inline=true | AH89: 46321.778 | AI89: 46321.781
A90: 89 | B90: 79C-2 | C90: 45961.471 | D90: Original | E90: IL | F90: Angélique Da Teresa; Carlos Guimarães Pinto; Joana Cordeiro; Jorge Miguel Teixeira; Mariana Leitão; Mário Amorim Lopes; Miguel Rangel; Rodrigo Saraiva; Rui Rocha | G90: Art. 63.º-A (aditamento) | L90: Artigo 63.º-A (Aditamento ao Código do IVA) | S90: Rejeitado(a) em Comissão | T90: Rejeitada | U90: Favor: CH, IL; Contra: PSD, PS, L, PCP, CDS-PP, BE; Abstenção: PAN | V90: 45982 | W90: AR: https://www.parlamento.pt/OrcamentoEstado/Paginas/DetalhePropostaAlteracao.aspx?BID=24483 PDF: https://app.parlamento.pt/webutils/docs/doc.pdf?path=6148523063484d364c793942556b356c6443397a6158526c63793959566b6c4a544556484c3039464c7a49774d6a59794d4449314d5441774f533951515338354f475a6b4e4751785a43316d4d4467334c5451324e574d74595445785969316d4d6a466d59575a6a4d474d335a6a55756347526d&Fich=98fd4d1d-f087-465c-a11b-f21fafc0c7f5.pdf&Inline=true | X90: Comissão de Economia e Coesão Territorial; Infraestruturas, Mobilidade e Habitação; Orçamento, Finanças e Administração Pública | Y90: Articulado | Z90: Aditamento (Artigo PPL) | AA90: Rejeitado(a) em Comissão | AC90: 2 | AD90: 1 | AE90: 24483 | AF90: https://www.parlamento.pt/OrcamentoEstado/Paginas/DetalhePropostaAlteracao.aspx?BID=24483 | AG90: https://app.parlamento.pt/webutils/docs/doc.pdf?path=6148523063484d364c793942556b356c6443397a6158526c63793959566b6c4a544556484c3039464c7a49774d6a59794d4449314d5441774f533951515338354f475a6b4e4751785a43316d4d4467334c5451324e574d74595445785969316d4d6a466d59575a6a4d474d335a6a55756347526d&Fich=98fd4d1d-f087-465c-a11b-f21fafc0c7f5.pdf&Inline=true | AH90: 46321.778 | AI90: 46321.781
A91: 90 | B91: 80C | C91: 45961.489 | D91: Original | E91: IL | F91: Angélique Da Teresa; Carlos Guimarães Pinto; Joana Cordeiro; Jorge Miguel Teixeira; Mariana Leitão; Mário Amorim Lopes; Miguel Rangel; Rodrigo Saraiva; Rui Rocha | G91: Art. 63.º-A (aditamento) | L91: Artigo 63.º-A (Alteração ao Decreto-Lei n.º 84/2017, de 21 de julho) | S91: Rejeitado(a) em Comissão | T91: Rejeitada | U91: Favor: IL, PAN; Contra: PSD, CDS-PP; Abstenção: CH, PS, L, PCP, BE | V91: 45982 | W91: AR: https://www.parlamento.pt/OrcamentoEstado/Paginas/DetalhePropostaAlteracao.aspx?BID=23273 PDF: https://app.parlamento.pt/webutils/docs/doc.pdf?path=6148523063484d364c793942556b356c6443397a6158526c63793959566b6c4a544556484c3039464c7a49774d6a59794d4449314d5441774f533951515338774d324d324e7a4a6859533034596d597a4c5451354e7a4974595445784f433079595441314e7a41785a5446684f5449756347526d&Fich=03c672aa-8bf3-4972-a118-2a05701e1a92.pdf&Inline=true | X91: Comissão de Economia e Coesão Territorial; Orçamento, Finanças e Administração Pública | Y91: Articulado | Z91: Aditamento (Artigo PPL) | AA91: Rejeitado(a) em Comissão | AD91: 1 | AE91: 23273 | AF91: https://www.parlamento.pt/OrcamentoEstado/Paginas/DetalhePropostaAlteracao.aspx?BID=23273 | AG91: https://app.parlamento.pt/webutils/docs/doc.pdf?path=6148523063484d364c793942556b356c6443397a6158526c63793959566b6c4a544556484c3039464c7a49774d6a59794d4449314d5441774f533951515338774d324d324e7a4a6859533034596d597a4c5451354e7a4974595445784f433079595441314e7a41785a5446684f5449756347526d&Fich=03c672aa-8bf3-4972-a118-2a05701e1a92.pdf&Inline=true | AH91: 46321.778 | AI91: 46321.781
A92: 91 | B92: 81C | C92: 45961.492 | D92: Original | E92: IL | F92: Angélique Da Teresa; Carlos Guimarães Pinto; Joana Cordeiro; Jorge Miguel Teixeira; Mariana Leitão; Mário Amorim Lopes; Miguel Rangel; Rodrigo Saraiva; Rui Rocha | G92: Art. 68.º-A (aditamento) | L92: Artigo 68.º-A (Alteração ao Código do Imposto Municipal sobre Imóveis) | S92: Rejeitado(a) em Comissão | T92: Rejeitada | U92: Favor: CH, IL, PAN; Contra: PSD, PS, PCP, CDS-PP, BE; Abstenção: L | V92: 45982 | W92: AR: https://www.parlamento.pt/OrcamentoEstado/Paginas/DetalhePropostaAlteracao.aspx?BID=23274 PDF: https://app.parlamento.pt/webutils/docs/doc.pdf?path=6148523063484d364c793942556b356c6443397a6158526c63793959566b6c4a544556484c3039464c7a49774d6a59794d4449314d5441774f5339515153387a597a5a6c4e6d59304e4330315a6a6b324c54517a5a574574596a41774d6930774e325132597a51354e7a55344d5463756347526d&Fich=3c6e6f44-5f96-43ea-b002-07d6c4975817.pdf&Inline=true | X92: Infraestruturas, Mobilidade e Habitação; Orçamento, Finanças e Administração Pública; Reforma do Estado e Poder Local | Y92: Articulado | Z92: Aditamento (Artigo PPL) | AA92: Rejeitado(a) em Comissão | AD92: 1 | AE92: 23274 | AF92: https://www.parlamento.pt/OrcamentoEstado/Paginas/DetalhePropostaAlteracao.aspx?BID=23274 | AG92: https://app.parlamento.pt/webutils/docs/doc.pdf?path=6148523063484d364c793942556b356c6443397a6158526c63793959566b6c4a544556484c3039464c7a49774d6a59794d4449314d5441774f5339515153387a597a5a6c4e6d59304e4330315a6a6b324c54517a5a574574596a41774d6930774e325132597a51354e7a55344d5463756347526d&Fich=3c6e6f44-5f96-43ea-b002-07d6c4975817.pdf&Inline=true | AH92: 46321.778 | AI92: 46321.781
A93: 92 | B93: 82C | C93: 45961.494 | D93: Original | E93: IL | F93: Angélique Da Teresa; Carlos Guimarães Pinto; Joana Cordeiro; Jorge Miguel Teixeira; Mariana Leitão; Mário Amorim Lopes; Miguel Rangel; Rodrigo Saraiva; Rui Rocha | G93: Art. 60.º-A (aditamento) | L93: Artigo 60.º-A (Isenção extraordinária de mais-valias de imóveis para habitação) | S93: Rejeitado(a) em Comissão | T93: Rejeitada | U93: Favor: CH, IL; Contra: PSD, PS, L, PCP, CDS-PP, BE, PAN | V93: 45981 | W93: AR: https://www.parlamento.pt/OrcamentoEstado/Paginas/DetalhePropostaAlteracao.aspx?BID=23275 PDF: https://app.parlamento.pt/webutils/docs/doc.pdf?path=6148523063484d364c793942556b356c6443397a6158526c63793959566b6c4a544556484c3039464c7a49774d6a59794d4449314d5441774f5339515153396d4d7a466c5a575669597930334d574d304c545135597a5574596d5579597930304d546b314e57526a595441324f5751756347526d&Fich=f31eeebc-71c4-49c5-be2c-41955dca069d.pdf&Inline=true | X93: Comissão de Economia e Coesão Territorial; Infraestruturas, Mobilidade e Habitação; Orçamento, Finanças e Administração Pública | Y93: Articulado | Z93: Aditamento (Artigo PPL) | AA93: Rejeitado(a) em Comissão | AD93: 1 | AE93: 23275 | AF93: https://www.parlamento.pt/OrcamentoEstado/Paginas/DetalhePropostaAlteracao.aspx?BID=23275 | AG93: https://app.parlamento.pt/webutils/docs/doc.pdf?path=6148523063484d364c793942556b356c6443397a6158526c63793959566b6c4a544556484c3039464c7a49774d6a59794d4449314d5441774f5339515153396d4d7a466c5a575669597930334d574d304c545135597a5574596d5579597930304d546b314e57526a595441324f5751756347526d&Fich=f31eeebc-71c4-49c5-be2c-41955dca069d.pdf&Inline=true | AH93: 46321.778 | AI93: 46321.781
A94: 93 | B94: 83C-1 | C94: 45961.497 | D94: Original | E94: IL | F94: Angélique Da Teresa; Carlos Guimarães Pinto; Joana Cordeiro; Jorge Miguel Teixeira; Mariana Leitão; Mário Amorim Lopes; Miguel Rangel; Rodrigo Saraiva; Rui Rocha | G94: Art. 60.º (substituição) | L94: Alínea a), N.º 5, Corpo, Alínea a), Alínea b), N.º 7, N.º 9, Artigo 10.º do Código do IRS | S94: Rejeitado(a) em Comissão | T94: Rejeitada | U94: Favor: CH, IL; Contra: PSD, PS, L, PCP, CDS-PP, BE; Abstenção: PAN | V94: 45981 | W94: AR: https://www.parlamento.pt/OrcamentoEstado/Paginas/DetalhePropostaAlteracao.aspx?BID=23276 PDF: https://app.parlamento.pt/webutils/docs/doc.pdf?path=6148523063484d364c793942556b356c6443397a6158526c63793959566b6c4a544556484c3039464c7a49774d6a59794d4449314d5441774f5339515153396c596d49335a446b315a6930314f44426a4c54526a4e325974595449334d433169596d51305a6a63344e7a63794d6d51756347526d&Fich=ebb7d95f-580c-4c7f-a270-bbd4f787722d.pdf&Inline=true | X94: Infraestruturas, Mobilidade e Habitação; Orçamento, Finanças e Administração Pública | Y94: Articulado | Z94: Substituição | AA94: Rejeitado(a) em Comissão | AC94: 1 | AD94: 1 | AE94: 23276 | AF94: https://www.parlamento.pt/OrcamentoEstado/Paginas/DetalhePropostaAlteracao.aspx?BID=23276 | AG94: https://app.parlamento.pt/webutils/docs/doc.pdf?path=6148523063484d364c793942556b356c6443397a6158526c63793959566b6c4a544556484c3039464c7a49774d6a59794d4449314d5441774f5339515153396c596d49335a446b315a6930314f44426a4c54526a4e325974595449334d433169596d51305a6a63344e7a63794d6d51756347526d&Fich=ebb7d95f-580c-4c7f-a270-bbd4f787722d.pdf&Inline=true | AH94: 46321.778 | AI94: 46321.781
A95: 94 | B95: 83C-2 | C95: 45961.497 | D95: Original | E95: IL | F95: Angélique Da Teresa; Carlos Guimarães Pinto; Joana Cordeiro; Jorge Miguel Teixeira; Mariana Leitão; Mário Amorim Lopes; Miguel Rangel; Rodrigo Saraiva; Rui Rocha | G95: Art. 60.º (aditamento) | L95: Subalínea V), Subalínea VI), Alínea a), N.º 7, N.º 24, Artigo 10.º do Código do IRS | S95: Rejeitado(a) em Comissão | T95: Rejeitada | U95: Favor: CH, IL; Contra: PSD, PS, L, PCP, CDS-PP, BE; Abstenção: PAN | V95: 45981 | W95: AR: https://www.parlamento.pt/OrcamentoEstado/Paginas/DetalhePropostaAlteracao.aspx?BID=23596 PDF: https://app.parlamento.pt/webutils/docs/doc.pdf?path=6148523063484d364c793942556b356c6443397a6158526c63793959566b6c4a544556484c3039464c7a49774d6a59794d4449314d5441774f533951515338784d5441324d446b314e43316d5a5455324c5451325a546b744f4455775a53307a4d3251334e546c6a4f5745354d6d49756347526d&Fich=11060954-fe56-46e9-850e-33d759c9a92b.pdf&Inline=true | X95: Infraestruturas, Mobilidade e Habitação; Orçamento, Finanças e Administração Pública | Y95: Articulado | Z95: Aditamento (Números e Alíneas) | AA95: Rejeitado(a) em Comissão | AC95: 2 | AD95: 1 | AE95: 23596 | AF95: https://www.parlamento.pt/OrcamentoEstado/Paginas/DetalhePropostaAlteracao.aspx?BID=23596 | AG95: https://app.parlamento.pt/webutils/docs/doc.pdf?path=6148523063484d364c793942556b356c6443397a6158526c63793959566b6c4a544556484c3039464c7a49774d6a59794d4449314d5441774f533951515338784d5441324d446b314e43316d5a5455324c5451325a546b744f4455775a53307a4d3251334e546c6a4f5745354d6d49756347526d&Fich=11060954-fe56-46e9-850e-33d759c9a92b.pdf&Inline=true | AH95: 46321.778 | AI95: 46321.781
A96: 95 | B96: 83C-3 | C96: 45961.497 | D96: Original | E96: IL | F96: Angélique Da Teresa; Carlos Guimarães Pinto; Joana Cordeiro; Jorge Miguel Teixeira; Mariana Leitão; Mário Amorim Lopes; Miguel Rangel; Rodrigo Saraiva; Rui Rocha | G96: Art. 138.º (aditamento) | L96: Alínea c), Artigo 138.º | S96: Rejeitado(a) em Comissão | T96: Rejeitada | U96: Favor: CH, IL; Contra: PSD, PS, L, PCP, CDS-PP, BE; Abstenção: PAN | V96: 45987 | W96: AR: https://www.parlamento.pt/OrcamentoEstado/Paginas/DetalhePropostaAlteracao.aspx?BID=23622 PDF: https://app.parlamento.pt/webutils/docs/doc.pdf?path=6148523063484d364c793942556b356c6443397a6158526c63793959566b6c4a544556484c3039464c7a49774d6a59794d4449314d5441774f5339515153396d4d445131596a45314f4330314e7a6b304c54517a5a6d51744f474e6c4d53316a595467784e6a566a59574e6d4d6d59756347526d&Fich=f045b158-5794-43fd-8ce1-ca8165cacf2f.pdf&Inline=true | X96: Infraestruturas, Mobilidade e Habitação; Orçamento, Finanças e Administração Pública | Y96: Articulado | Z96: Aditamento (Números e Alíneas) | AA96: Rejeitado(a) em Comissão | AC96: 3 | AD96: 1 | AE96: 23622 | AF96: https://www.parlamento.pt/OrcamentoEstado/Paginas/DetalhePropostaAlteracao.aspx?BID=23622 | AG96: https://app.parlamento.pt/webutils/docs/doc.pdf?path=6148523063484d364c793942556b356c6443397a6158526c63793959566b6c4a544556484c3039464c7a49774d6a59794d4449314d5441774f5339515153396d4d445131596a45314f4330314e7a6b304c54517a5a6d51744f474e6c4d53316a595467784e6a566a59574e6d4d6d59756347526d&Fich=f045b158-5794-43fd-8ce1-ca8165cacf2f.pdf&Inline=true | AH96: 46321.778 | AI96: 46321.781
A97: 96 | B97: 84C | C97: 45961.5 | D97: Retirada | E97: IL | F97: Angélique Da Teresa; Carlos Guimarães Pinto; Joana Cordeiro; Jorge Miguel Teixeira; Mariana Leitão; Mário Amorim Lopes; Miguel Rangel; Rodrigo Saraiva; Rui Rocha | G97: Art. 62.º-A (aditamento) | L97: Artigo 62.º-A (Aditamento ao Estatuto dos Benefícios Fiscais) | S97: Retirado(a) | T97: Retirada | W97: AR: https://www.parlamento.pt/OrcamentoEstado/Paginas/DetalhePropostaAlteracao.aspx?BID=23277 PDF: https://app.parlamento.pt/webutils/docs/doc.pdf?path=6148523063484d364c793942556b356c6443397a6158526c63793959566b6c4a544556484c3039464c7a49774d6a59794d4449314d5441774f533951515338304e324d33596d59354f43307a4d6a5a6d4c5451325a6a4d745954566d5969303559544e6c4f4445774e7a49775a6a4d756347526d&Fich=47c7bf98-326f-46f3-a5fb-9a3e810720f3.pdf&Inline=true | X97: Infraestruturas, Mobilidade e Habitação; Orçamento, Finanças e Administração Pública | Y97: Articulado | Z97: Aditamento (Artigo PPL) | AA97: Retirado(a) | AD97: 0 | AE97: 23277 | AF97: https://www.parlamento.pt/OrcamentoEstado/Paginas/DetalhePropostaAlteracao.aspx?BID=23277 | AG97: https://app.parlamento.pt/webutils/docs/doc.pdf?path=6148523063484d364c793942556b356c6443397a6158526c63793959566b6c4a544556484c3039464c7a49774d6a59794d4449314d5441774f533951515338304e324d33596d59354f43307a4d6a5a6d4c5451325a6a4d745954566d5969303559544e6c4f4445774e7a49775a6a4d756347526d&Fich=47c7bf98-326f-46f3-a5fb-9a3e810720f3.pdf&Inline=true | AH97: 46321.778 | AI97: 46321.781
A98: 97 | B98: 85C | C98: 45961.755 | D98: Original | E98: L | F98: Filipa Pinto; Isabel Mendes Lopes; Jorge Pinto; Patrícia Gonçalves; Paulo Muacho; Rui Tavares | G98: Art. 123.º-A (aditamento) | L98: Artigo 123.º-A (Passe de Mobilidade Nacional) | S98: Rejeitado(a) em Comissão | T98: Rejeitada | U98: Favor: L, BE, PAN; Contra: PSD, IL, CDS-PP; Abstenção: CH, PS, PCP | V98: 45985 | W98: AR: https://www.parlamento.pt/OrcamentoEstado/Paginas/DetalhePropostaAlteracao.aspx?BID=23278 PDF: https://app.parlamento.pt/webutils/docs/doc.pdf?path=6148523063484d364c793942556b356c6443397a6158526c63793959566b6c4a544556484c3039464c7a49774d6a59794d4449314d5441774f5339515153396c4d544e695a446c684e5330785a44466c4c54517a4e325174596a56684f4330774f5445334d7a49334e3245324d4751756347526d&Fich=e13bd9a5-1d1e-437d-b5a8-09173277a60d.pdf&Inline=true | X98: Infraestruturas, Mobilidade e Habitação | Y98: Articulado | Z98: Aditamento (Artigo PPL) | AA98: Rejeitado(a) em Comissão | AD98: 1 | AE98: 23278 | AF98: https://www.parlamento.pt/OrcamentoEstado/Paginas/DetalhePropostaAlteracao.aspx?BID=23278 | AG98: https://app.parlamento.pt/webutils/docs/doc.pdf?path=6148523063484d364c793942556b356c6443397a6158526c63793959566b6c4a544556484c3039464c7a49774d6a59794d4449314d5441774f5339515153396c4d544e695a446c684e5330785a44466c4c54517a4e325174596a56684f4330774f5445334d7a49334e3245324d4751756347526d&Fich=e13bd9a5-1d1e-437d-b5a8-09173277a60d.pdf&Inline=true | AH98: 46321.778 | AI98: 46321.781
A99: 98 | B99: 86C | C99: 45961.812 | D99: Original | E99: L | F99: Filipa Pinto; Isabel Mendes Lopes; Jorge Pinto; Patrícia Gonçalves; Paulo Muacho; Rui Tavares | G99: Art. 123.º-A (aditamento) | L99: Artigo 123.º-A (Estrutura de Missão para a Mobilidade Ativa) | S99: Rejeitado(a) em Comissão | T99: Rejeitada | U99: Favor: L, PCP, BE, PAN; Contra: PSD, CH, IL, CDS-PP; Abstenção: PS | V99: 45985 | W99: AR: https://www.parlamento.pt/OrcamentoEstado/Paginas/DetalhePropostaAlteracao.aspx?BID=23279 PDF: https://app.parlamento.pt/webutils/docs/doc.pdf?path=6148523063484d364c793942556b356c6443397a6158526c63793959566b6c4a544556484c3039464c7a49774d6a59794d4449314d5441774f533951515338774e4749784e6d5a6d5a5331695a6d45324c5451314e324d744f4459324d6930354f444e6a4f4745344e6d4e694e6a55756347526d&Fich=04b16ffe-bfa6-457c-8662-983c8a86cb65.pdf&Inline=true | X99: Infraestruturas, Mobilidade e Habitação | Y99: Articulado | Z99: Aditamento (Artigo PPL) | AA99: Rejeitado(a) em Comissão | AD99: 1 | AE99: 23279 | AF99: https://www.parlamento.pt/OrcamentoEstado/Paginas/DetalhePropostaAlteracao.aspx?BID=23279 | AG99: https://app.parlamento.pt/webutils/docs/doc.pdf?path=6148523063484d364c793942556b356c6443397a6158526c63793959566b6c4a544556484c3039464c7a49774d6a59794d4449314d5441774f533951515338774e4749784e6d5a6d5a5331695a6d45324c5451314e324d744f4459324d6930354f444e6a4f4745344e6d4e694e6a55756347526d&Fich=04b16ffe-bfa6-457c-8662-983c8a86cb65.pdf&Inline=true | AH99: 46321.778 | AI99: 46321.781
A100: 99 | B100: 87C | C100: 45961.819 | D100: Original | E100: L | F100: Filipa Pinto; Isabel Mendes Lopes; Jorge Pinto; Patrícia Gonçalves; Paulo Muacho; Rui Tavares | G100: Art. 123.º-A (aditamento) | L100: Artigo 123.º-A (Retoma dos comboios noturnos internacionais Portugal-Espanha) | S100: Aprovado(a) em Comissão | T100: Aprovada | U100: Favor: CH, PS, L, PCP, BE, PAN; Contra: PSD, CDS-PP; Abstenção: IL | V100: 45985 | W100: AR: https://www.parlamento.pt/OrcamentoEstado/Paginas/DetalhePropostaAlteracao.aspx?BID=23280 PDF: https://app.parlamento.pt/webutils/docs/doc.pdf?path=6148523063484d364c793942556b356c6443397a6158526c63793959566b6c4a544556484c3039464c7a49774d6a59794d4449314d5441774f533951515338314d546c685a444a6d4f53316b5954466c4c545134595463744f544a694d433032597a49314f44426d4d4449795a4451756347526d&Fich=519ad2f9-da1e-48a7-92b0-6c2580f022d4.pdf&Inline=true | X100: Infraestruturas, Mobilidade e Habitação | Y100: Articulado | Z100: Aditamento (Artigo PPL) | AA100: Aprovado(a) em Comissão | AD100: 1 | AE100: 23280 | AF100: https://www.parlamento.pt/OrcamentoEstado/Paginas/DetalhePropostaAlteracao.aspx?BID=23280 | AG100: https://app.parlamento.pt/webutils/docs/doc.pdf?path=6148523063484d364c793942556b356c6443397a6158526c63793959566b6c4a544556484c3039464c7a49774d6a59794d4449314d5441774f533951515338314d546c685a444a6d4f53316b5954466c4c545134595463744f544a694d433032597a49314f44426d4d4449795a4451756347526d&Fich=519ad2f9-da1e-48a7-92b0-6c2580f022d4.pdf&Inline=true | AH100: 46321.778 | AI100: 46321.781
A101: 100 | B101: 88C | C101: 45961.828 | D101: Original | E101: L | F101: Filipa Pinto; Isabel Mendes Lopes; Jorge Pinto; Patrícia Gonçalves; Paulo Muacho; Rui Tavares | G101: Art. 67.º (substituição) | L101: N.º 2, N.º 4, Artigo 54.º do Código do ISV | S101: Rejeitado(a) em Comissão | T101: Rejeitada | U101: Favor: IL, L, PCP, BE, PAN; Contra: PSD, CH, CDS-PP; Abstenção: PS | V101: 45982 | W101: AR: https://www.parlamento.pt/OrcamentoEstado/Paginas/DetalhePropostaAlteracao.aspx?BID=23281 PDF: https://app.parlamento.pt/webutils/docs/doc.pdf?path=6148523063484d364c793942556b356c6443397a6158526c63793959566b6c4a544556484c3039464c7a49774d6a59794d4449314d5441774f533951515339684f474d78596d49315969307a5a4459314c5451774d574574595451324d4331694e6d55344d7a4e6c5a6d466c595459756347526d&Fich=a8c1bb5b-3d65-401a-a460-b6e833efaea6.pdf&Inline=true | X101: Infraestruturas, Mobilidade e Habitação; Orçamento, Finanças e Administração Pública | Y101: Articulado | Z101: Substituição | AA101: Rejeitado(a) em Comissão | AD101: 1 | AE101: 23281 | AF101: https://www.parlamento.pt/OrcamentoEstado/Paginas/DetalhePropostaAlteracao.aspx?BID=23281 | AG101: https://app.parlamento.pt/webutils/docs/doc.pdf?path=6148523063484d364c793942556b356c6443397a6158526c63793959566b6c4a544556484c3039464c7a49774d6a59794d4449314d5441774f533951515339684f474d78596d49315969307a5a4459314c5451774d574574595451324d4331694e6d55344d7a4e6c5a6d466c595459756347526d&Fich=a8c1bb5b-3d65-401a-a460-b6e833efaea6.pdf&Inline=true | AH101: 46321.778 | AI101: 46321.781
A102: 101 | B102: 89C | C102: 45961.832 | D102: Original | E102: L | F102: Filipa Pinto; Isabel Mendes Lopes; Jorge Pinto; Patrícia Gonçalves; Paulo Muacho; Rui Tavares | G102: Art. 67.º (substituição) | L102: Alínea a), N.º 1, Artigo 55.º do Código do ISV | S102: Rejeitado(a) em Comissão | T102: Rejeitada | U102: Favor: IL, L, PCP, BE, PAN; Contra: PSD, CH, CDS-PP; Abstenção: PS | V102: 45982 | W102: AR: https://www.parlamento.pt/OrcamentoEstado/Paginas/DetalhePropostaAlteracao.aspx?BID=23282 PDF: https://app.parlamento.pt/webutils/docs/doc.pdf?path=6148523063484d364c793942556b356c6443397a6158526c63793959566b6c4a544556484c3039464c7a49774d6a59794d4449314d5441774f533951515338794e47466b4d44466c4d69316b5a5451774c5452694d6d5974596a5535597930785a6a4935596a67334d446b774e5445756347526d&Fich=24ad01e2-de40-4b2f-b59c-1f29b8709051.pdf&Inline=true | X102: Infraestruturas, Mobilidade e Habitação; Orçamento, Finanças e Administração Pública | Y102: Articulado | Z102: Substituição | AA102: Rejeitado(a) em Comissão | AD102: 1 | AE102: 23282 | AF102: https://www.parlamento.pt/OrcamentoEstado/Paginas/DetalhePropostaAlteracao.aspx?BID=23282 | AG102: https://app.parlamento.pt/webutils/docs/doc.pdf?path=6148523063484d364c793942556b356c6443397a6158526c63793959566b6c4a544556484c3039464c7a49774d6a59794d4449314d5441774f533951515338794e47466b4d44466c4d69316b5a5451774c5452694d6d5974596a5535597930785a6a4935596a67334d446b774e5445756347526d&Fich=24ad01e2-de40-4b2f-b59c-1f29b8709051.pdf&Inline=true | AH102: 46321.778 | AI102: 46321.781
A103: 102 | B103: 90C | C103: 45961.835 | D103: Original | E103: L | F103: Filipa Pinto; Isabel Mendes Lopes; Jorge Pinto; Patrícia Gonçalves; Paulo Muacho; Rui Tavares | G103: Art. 138.º (aditamento) | L103: Alínea c), Artigo 138.º | S103: Rejeitado(a) em Comissão | T103: Rejeitada | U103: Favor: IL, L, PCP, BE, PAN; Contra: PSD, CDS-PP; Abstenção: CH, PS | V103: 45987 | W103: AR: https://www.parlamento.pt/OrcamentoEstado/Paginas/DetalhePropostaAlteracao.aspx?BID=23283 PDF: https://app.parlamento.pt/webutils/docs/doc.pdf?path=6148523063484d364c793942556b356c6443397a6158526c63793959566b6c4a544556484c3039464c7a49774d6a59794d4449314d5441774f533951515338304e4455784d6a426c4d69316a5a4449324c5451794f545174596d5a6a5969316c4d4445774e54466a4d6d56694f5751756347526d&Fich=445120e2-cd26-4294-bfcb-e01051c2eb9d.pdf&Inline=true | X103: Infraestruturas, Mobilidade e Habitação; Orçamento, Finanças e Administração Pública | Y103: Articulado | Z103: Aditamento (Números e Alíneas) | AA103: Rejeitado(a) em Comissão | AD103: 1 | AE103: 23283 | AF103: https://www.parlamento.pt/OrcamentoEstado/Paginas/DetalhePropostaAlteracao.aspx?BID=23283 | AG103: https://app.parlamento.pt/webutils/docs/doc.pdf?path=6148523063484d364c793942556b356c6443397a6158526c63793959566b6c4a544556484c3039464c7a49774d6a59794d4449314d5441774f533951515338304e4455784d6a426c4d69316a5a4449324c5451794f545174596d5a6a5969316c4d4445774e54466a4d6d56694f5751756347526d&Fich=445120e2-cd26-4294-bfcb-e01051c2eb9d.pdf&Inline=true | AH103: 46321.778 | AI103: 46321.781
A104: 103 | B104: 91C | C104: 45961.84 | D104: Original | E104: L | F104: Filipa Pinto; Isabel Mendes Lopes; Jorge Pinto; Patrícia Gonçalves; Paulo Muacho; Rui Tavares | G104: Art. 126.º-A (aditamento) | L104: Artigo 126.º-A (Apoio para instalação de hangares de bicicletas em parques de estacionamento) | S104: Rejeitado(a) em Comissão | T104: Rejeitada | U104: Favor: L, BE, PAN; Contra: PSD, CH, CDS-PP; Abstenção: PS, IL, PCP | V104: 45985 | W104: AR: https://www.parlamento.pt/OrcamentoEstado/Paginas/DetalhePropostaAlteracao.aspx?BID=23284 PDF: https://app.parlamento.pt/webutils/docs/doc.pdf?path=6148523063484d364c793942556b356c6443397a6158526c63793959566b6c4a544556484c3039464c7a49774d6a59794d4449314d5441774f533951515338304e546c6b4f574a6a5969316b59324e694c5451774d545174596d597a4f53307859325534596a517a4f4745304e6a51756347526d&Fich=459d9bcb-dccb-4014-bf39-1ce8b438a464.pdf&Inline=true | X104: Ambiente e Energia; Infraestruturas, Mobilidade e Habitação | Y104: Articulado | Z104: Aditamento (Artigo PPL) | AA104: Rejeitado(a) em Comissão | AD104: 1 | AE104: 23284 | AF104: https://www.parlamento.pt/OrcamentoEstado/Paginas/DetalhePropostaAlteracao.aspx?BID=23284 | AG104: https://app.parlamento.pt/webutils/docs/doc.pdf?path=6148523063484d364c793942556b356c6443397a6158526c63793959566b6c4a544556484c3039464c7a49774d6a59794d4449314d5441774f533951515338304e546c6b4f574a6a5969316b59324e694c5451774d545174596d597a4f53307859325534596a517a4f4745304e6a51756347526d&Fich=459d9bcb-dccb-4014-bf39-1ce8b438a464.pdf&Inline=true | AH104: 46321.778 | AI104: 46321.781
A105: 104 | B105: 92C | C105: 45961.843 | D105: Original | E105: L | F105: Filipa Pinto; Isabel Mendes Lopes; Jorge Pinto; Patrícia Gonçalves; Paulo Muacho; Rui Tavares | G105: Art. 126.º-A (aditamento) | L105: Artigo 126.º-A (Projetos-piloto de logística urbana sustentável) | S105: Rejeitado(a) em Comissão | T105: Rejeitada | U105: Favor: L, PCP, BE, PAN; Contra: PSD, CH, IL, CDS-PP; Abstenção: PS | V105: 45985 | W105: AR: https://www.parlamento.pt/OrcamentoEstado/Paginas/DetalhePropostaAlteracao.aspx?BID=23285 PDF: https://app.parlamento.pt/webutils/docs/doc.pdf?path=6148523063484d364c793942556b356c6443397a6158526c63793959566b6c4a544556484c3039464c7a49774d6a59794d4449314d5441774f533951515338784e3245305a546b354e5330784f5441784c54526b4e474974595749304f5331695a544a694e5755354e6a59315a4759756347526d&Fich=17a4e995-1901-4d4b-ab49-be2b5e9665df.pdf&Inline=true | X105: Ambiente e Energia; Infraestruturas, Mobilidade e Habitação | Y105: Articulado | Z105: Aditamento (Artigo PPL) | AA105: Rejeitado(a) em Comissão | AD105: 1 | AE105: 23285 | AF105: https://www.parlamento.pt/OrcamentoEstado/Paginas/DetalhePropostaAlteracao.aspx?BID=23285 | AG105: https://app.parlamento.pt/webutils/docs/doc.pdf?path=6148523063484d364c793942556b356c6443397a6158526c63793959566b6c4a544556484c3039464c7a49774d6a59794d4449314d5441774f533951515338784e3245305a546b354e5330784f5441784c54526b4e474974595749304f5331695a544a694e5755354e6a59315a4759756347526d&Fich=17a4e995-1901-4d4b-ab49-be2b5e9665df.pdf&Inline=true | AH105: 46321.778 | AI105: 46321.781
A106: 105 | B106: 93C | C106: 45961.847 | D106: Original | E106: L | F106: Filipa Pinto; Isabel Mendes Lopes; Jorge Pinto; Patrícia Gonçalves; Paulo Muacho; Rui Tavares | G106: Art. 22.º-A (aditamento) | L106: Artigo 22.º-A (Projeto-Piloto Saúde Materna Mais Próxima) | S106: Rejeitado(a) em Comissão | T106: Rejeitada | U106: Favor: IL, L, BE, PAN; Contra: PSD, CDS-PP; Abstenção: CH, PS, PCP | V106: 45981 | W106: AR: https://www.parlamento.pt/OrcamentoEstado/Paginas/DetalhePropostaAlteracao.aspx?BID=23286 PDF: https://app.parlamento.pt/webutils/docs/doc.pdf?path=6148523063484d364c793942556b356c6443397a6158526c63793959566b6c4a544556484c3039464c7a49774d6a59794d4449314d5441774f533951515338335a444a694f5445774d69307a595445314c5451345a5759744f446c6b5a53316c4d446c6d5954426b4f4441325a6a67756347526d&Fich=7d2b9102-3a15-48ef-89de-e09fa0d806f8.pdf&Inline=true | X106: Saúde | Y106: Articulado | Z106: Aditamento (Artigo PPL) | AA106: Rejeitado(a) em Comissão | AD106: 1 | AE106: 23286 | AF106: https://www.parlamento.pt/OrcamentoEstado/Paginas/DetalhePropostaAlteracao.aspx?BID=23286 | AG106: https://app.parlamento.pt/webutils/docs/doc.pdf?path=6148523063484d364c793942556b356c6443397a6158526c63793959566b6c4a544556484c3039464c7a49774d6a59794d4449314d5441774f533951515338335a444a694f5445774d69307a595445314c5451345a5759744f446c6b5a53316c4d446c6d5954426b4f4441325a6a67756347526d&Fich=7d2b9102-3a15-48ef-89de-e09fa0d806f8.pdf&Inline=true | AH106: 46321.778 | AI106: 46321.781
...

Sheet Medidas Anunciadas
A1: ID | B1: Data do Anúncio | C1: Partido | D1: Quem Anunciou | E1: Natureza | F1: Medida Anunciada | G1: Tema | H1: Valor Anunciado | I1: Canal Oficial | J1: Ligação | K1: Entregue como PA (S/N) | L1: N.º PA Associada | M1: Observações

Sheet Ponto de Situação
A1: Propostas de alteração à Proposta de Lei n.º 37/XVII/1.ª (Orçamento do Estado para 2026)
A2: Última atualização: | B2: 26/10/2026, 21h59 UTC
A3: Situação na fonte oficial: | B3: 2076 PA (2193 registos, com as partes) publicadas pela AR; última entrada registada: 2025-11-07 20:00.
A5: Total de PA registadas | B5: =COUNTA('Propostas de Alteração'!B2:B5001)
A7: Por partido
A8: Partido | B8: N.º PA | C8: Aprovadas | D8: Rejeitadas
A9: PSD | B9: =COUNTIF('Propostas de Alteração'!$E$2:$E$5001,A9) | C9: =COUNTIFS('Propostas de Alteração'!$E$2:$E$5001,A9,'Propostas de Alteração'!$T$2:$T$5001,"Aprovada") | D9: =COUNTIFS('Propostas de Alteração'!$E$2:$E$5001,A9,'Propostas de Alteração'!$T$2:$T$5001,"Rejeitada")
A10: CH | B10: =COUNTIF('Propostas de Alteração'!$E$2:$E$5001,A10) | C10: =COUNTIFS('Propostas de Alteração'!$E$2:$E$5001,A10,'Propostas de Alteração'!$T$2:$T$5001,"Aprovada") | D10: =COUNTIFS('Propostas de Alteração'!$E$2:$E$5001,A10,'Propostas de Alteração'!$T$2:$T$5001,"Rejeitada")
A11: PS | B11: =COUNTIF('Propostas de Alteração'!$E$2:$E$5001,A11) | C11: =COUNTIFS('Propostas de Alteração'!$E$2:$E$5001,A11,'Propostas de Alteração'!$T$2:$T$5001,"Aprovada") | D11: =COUNTIFS('Propostas de Alteração'!$E$2:$E$5001,A11,'Propostas de Alteração'!$T$2:$T$5001,"Rejeitada")
A12: IL | B12: =COUNTIF('Propostas de Alteração'!$E$2:$E$5001,A12) | C12: =COUNTIFS('Propostas de Alteração'!$E$2:$E$5001,A12,'Propostas de Alteração'!$T$2:$T$5001,"Aprovada") | D12: =COUNTIFS('Propostas de Alteração'!$E$2:$E$5001,A12,'Propostas de Alteração'!$T$2:$T$5001,"Rejeitada")
A13: L | B13: =COUNTIF('Propostas de Alteração'!$E$2:$E$5001,A13) | C13: =COUNTIFS('Propostas de Alteração'!$E$2:$E$5001,A13,'Propostas de Alteração'!$T$2:$T$5001,"Aprovada") | D13: =COUNTIFS('Propostas de Alteração'!$E$2:$E$5001,A13,'Propostas de Alteração'!$T$2:$T$5001,"Rejeitada")
A14: PCP | B14: =COUNTIF('Propostas de Alteração'!$E$2:$E$5001,A14) | C14: =COUNTIFS('Propostas de Alteração'!$E$2:$E$5001,A14,'Propostas de Alteração'!$T$2:$T$5001,"Aprovada") | D14: =COUNTIFS('Propostas de Alteração'!$E$2:$E$5001,A14,'Propostas de Alteração'!$T$2:$T$5001,"Rejeitada")
A15: CDS-PP | B15: =COUNTIF('Propostas de Alteração'!$E$2:$E$5001,A15) | C15: =COUNTIFS('Propostas de Alteração'!$E$2:$E$5001,A15,'Propostas de Alteração'!$T$2:$T$5001,"Aprovada") | D15: =COUNTIFS('Propostas de Alteração'!$E$2:$E$5001,A15,'Propostas de Alteração'!$T$2:$T$5001,"Rejeitada")
A16: BE | B16: =COUNTIF('Propostas de Alteração'!$E$2:$E$5001,A16) | C16: =COUNTIFS('Propostas de Alteração'!$E$2:$E$5001,A16,'Propostas de Alteração'!$T$2:$T$5001,"Aprovada") | D16: =COUNTIFS('Propostas de Alteração'!$E$2:$E$5001,A16,'Propostas de Alteração'!$T$2:$T$5001,"Rejeitada")
A17: PAN | B17: =COUNTIF('Propostas de Alteração'!$E$2:$E$5001,A17) | C17: =COUNTIFS('Propostas de Alteração'!$E$2:$E$5001,A17,'Propostas de Alteração'!$T$2:$T$5001,"Aprovada") | D17: =COUNTIFS('Propostas de Alteração'!$E$2:$E$5001,A17,'Propostas de Alteração'!$T$2:$T$5001,"Rejeitada")
A18: JPP | B18: =COUNTIF('Propostas de Alteração'!$E$2:$E$5001,A18) | C18: =COUNTIFS('Propostas de Alteração'!$E$2:$E$5001,A18,'Propostas de Alteração'!$T$2:$T$5001,"Aprovada") | D18: =COUNTIFS('Propostas de Alteração'!$E$2:$E$5001,A18,'Propostas de Alteração'!$T$2:$T$5001,"Rejeitada")
A19: Deputado único/não inscrito | B19: =COUNTIF('Propostas de Alteração'!$E$2:$E$5001,A19) | C19: =COUNTIFS('Propostas de Alteração'!$E$2:$E$5001,A19,'Propostas de Alteração'!$T$2:$T$5001,"Aprovada") | D19: =COUNTIFS('Propostas de Alteração'!$E$2:$E$5001,A19,'Propostas de Alteração'!$T$2:$T$5001,"Rejeitada")
A20: Vários | B20: =COUNTIF('Propostas de Alteração'!$E$2:$E$5001,A20) | C20: =COUNTIFS('Propostas de Alteração'!$E$2:$E$5001,A20,'Propostas de Alteração'!$T$2:$T$5001,"Aprovada") | D20: =COUNTIFS('Propostas de Alteração'!$E$2:$E$5001,A20,'Propostas de Alteração'!$T$2:$T$5001,"Rejeitada")
A21: Total | B21: =SUM(B9:B20) | C21: =SUM(C9:C20) | D21: =SUM(D9:D20)
A23: Por resultado da votação
A24: Resultado | B24: N.º PA
A25: Aprovada | B25: =COUNTIF('Propostas de Alteração'!$T$2:$T$5001,A25)
A26: Rejeitada | B26: =COUNTIF('Propostas de Alteração'!$T$2:$T$5001,A26)
A27: Prejudicada | B27: =COUNTIF('Propostas de Alteração'!$T$2:$T$5001,A27)
A28: Retirada | B28: =COUNTIF('Propostas de Alteração'!$T$2:$T$5001,A28)
A29: Aprovada parcialmente | B29: =COUNTIF('Propostas de Alteração'!$T$2:$T$5001,A29)
A30: Sem resultado registado | B30: =B5-SUM(B25:B29)
A32: Por tipo de PA
A33: Tipo de PA | B33: N.º PA | C33: Impacto Receita (€) | D33: Impacto Despesa (€)
A34: Receita | B34: =COUNTIF('Propostas de Alteração'!$H$2:$H$5001,A34) | C34: =SUMIF('Propostas de Alteração'!$H$2:$H$5001,A34,'Propostas de Alteração'!$M$2:$M$5001) | D34: =SUMIF('Propostas de Alteração'!$H$2:$H$5001,A34,'Propostas de Alteração'!$N$2:$N$5001)
A35: Despesa | B35: =COUNTIF('Propostas de Alteração'!$H$2:$H$5001,A35) | C35: =SUMIF('Propostas de Alteração'!$H$2:$H$5001,A35,'Propostas de Alteração'!$M$2:$M$5001) | D35: =SUMIF('Propostas de Alteração'!$H$2:$H$5001,A35,'Propostas de Alteração'!$N$2:$N$5001)
A36: Norma orçamental | B36: =COUNTIF('Propostas de Alteração'!$H$2:$H$5001,A36) | C36: =SUMIF('Propostas de Alteração'!$H$2:$H$5001,A36,'Propostas de Alteração'!$M$2:$M$5001) | D36: =SUMIF('Propostas de Alteração'!$H$2:$H$5001,A36,'Propostas de Alteração'!$N$2:$N$5001)
A37: Alteração a legislação avulsa | B37: =COUNTIF('Propostas de Alteração'!$H$2:$H$5001,A37) | C37: =SUMIF('Propostas de Alteração'!$H$2:$H$5001,A37,'Propostas de Alteração'!$M$2:$M$5001) | D37: =SUMIF('Propostas de Alteração'!$H$2:$H$5001,A37,'Propostas de Alteração'!$N$2:$N$5001)
A38: Autorização legislativa | B38: =COUNTIF('Propostas de Alteração'!$H$2:$H$5001,A38) | C38: =SUMIF('Propostas de Alteração'!$H$2:$H$5001,A38,'Propostas de Alteração'!$M$2:$M$5001) | D38: =SUMIF('Propostas de Alteração'!$H$2:$H$5001,A38,'Propostas de Alteração'!$N$2:$N$5001)
A40: Nota: os impactos somam apenas os valores registados; PA sem quantificação na fonte não são contabilizadas.

Sheet Listas
A1: Versão | B1: Partido | C1: Tipo de PA | D1: SN | E1: Relevância | F1: Estado | G1: Resultado | H1: Área Governativa
A2: Original | B2: PSD | C2: Receita | D2: S | E2: Alta | F2: Entregue | G2: Aprovada | H2: Presidência
A3: Substituição | B3: CH | C3: Despesa | D3: N | E3: Média | F3: Admitida | G3: Rejeitada | H3: Estado e Finanças
A4: Retirada | B4: PS | C4: Norma orçamental | E4: Baixa | F4: Substituída | G4: Prejudicada | H4: Estado e Negócios Estrangeiros
B5: IL | C5: Alteração a legislação avulsa | F5: Retirada | G5: Retirada | H5: Adjunto e Reforma do Estado
B6: L | C6: Autorização legislativa | F6: Em votação | G6: Aprovada parcialmente | H6: Assuntos Parlamentares
B7: PCP | F7: Votada | H7: Defesa Nacional
B8: CDS-PP | F8: Avocada a Plenário | H8: Administração Interna
B9: BE | H9: Justiça
B10: PAN | H10: Economia e Coesão Territorial
B11: JPP | H11: Educação, Ciência e Inovação
B12: Deputado único/não inscrito | H12: Saúde
B13: Vários | H13: Infraestruturas e Habitação
H14: Trabalho, Solidariedade e Segurança Social
H15: Ambiente e Energia
H16: Agricultura e Mar
H17: Cultura, Juventude e Desporto
H18: Transversal

Sheet Instruções
A1: Instruções de preenchimento
A2: Um registo por proposta de alteração (PA). Preencher apenas com informação constante de fontes oficiais. Quando a fonte não indicar o valor, deixar a célula em branco e referir a ausência em Observações.
A4: Campo | B4: Conteúdo | C4: Valores admissíveis / formato
A5: ID | B5: Número sequencial interno do registo. | C5: Inteiro (1, 2, 3…)
A6: N.º PA | B6: Número atribuído à PA pela Assembleia da República. | C6: Conforme publicado pela AR
A7: Data Entrada | B7: Data de entrada da PA na AR. | C7: DD/MM/AAAA
A8: Versão | B8: Versão da PA. Cada PA mantém o número original; as substituições registam-se em nova linha. | C8: Original · Substituição · Retirada
A9: Partido | B9: Grupo parlamentar ou partido proponente. | C9: PSD · CH · PS · IL · L · PCP · CDS-PP · BE · PAN · JPP · Deputado único/não inscrito · Vários
A10: Deputado/Proponente | B10: Deputado(s) subscritor(es), conforme a PA. | C10: Texto
A11: Artigo Alterado | B11: Artigo ou mapa da Proposta de Lei alterado, aditado ou eliminado. | C11: Ex.: formato «Art. n.º (alteração)», «Artigo novo», «Mapa n.º»
A12: Tipo de PA | B12: Natureza da PA. | C12: Receita · Despesa · Norma orçamental · Alteração a legislação avulsa · Autorização legislativa
A13: Tema | B13: Tema da PA. | C13: Texto (taxonomia a fixar pela DACDP)
A14: Área Governativa | B14: Área governativa abrangida. | C14: Texto, conforme a orgânica do Governo
A15: Ministério | B15: Ministério responsável pela execução. | C15: Texto, conforme a orgânica do Governo
... A27: Observações | B27: Fonte (com ligação), ausência de dados, avocação, histórico de versões e outras notas. | C27: Texto
A29: Preenchimento automático pela UPE
A30: As colunas B, C, E, F, G, L, S, T, U e V e as ligações em W são preenchidas a partir dos dados abertos da Assembleia da República em cada captura automática. As colunas X em diante são informação adicional publicada pela AR: tema, incidência, natureza e estado da PA, avocação, identificadores e ligações. As restantes colunas do modelo (D, H a K, M a R e o texto de W) são da DACDP e nunca são alteradas pela sincronização.
A32: Fontes oficiais
A33: Página do OE na COFAP | B33: https://www.parlamento.pt/sites/COM/XVIILeg/5COFAP/Paginas/OE2026.aspx
A34: Dados abertos — Orçamento do Estado | B34: https://www.parlamento.pt/Cidadania/Paginas/DAOE.aspx
A35: Painel UPE | B35: https://upe-sggov.github.io/oe2027-pa/
A36: Repositório | B36: https://github.com/upe-sggov/oe2027-pa

Sheet Registo de Consultas
A1: Data/hora | B1: Fonte | C1: Ligação | D1: Resultado da consulta | E1: N.º PA novas
A2: 2026-10-26 18:44 UTC | B2: Dados abertos da AR — ficheiro de PA da edição | C2: https://www.parlamento.pt/Cidadania/Paginas/DAOE.aspx | D2: Ficheiro OEPropostasAlteracao2026Or_json.txt: 2076 PA (2193 registos); última entrada 2025-11-07 20:00; atualizado pela AR: — | E2: 0
A3: 2026-10-26 18:41 UTC | B3: Dados abertos da AR — ficheiro de PA da edição | C3: https://www.parlamento.pt/Cidadania/Paginas/DAOE.aspx | D3: Ficheiro OEPropostasAlteracao2026Or_json.txt: 2076 PA (2193 registos); última entrada 2025-11-07 20:00; atualizado pela AR: — | E3: 2193

Sheet Calendário e Documentos
A1: Calendário oficial e documentos publicados (situação a 26/10/2026)
A3: Data | B3: Momento / Documento | C3: Fonte oficial | D3: Observações
A4: — | B4: Resultado das votações em Comissão 1.º Dia (20.11.2025) - Artigo 2.º a Artigo 62.º-A (exceto Artigo 7.º + Artigo 53.º) | C4: https://app.parlamento.pt/webutils/docs/doc.pdf?path=3tlJ2UuiPRSNFcBby0XoDS3e5ZeDrETl1J4BMwqhYfqoFkz92ae0Q%2bdq0hFumIBcM8lBg3idm7v59tZ7UtiGYBGniGroJ49sTbN4CJ02B94hI%2f1Ipc0qclbuKc70%2fY5hscIyz33S2VpGw%2fnNLKa7q7ZzrcGsstxvjeQaR5tCkn70XzYNEJYxM0oxMOhPm4zBdMizPBPqDsK2obRRm89V6ss6T1Kqv6PnVr78yWJgLqKAZn0Eyygv92JcjspWNtC3zHWp32UZKqyLjceYpPI6tbAGvPsHbLnxtgPIZM1EdDvuiB0hDO%2b9aAgQpVZjkPo2Fj59SeZqOBviTY3bTvrYnRJvgaunHVdu91IzOs5DivLwOSw8%2fhIdbWnEP0nKj1oiWqdtnLa60TU3LfciLsuuhGZ8aSFGBtcXkvgxrrQcCEU8R1gpv%2bWKlZQga4D%2f60%2bdoOxWQ4SSXCRg6IIIT5xWAsBDtjIp%2bPnaZqFBEYeJz%2fqnUHzAot0AEt2%2bzur0BljY2sInLTRbMf0K40i%2fOMgc8WRiimTzu1L%2bZ5BcZqxAk%2fqLN%2bbveVZR7wYEDEZZ1A4wat384DqvM3jdH5o5wiH6xGNn9O8bMRPHtVobyww8EMrXxo1oJc%2b%2feGG8XA9wZy2T&fich=Resultado+das+vota%c3%a7%c3%b5es+em+Comiss%c3%a3o+1.%c2%ba+Dia+(20.11.2025)+-+Artigo+2.%c2%ba+a+Artigo+62.%c2%ba-A+(exceto+Artigo+7.%c2%ba+%2b+Artigo+53.%c2%ba).pdf&Inline=true | D4: Registado no painel em 2026-10-26 18:41
A5: — | B5: Resultado de votações Plenário - Dia 21-11-2025 | C5: https://app.parlamento.pt/webutils/docs/doc.pdf?path=h3AEE%2fTTXfXK3PG%2flqS28%2fTQw%2b3xUtg5CQugXfVIlmaJFtlvfrOZ8n%2fMU2NGMh8N%2fR2080kCWHobSV3D6d%2bfzY97UBdd1y3eZTulU0LXLp1iwcr2VEU9KBgkVuw6yWIUXItj5Q1zZk4kFFM2gao%2fqAkNjqOvUYrZAYj3TFLKODnYrDbJuPrQaw6%2bf9XY%2fUEZprk%2foIpbarao7%2ffKbw5AZXkkKyTBnfr9xCcu40op8rdQvznsUT2Os9wzTFtP9%2fZjagaD%2f2gXUN4wvo8ZXgdjqM4PHlgXL1425EEjUqNpdgF4Of2z%2b7PDs3dBZ1l7njsSw5IIJhJ5KVNaMfsOKHqH2EN1uy9Y6IyD9GalZv0HZuabnuoQzK7gjqhuXpxrucL5Jq4BdYntA%2bwhytSIMc7BoXddo%2fh1NtClFZm26jaaE0Q%3d&fich=Resultado+de+vota%c3%a7%c3%b5es+-+Dia+21-11-2025.pdf&Inline=true | D5: Registado no painel em 2026-10-26 18:41
A6: — | B6: Resultado das votações em Comissão 2.º Dia (21.11.2025) - Artigo 63.º a Artigo 112.º-E | C6: https://app.parlamento.pt/webutils/docs/doc.pdf?path=Od%2fpGeJe28nrPzhuzzOtOhYYBFN%2fYYTTmKxUUwruC%2bdbPY6ds%2bwg6Ll2eK15ig2R5Z72YDL%2fB5vFmVw2ntO8Rw9y6eKXVo1Q3n8OiIMONtyGh4%2fN2HOYA9gFLOyuIVp9T2IfTqukn6316mPEgQWG%2frgZH9Wp9%2fHTfRfxTW5f9HxNJs%2flocNTrJEsIQBNy6rUJpn4kPPQoizjHEVDhwwU0QXCgmr6wwHBRKqYarpAHlD5sEx%2b5A69gWBXoobhA71JPtrgvk33GrH4P2Mr2flDkB3%2b02jHuaT9T2l8opCYec3hpngSNNK1lpPUQ46HRSCd8UVuxMZb1K5AZlC8Zij7x8%2btwqBu2sAdQYBfvic7cGO%2b4VVd2HtSKhprb4zg5Ep%2fxUl7rXNyOHV%2bCu1d9w5JbdeyzuRTapo1%2bgkFh7JbZgqYqMf7VMtUB2FGlwjCa15%2fKU%2fuQa8eJFbfvccnl6MQE4fOIqMms6wmyvxRWhDI5tluXQr%2bougfnn4wG18gzgxzVFn3amauOdZYgtW34XVQP4uCRvYVcACbSVdoifsbwM0%3d&fich=Resultado+das+vota%c3%a7%c3%b5es+em+Comiss%c3%a3o+2.%c2%ba+Dia+(21.11.2025)+-+Artigo+63.%c2%ba+a+Artigo+112.%c2%ba-E.pdf&Inline=true | D6: Registado no painel em 2026-10-26 18:41
A7: — | B7: Resultado de votações Plenário - Dia 24-11-2025 | C7: https://app.parlamento.pt/webutils/docs/doc.pdf?path=QP%2fmj2jjEuVXq6KEexux15p1q71IbATuBfM8wqhYZ5CpNPCBMmDuxHxwTkaNvgrj53vKGmFNOsB0tEM5jlBy2OcFWnnV5vfsPkzXMG86LWhkS8wWLm1N5bP%2bqeDbCCHnIZZnECUI7DpW699CqQbxgJqpcFFIpdfHrRhoAfUfS9PM9r%2bSJzsaqLrY7AaLUtsoRU7Airt9QvQUScj5YMQC57SoJxiURRy7nHQH9vz8WOeo3vQO8YxQQUrZkI%2bwsFjnhlMoKHKoqZfL01I7UNctG%2fgUJlh2Ae2Hlem3tIAUzCLRrTHpiAeisfbER8iYwgVfjBx6Bw2ONBfhwQJwKdelh5FMRv4ZOLJaj3NDYQQVZuVYzCP0Bqgls5Y0ZyvOOjvEYd6wCLvkG3bnWuSkCj7DCJuTV9dQHedc2ickZBLRNWE%3d&fich=Resultado+de+vota%c3%a7%c3%b5es+-+Dia+24-11-2025.pdf&Inline=true | D7: Registado no painel em 2026-10-26 18:41
A8: — | B8: Resultado das votações em Comissão 3.º Dia (24.11.2025) - Artigo 113.º a Artigo 134.º-A | C8: https://app.parlamento.pt/webutils/docs/doc.pdf?path=M2WHnCUQTMzeZcrUA4XH%2b24y1rUvplIWMIbpQZMB6CtTtYqJV4X%2fNiMwZ38fT%2fdAMUCpm%2fudkKrMzvGsI%2bG%2bOE9r1WMWctuS%2bZziG7aIS3blmb7H6bwH7MD%2bV40MxDFN9LKelOk29oqwIuPEQiXQ1OZ3YzOofjQX2qqyza%2bVEg46GGD8gPqbYfy%2fxon6O98iTt82Ja1u6HXXogQRSLwATG6vQy6hjv8wQtXN%2fb4%2bqFPA653dDC7xDuH8GP%2bKrsJ5TotgI0WgPk7d1hV%2fKUntjVh%2bTbDrPmU2fv0Nr9WGkL7kN79fP3%2fl9x6ZSWA8RxHRs4Di8lP4FOzMPG850SvvRzJcCQkLvDoXkawHhRaM%2fJmqmbh0yA1unOS92biwGzg4%2briVuSnrTbPUoK%2fAPnC4Kmb3uZ3jkGruFFq4%2fVPCWdcTBd%2fZcr8OUGDbo4NGdhXxYbasE%2fgVztXcLAmQtlrWAj4MAywo54ddWEz3PhrxE0b5TOuYxsQz%2f6zhPcbJH7872MltFMxjqzTclU88wIWyOQ%3d%3d&fich=Resultado+das+vota%c3%a7%c3%b5es+em+Comiss%c3%a3o+3.%c2%ba+Dia+(24.11.2025)+-+Artigo+113.%c2%ba+a+Artigo+134.%c2%ba-A.pdf&Inline=true | D8: Registado no painel em 2026-10-26 18:41
A9: — | B9: Resultado de votações Plenário - Dia 26-11-2025 | C9: https://app.parlamento.pt/webutils/docs/doc.pdf?path=YmluDq8tVVfAppT0S%2f2zbMFyhJSsfiwY9iwiH6XCTNUmF2AfiJSWleA9rMryI3gTTwwKhps%2bXcjtlX95otkE0z%2bkNDIE12YyIEt6vCA1OU6S6%2f%2fNA0KS6M7MUPFjQqlJxlh0n8T0yoHLYihY4i7k%2fAjrYBYoBmXQ4eE5tcAsYfQ1CyCS%2fWd%2fr0R0zF1VcmyTlsNNf4E3N3eD5gRkQJg0G%2fdk5hPaVI4YfsE50OUlUIq5HAS%2f9Po9VmYh97TjOx8VCckoBqw5X1h43RycNnDM43QmI8s%2bNVm4KsmRK44hDXRbgnDnkC%2ff8BiSjV2YWfdnyEy%2fj43Bwpvj9ejbenWyuYgI2a6%2fhI0y7SY2l5er6Rjll7%2bkKCrSxYqzkROCRKMizGeurIrKEjsjMRg5XFNceOT4ghjrPF2R8BmDZL3gr1lI3UWFb6%2bjPGg104muKrMo&fich=Resultado+de+vota%c3%a7%c3%b5es+-+Dia+26-11-2025.pdf&Inline=true | D9: Registado no painel em 2026-10-26 18:41
A10: — | B10: Resultado de Votações Plenário - Dia 27-11-2025 | C10: https://app.parlamento.pt/webutils/docs/doc.pdf?path=4VlLIWuUGU5Zk7CWBpQlhtKtR8XYGFr%2fqCqc954BzrL57RJR48b5mjXZu%2fLw3xmjSMvzZUCopsaeHUgG4rC1HeEfBykvVH3NrHzm2xRZAPMBoH5i4G4xX9jFRHJf3hBoboHL%2bx48uqto9CciYV49RprmgVWzGwQ2IJxgVlvsfhl9h4hHNghQXrZfH7ZniULsAuJGIVjhU1D2MDNPp9v9iIYP0vGO7Ysgb%2bLaJ6S8ArxFM6dCAXAP1CEFWyvjNPZ4LZlRM1zziqBvb2QmZz6j5D1WskPfAaHFcNQUnL4w5dyw8HQ%2f9lTTNw3YEgPEbkpEbkPLEc9oOJC%2bJr2VSkiqBl6gNpPN3NcdxaSruvp3GVk6XmaOFPgNyJ1jFMo6VJxG7MrI5TN19zjjKs62uwyNcCvwuU9flXQkEXXAjhFBcnM%3d&fich=Resultado+de+vota%c3%a7%c3%b5es+-+Dia+27-11-2025.pdf&Inline=true | D10: Registado no painel em 2026-10-26 18:41
A11: — | B11: Resultado das votações em Comissão 4.º Dia (26.11.2025) - Artigo 135.º a Artigo 139.º + Artigo 53.º + Artigo 7.º + Artigo 1.º | C11: https://app.parlamento.pt/webutils/docs/doc.pdf?path=eckHxNWxYhKzRzbyXUruWs1LbK5VX%2bNKe4oRR1j7PJ4ZcJfQdxbmIR2yLwDLssSZX3jPz7D8HgooJmpr%2fc6%2bbsI65mzSdtICkwsmFf8Jj7AtO2cbBxeTWnUr9u9Xb005u7JUX9hn6qW018ogvqyhsXhBZw6ihHtIRjy6In4JlYOkTZVImtAAjlkQLTAqe6n15AcIzfI5jnh7PMaPaVvvwmsa04ZUlhAI1flskjrAEqmb67FA%2fZxEbWMuDbHWr44%2bai3VnNQIi2AW0PvA5PHbj0TaX81%2fxpbsbZNIrh6yNIa2nwVprE2Szm8tILhnYDGmhJFfcp03cpopxb7PNRncQ5FiPRwoAqEqWtQshbZqYo%2bzHZBduu6uAGMe0jCXTQmRTd6Nptt%2fQFyKediVHeikqjuV2p77%2fwYKnMZiC3iGjWUIvWGaY44K2imfXd3Yt7szF0rIzmJx0gXAZ5bzeT%2fcYn4sHcGfgvEyAkEX%2fuQm4sw8fTV7a4g2dNVO58PWC4Q4YXKL4iD1STu5afwetphUfY1CEK9uwnfgHDLjM9JxB62x041NrH4V9BSVSJyxIIJgGalnrpO3lu6c8QY%2fGUqnYJ%2fWe84f%2fAqxg1zbPkZj9EaY9PdmdMdqhI2Uxk3BOHzICSW76KCA4mcF%2bRUL2vXf6kwaX4ljJWBVVV2GnOOuHrU%3d&fich=Resultado+das+vota%c3%a7%c3%b5es+em+Comiss%c3%a3o+4.%c2%ba+Dia+(26.11.2025)+-+Artigo+135.%c2%ba+a+Artigo+139.%c2%ba+%2b+Artigo+53.%c2%ba+%2b+Artigo+7.%c2%ba+%2b+Artigo+1.%c2%ba.pdf&Inline=true | D11: Registado no painel em 2026-10-26 18:41
A12: — | B12: Guião Comissão - Artigos 2.º a 62.º-A, exceto Artigo 7.º e 53.º | C12: https://app.parlamento.pt/webutils/docs/doc.pdf?path=BPMtsE3xe%2ftBK2SzEKzgnuPjvbPEBjZnBY815f69ejXAuz6AeTqKVY%2fFzNebieYygy8xsiMLKFRaUiQx8MbwIW1w%2f73sSHdty0Nk0sSWli%2bNeNzk7gdlHFLgNiTDfXbCRHTowX6rlBJEk%2bxDpse3%2bxZlRIKcutZN8P4c2YTxOCpWm4I1t7AhkG17MIqLe4vrc0EoF41gI7aT9vIcO%2fPD9UAFU0LxgGe4cT5f5TYgWjx1pQKrfxrMsTwU5JUBYkS6SRHkiT%2fdTNa9yrOqm1onqYiq2cIQntMZBnb58oPOh4fT0qZsdRRoTr8bOyupDL3jiSFMqA338KKxW1YfZPkjTYjqUM1RlicXANIwEYIKxh%2bLl2gfJyXf5A6Duu%2f7nAcOaqdEJr6xkc5fM1dpRAUaIgND%2ftdr1Z%2fzpWPBIINA4WqZa7db%2bAJ2isGTdAgZCNa9MSIQ690OJ34Lndf2XTDHNsXpb9IYA2%2bhPCmYTS7o5lVEVqa6TMRcPIJivt0y3OEBeSBFxXul9TTnxcnKrMdPHQ%3d%3d&fich=Gui%c3%a3o+-+1.%c2%ba+dia+-+Artigo+2.%c2%ba+a+62.%c2%ba-A+excepto+7.%c2%ba+e+53.%c2%ba.pdf&Inline=true | D12: Registado no painel em 2026-10-26 18:41
A13: — | B13: Guião - 1.º dia - Artigo 2.º a 62.º-A excepto 7.º e 53.º - consolidado | C13: https://app.parlamento.pt/webutils/docs/doc.pdf?path=vfAKDJIAEJzdAXEtHynjZTY4MYn7Jt5rARDxf%2fG9YBW2ex4gOUMenlemAt%2ffsaogmt6YRwlDgSZIqDJHDoN18AcY2Z5h7o17QI1TeSry7PmPDkX4A8k1Z1sk17mkNOAJppugPRFAOV%2fKCJ9foVD%2fDDcJVrjgTQsl7J3BkRzi%2bNZa0xVsDUC%2bvJ0Te5k6O2qhpYbCpXGTZIPxhGGRBhtKfj3gdq3ho5cVCLdepNc0hRHddHGTotry4E4MW6XuqN2X%2fTenrn5crBTaapyjTI42lDZM6HXE41r8eNQIGbki9EtQVmRsrYEDfh7FHbPzw4U%2bzIbGSAqTdYwvag26oBtuYJtgCdi%2fkI%2fXuwqjUcjDAxv%2bJeFK8AcH5zaKTLeeHZpSIhXYqwlhCCHBNjRGcOkVBiCO0r3USEmiPqQWb%2b1g06uxihHw8fx56Eo247Dd%2b32nrAR%2b%2bgU5dk3EMWWLXWYrv6UNv0tzJZXeKBGgUJk3BUKEXdKsXUFIRi66w0mITCpizx5eChAyI9vm4B3wggIlfyFPNTA4zgHBesl5AXwkpIE%3d&fich=Gui%c3%a3o+-+1.%c2%ba+dia+-+Artigo+2.%c2%ba+a+62.%c2%ba-A+excepto+7.%c2%ba+e+53.%c2%ba+-+consolidado.pdf&Inline=true | D13: Registado no painel em 2026-10-26 18:41
A14: — | B14: Guião Comissão - Artigos 63.º a 112.º-E | C14: https://app.parlamento.pt/webutils/docs/doc.pdf?path=5O9dh0WChjJVdyNDHXASYujtFIWgI3T4FS3brJ92afylVph%2bucQdaV1PVhq12X%2fLt3VKa89beYxkGtzDdVylZG2RaMjObbPeLOV5jHWkMkvyIxURsqk6O9LSBW7XwiWLfdh9FgZzyusC363gOGvjp1JXFxAz7WA7AssawhB%2b092RG5Yw3qaJ6JYRhGZqIOhJ46NTZuTDu0nZJ0nqk0imlDnaQ6enUagTnFz0i8plLDmLUQgpuG5049n5rnWw0d7qBzMENXIoe7kr6T0IznRIV98uAu6D1M9KH4cBo4VJ4E73HLoTSyWfguDLgj5MvgQtC1Mb8p4jmbhc1ld6GROpBK9pQ6bMTBYnuWqymy2K0RY9mMVW9EjuHZne7r8rwYhGR6KPrwPbeVs2s3eeoZQGowT4nrTNyY8dVwUn8fXQwbn8UW8NeGp0VGJJAF%2bNmQWY&fich=Gui%c3%a3o+-+2.%c2%ba+dia+-+Artigo+63.%c2%ba+a+112.%c2%ba-E.pdf&Inline=true | D14: Registado no painel em 2026-10-26 18:41
... A40: — | B40: Relatório UTAO n.º 20/2025 - Impacto orçamental da Proposta de Alteração n.º 1491C | C40: https://app.parlamento.pt/webutils/docs/doc.pdf?path=ZFYC%2b%2bhrN776uL4X5WdQKgBKcoRd9MipxfqBrJhz46yvDa1kBYYWkeiCW%2fN5QwtuuZEm4E7C%2bwhqKBY6mFIkZ9KQ%2bt6d1at3iP9DfCr6mFmLQPeW%2fhwXuDVnFS4TjqihVK9CmLtxm9iEpFn4mawqKynaiBz6H9AC9y4Q20ODUl40MV0uNO6N5tPD01jg8O068dQPdcvLpbtCPkDOcdRUTj2YpxAlS1NG0MX4C5jklsMTphpymVWWxnEkSZwRnUQqB8pIoIn4IMf9QrRIf3dpWhs5w%2bTIMMkbHt%2fWZMFBstkMx4Ol%2fFednMB5rmYDKGgUbE5ZYaDey%2fjAagDqpNdlbub8aG5YvyL4zzHQ2M4A%2foU%3d&fich=UTAO-Rel-20-2025-POE2026-PA-1491C.pdf&Inline=true | D40: Registado no painel em 2026-10-26 18:41

Sheet Resposta UPE
A1: Resposta da UPE ao modelo da DACDP: o que a captura automática assegura, o que exige desenvolvimento e as limitações
A2: Gerado automaticamente em 26/10/2026, 21h59 UTC a partir da informação publicada pela Assembleia da República. «Imediato»: preenchido em cada captura. «Desenvolvimento»: sugestão automática a validar pela DACDP. «Limitação»: sem fonte na AR.
A4: Campo | B4: Classificação | C4: Como se preenche | D4: Observações
A5: ID | B5: Imediato | C5: Número sequencial atribuído na exportação.
A6: N.º PA | B6: Imediato | C6: AR (dados abertos; reserva: página de cada PA). | D6: Uma PA com várias partes (120C-1, 120C-2) ocupa uma linha por parte, porque a AR as vota separadamente.
A7: Data Entrada | B7: Imediato | C7: AR: data e hora de entrada.
A8: Versão | B8: Limitação | C8: A AR não publica a ligação entre uma PA e a que ela substitui. A coluna recebe «Retirada» quando a AR publica esse estado e «Original» nos restantes casos. | D8: Confirmação pela DACDP.
A9: Partido | B9: Imediato | C9: AR: grupo(s) parlamentar(es) proponente(s). «Vários» quando há mais de um. | D9: Sigla normalizada (CDS-P → CDS-PP).
A10: Deputado/Proponente | B10: Imediato | C10: AR: deputados signatários.
A11: Artigo Alterado | B11: Imediato | C11: AR: artigo ou mapa e natureza (alteração, aditamento, eliminação).
A12: Tipo de PA | B12: Limitação | C12: Sem fonte na AR (a AR publica a natureza da PA: aditamento, substituição, eliminação, na coluna «Tipo (AR)»). | D12: Classificação da DACDP. Fase posterior: sugestão automática a validar.
A13: Tema | B13: Limitação | C13: A AR atribui um tema próprio (coluna «Tema AR»). A taxonomia da DACDP é preenchida pela DACDP.
A14: Área Governativa | B14: Desenvolvimento (fase posterior) | C14: Sem fonte na AR. O tema atribuído pela AR (coluna «Tema AR», a comissão parlamentar competente) é a aproximação disponível. A classificação por área governativa será feita numa fase posterior, com validação humana. | D14: Nesta fase, o painel e o Excel só usam variáveis dos dados abertos da AR.
A15: Ministério | B15: Desenvolvimento (fase posterior) | C15: Decorre da área governativa.
A16: Descrição Sumária | B16: Imediato (parcial) | C16: AR: título da PA tal como publicado. A DACDP pode reescrever; a UPE não substitui texto já escrito.
A17: Impacto Receita (€) | B17: Limitação | C17: Sem fonte na AR. Só existe quando a UTAO ou o proponente publicam uma estimativa. | D17: A UPE pode extrair o texto da nota justificativa do PDF de cada PA para facilitar a leitura.
A18: Impacto Despesa (€) | B18: Limitação | C18: Idem.
A19: Fonte da Estimativa | B19: Limitação | C19: Idem.
A20: Medida Anunciada (S/N) | B20: Limitação | C20: Sem fonte na AR. Ligação à folha «Medidas Anunciadas» pelo n.º da PA, a cargo da DACDP.
A21: Relevância | B21: Limitação | C21: Juízo da DACDP.
A22: Necessita Análise Jurídica (S/N) | B22: Limitação | C22: Juízo da DACDP.
A23: Estado | B23: Imediato | C23: AR: estado publicado (coluna «Estado (AR)»); a coluna «Estado» recebe o estado da AR, que é o único verificável. | D23: A lista do modelo (Entregue, Admitida, …) não coincide com os estados que a AR publica.
A24: Resultado Votação | B24: Imediato | C24: AR: resultado da última votação, nos valores do modelo (Aprovada, Rejeitada, Prejudicada, Retirada, Aprovada parcialmente).
A25: Sentido de Voto | B25: Imediato | C25: AR: sentido de voto de cada grupo parlamentar, no formato do modelo. | D25: Inclui os deputados únicos representantes de partido.
A26: Data Votação | B26: Imediato | C26: AR: data da última votação.
A27: Observações | B27: Imediato (parcial) | C27: A UPE acrescenta a ligação à ficha da PA e ao PDF, a avocação a Plenário e a nota «ausente da fonte» quando a PA deixa de constar da publicação. O resto é da DACDP.
A28: Medidas Anunciadas (folha) | B28: Limitação | C28: Fora das fontes da AR: fica a cargo da DACDP. A UPE preserva o conteúdo nas sincronizações.
A29: Ponto de Situação (folha) | B29: Imediato | C29: Fórmulas do modelo, alargadas a 5 000 linhas; situação na fonte oficial preenchida pela captura.
A30: Registo de Consultas (folha) | B30: Imediato | C30: Cada captura automática regista fonte, momento, resultado e PA novas.
A31: Calendário e Documentos (folha) | B31: Imediato | C31: Calendário oficial da AR e documentos publicados na página da COFAP.
